Workbook
Name a: '[1]QUOTATION BREAKDOWN (2)'!#REF!
Name contract: '01 PEK-001 Pen Eak'!#REF!
Name contract: '02 JPP-001 งานชัยนาท'!#REF!
Name contract: '03 TG-002 เปลี่ยน ACB'!#REF!
Name contract: '04 PKE-001 ติดตั้งลากสาย RASA1'!#REF!
Name contract: '05 QMP-001งาน PM 315kVA'!#REF!
Name contract: '06 UNT-001 รพ.ภัทรเวช'!#REF!
Name contract: '07 SUT-001 บ้านห้วยขวาง'!#REF!
Name contract: '08 PKE-002 ติดตั้งพัดลมระบายอาก'!#REF!
Name contract: '09 JEP-2601-001'!#REF!
Name contract: '10 UNT-2601-001 รพ.ภัทรเวช (2)'!#REF!
Name contract: '11 TMD-2601-001'!#REF!
Name contract: '12 TMD-2601-002'!#REF!
Name contract: '13 JPP-2601-001'!#REF!
Name contract: '14 TMD-2601-003'!#REF!
Name contract: '15 RACH36'!#REF!
Name contract: '20 SOL-264 02'!#REF!
Name contract: '21 TMD-004'!#REF!
Name contract: '22 TMD-005'!#REF!
Name contract: '23 TMD-006'!#REF!
Name contract: '24 POM-007'!#REF!
Name contract: 'MC-002 Udonthani'!#REF!
Name contract: 'PC-004 อาคาร D'!#REF!
Name contract: 'PC-005 SHIN FONG'!#REF!
Name contract: 'PC-006 JOWLE'!#REF!
Name contract: 'PC-007 บ้านลาดกระบัง'!#REF!
Name contract: 'PC-008 JINHAI'!#REF!
Name contract: 'PC-009 BHP'!#REF!
Name contract: 'PPC-001 Nestle'!#REF!
Name contract: 'XP-001 งานนครนายก'!#REF!
Name contract: ค่าใช้จ่ายออฟฟิศ!#REF!
Name contract: '[2]CMS REV1'!$L$3
Name customs: #REF!
Name di: #REF!
Name disc: #REF!
Name DISCOUNT: #REF!
Name equip: #REF!
Name In: '[1]QUOTATION BREAKDOWN (2)'!#REF!
Name k: [3]offer!$N$7
Name kk: [3]offer!$N$6
Name material: #REF!
Name Pro: #REF!
Name span: #REF!
Name stock: #REF!

Sheet JPP Code 
A2: No. | B2: Description | D2: Code
A4: 1 | B4: 10 | C4: MATERIALS | D4: 10
A5: 2 | B5: 20 | C5: SUB CONTRACTOR | D5: 20
A6: 3 | B6: 30 | C6: HEAVY EQUIPMENT | D6: 30
A7: 4 | B7: 40 | C7: RENTAL | D7: 40
A8: 5 | B8: 50 | C8: STAFF EXPENSE (Salary) | D8: 50
A9: 6 | B9: 60 | C9: OFFICE EXPENSE | D9: 60
A10: 7 | B10: 70 | C10: ENTERTAIN | D10: 70
A11: 8 | B11: 80 | C11: MISCELLANEOUS | D11: 80
A13: Code ทางด้านบัญชี (ในอนาคต)

Sheet Money forecast
C1: วันที่เงินจะเข้า
A2: 1 | B2: เงินสดย่อย | C2: 46152 | D2: 15000 | E2: 20000 | H2: =SUM(D2:G2) -> 35000
A3: 2 | B3: เบิกเงินงานสระบุรี | C3: 46157 | D3: 90164.83 | H3: =SUM(D3:G3) -> 90164.83
A4: 3 | H4: =SUM(D4:G4) -> 0
A5: 4 | H5: =SUM(D5:G5) -> 0
A6: 5 | H6: =SUM(D6:G6) -> 0
A7: 6 | H7: =SUM(D7:G7) -> 0
A8: 7 | H8: =SUM(D8:G8) -> 0
A9: 8 | B9: เงินเบิกเมเดนชา | C9: 46192 | D9: 20000 | E9: 36000 | F9: 12795 | H9: =SUM(D9:G9) -> 68795
G11: ยอดรวม | H11: =SUM(H2:H10) -> 193959.83
G12: กระแสเงินสด

Sheet Project Onhand
A2: Item No. | B2: Job No. | C2: Client Name | D2: Work Description | E2: Contract Price | F2: Start Date | G2: Finish Date | H2: % Complete | I2: Profit | K2: Invoice Oct 2025 | N2: % | O2: 46082 | P2: % | Q2: 46113 | R2: % | S2: 46143 | T2: % | U2: 46174 | V2: % | W2: 46204 | X2: % | Y2: 46235 | Z2: % | AA2: 46266 | AB2: % | AC2: 46296 | AD2: % | AE2: 46327 | AF2: % | AG2: 46357 | AH2: % | AI2: 46388 | AJ2: % | AK2: 46419 | AL2: % | AM2: 46447 | AN2: % | AO2: 46478
O3: =SUM(O4:O19) -> 740100.93 | Q3: =SUM(Q4:Q19) -> 873629.6 | S3: =SUM(S4:S19) -> 593927.47 | U3: =SUM(U4:U19) -> 85000 | W3: =SUM(W4:W19) -> 85000 | Y3: =SUM(Y4:Y19) -> 0 | AA3: =SUM(AA4:AA19) -> 0 | AC3: =SUM(AC4:AC19) -> 0 | AE3: =SUM(AE4:AE19) -> 0 | AG3: =SUM(AG4:AG19) -> 0 | AI3: =SUM(AI4:AI19) -> 0 | AK3: =SUM(AK4:AK19) -> 0 | AM3: =SUM(AM4:AM19) -> 0 | AO3: =SUM(AO4:AO19) -> 0
A4: 1 | C4: TMD | D4: งานติดตั้งระบบไฟฟ้า ระบบแจ้งเตือนเพลิงไหม้ Depot ORL MWS | E4: 610770 | F4: 46082 | G4: 46122 | H4: 0.8 | I4: 0.9 | J4: =I4*C4 -> #VALUE! | K4: 0.9 | L4: =K4*E4 -> 549693 | N4: 0.5 | O4: =N4*E4 -> 305385 | P4: 0.4 | Q4: =P4*$E$4 -> 244308 | R4: 0.1 | S4: =R4*$E$4 -> 61077 | U4: =T4*$E$4 -> 0 | W4: =V4*$E$4 -> 0 | Y4: =X4*$E$4 -> 0 | AA4: =Z4*$E$4 -> 0 | AC4: =AB4*$E$4 -> 0 | AE4: =AD4*$E$4 -> 0 | AG4: =AF4*$E$4 -> 0 | AI4: =AH4*$E$4 -> 0 | AK4: =AJ4*$E$4 -> 0 | AM4: =AL4*$E$4 -> 0 | AO4: =AN4*$E$4 -> 0
A5: 2 | C5: PK-ESS | D5: งาน Turnkey งานติดตั้งระบบไฟฟ้า UPS โรงพยาบาลการไฟฟ้าสามเสน | E5: 850000 | F5: 46101 | G5: 46172 | H5: 0.1 | I5: 0.3 | J5: =I5*C5 -> #VALUE! | K5: 0.3 | L5: =K5*E5 -> 255000 | O5: =N5*$E$5 -> 0 | P5: 0.3 | Q5: =P5*$E$5 -> 255000 | R5: 0.5 | S5: =R5*$E$5 -> 425000 | T5: 0.1 | U5: =T5*$E$5 -> 85000 | V5: 0.1 | W5: =V5*$E$5 -> 85000 | Y5: =X5*$E$5 -> 0 | AA5: =Z5*$E$5 -> 0 | AC5: =AB5*$E$5 -> 0 | AE5: =AD5*$E$5 -> 0 | AG5: =AF5*$E$5 -> 0 | AI5: =AH5*$E$5 -> 0 | AK5: =AJ5*$E$5 -> 0 | AM5: =AL5*$E$5 -> 0 | AO5: =AN5*$E$5 -> 0
A6: 3 | C6: Khun Ma | D6: งานติดตั้งระบบโซล่าร์เซลล์ บนหลังคา 10kW + Battery 21kW | E6: 400000 | F6: 46118 | G6: 46118 | H6: 1 | I6: 1 | J6: =I6*C6 -> #VALUE! | K6: 1 | L6: =K6*E6 -> 400000 | N6: 0.5 | O6: =N6*$E$6 -> 200000 | P6: 0.5 | Q6: =P6*$E$6 -> 200000 | S6: =R6*$E$6 -> 0 | U6: =T6*$E$6 -> 0 | W6: =V6*$E$6 -> 0 | Y6: =X6*$E$6 -> 0 | AA6: =Z6*$E$6 -> 0 | AC6: =AB6*$E$6 -> 0 | AE6: =AD6*$E$6 -> 0 | AG6: =AF6*$E$6 -> 0 | AI6: =AH6*$E$6 -> 0 | AK6: =AJ6*$E$6 -> 0 | AM6: =AL6*$E$6 -> 0 | AO6: =AN6*$E$6 -> 0
A7: 4 | C7: Khun Ken | D7: งานเพิ่มแบตเตอรี่สำหรับโซล่าร์เซลล์บ้าน | E7: 220000 | F7: 46108 | G7: 46132 | H7: 0 | I7: 1 | J7: =I7*C7 -> #VALUE! | K7: 1 | L7: =K7*E7 -> 220000 | N7: 0.5 | O7: 112149.53 | R7: 0.5 | S7: =E7-O7 -> 107850.47 | U7: =T7*$E$7 -> 0 | W7: =V7*$E$7 -> 0 | Y7: =X7*$E$7 -> 0 | AA7: =Z7*$E$7 -> 0 | AC7: =AB7*$E$7 -> 0 | AE7: =AD7*$E$7 -> 0 | AG7: =AF7*$E$7 -> 0 | AI7: =AH7*$E$7 -> 0 | AK7: =AJ7*$E$7 -> 0 | AM7: =AL7*$E$7 -> 0 | AO7: =AN7*$E$7 -> 0
A8: 5 | C8: Khun Koson | D8: งานติดตั้งระบบโซล่าร์เซลล์ บนหลังคา 17.68kW | E8: 235000 | F8: 46108 | G8: 46132 | H8: 1 | I8: 1 | J8: =I8*C8 -> #VALUE! | K8: 1 | L8: =K8*E8 -> 235000 | N8: 0.5 | O8: =N8*$E$7 -> 110000 | P8: 0.5 | Q8: 125000 | S8: =R8*$E$7 -> 0 | U8: =T8*$E$7 -> 0 | W8: =V8*$E$7 -> 0 | Y8: =X8*$E$7 -> 0 | AA8: =Z8*$E$7 -> 0 | AC8: =AB8*$E$7 -> 0 | AE8: =AD8*$E$7 -> 0 | AG8: =AF8*$E$7 -> 0 | AI8: =AH8*$E$7 -> 0 | AK8: =AJ8*$E$7 -> 0 | AM8: =AL8*$E$7 -> 0 | AO8: =AN8*$E$7 -> 0
A9: 6 | C9: กฤชณรงค์ธัญกิจ | D9: งานเปลี่ยนหางปลา สาย SAC 95 | E9: 41888 | F9: 46108 | G9: 46108 | H9: 1 | I9: 1 | J9: =I9*C9 -> #VALUE! | K9: 1 | L9: =K9*E9 -> 41888 | N9: 0.3 | O9: =N9*$E$9 -> 12566.4 | P9: 0.7 | Q9: =E9-O9 -> 29321.6 | S9: =R9*$E$9 -> 0 | U9: =T9*$E$9 -> 0 | W9: =V9*$E$9 -> 0 | Y9: =X9*$E$9 -> 0 | AA9: =Z9*$E$9 -> 0 | AC9: =AB9*$E$9 -> 0 | AE9: =AD9*$E$9 -> 0 | AG9: =AF9*$E$9 -> 0 | AI9: =AH9*$E$9 -> 0 | AK9: =AJ9*$E$9 -> 0 | AM9: =AL9*$E$9 -> 0 | AO9: =AN9*$E$9 -> 0
A10: 7 | C10: TMD | D10: งานติดตั้งระบบไฟฟ้า Dangerous Waste - General Waste | E10: 339693.72 | F10: 46082 | G10: 46122 | H10: 0.5 | I10: 0.2 | J10: =I10*C10 -> #VALUE! | K10: 0.2 | L10: =K10*E10 -> 67938.744 | O10: =N10*$E$11 -> 0 | P10: 0.2 | Q10: =P10*$E$11 -> 20000 | R10: 0 | S10: =R10*$E$11 -> 0 | U10: =T10*$E$11 -> 0 | W10: =V10*$E$11 -> 0 | Y10: =X10*$E$11 -> 0 | AA10: =Z10*$E$11 -> 0 | AC10: =AB10*$E$11 -> 0 | AE10: =AD10*$E$11 -> 0 | AG10: =AF10*$E$11 -> 0 | AI10: =AH10*$E$11 -> 0 | AK10: =AJ10*$E$11 -> 0 | AM10: =AL10*$E$11 -> 0 | AO10: =AN10*$E$11 -> 0
A11: 8 | C11: TMD | D11: งานติดตั้งระบบไฟฟ้า Dangerous Goods | E11: 100000 | F11: 46082 | G11: 46122 | H11: 0 | I11: 0 | J11: =I11*C11 -> #VALUE! | K11: 0 | L11: =K11*E11 -> 0 | O11: =N11*$E$11 -> 0 | Q11: =P11*$E$11 -> 0 | R11: 0 | S11: =R11*$E$11 -> 0 | U11: =T11*$E$11 -> 0 | W11: =V11*$E$11 -> 0 | Y11: =X11*$E$11 -> 0 | AA11: =Z11*$E$11 -> 0 | AC11: =AB11*$E$11 -> 0 | AE11: =AD11*$E$11 -> 0 | AG11: =AF11*$E$11 -> 0 | AI11: =AH11*$E$11 -> 0 | AK11: =AJ11*$E$11 -> 0 | AM11: =AL11*$E$11 -> 0 | AO11: =AN11*$E$11 -> 0
A12: 9 | C12: วังสระปทุม | D12: งานติดตั้งโซล่าร์เซลล์ 10kW | E12: 874000 | F12: 46148 | G12: 46203 | H12: 0 | J12: =I12*C12 -> #VALUE! | L12: =K12*E12 -> 0 | O12: =N12*$E$12 -> 0 | Q12: =P12*$E$12 -> 0 | S12: =R12*$E$12 -> 0 | U12: =T12*$E$12 -> 0 | W12: =V12*$E$12 -> 0 | Y12: =X12*$E$12 -> 0 | AA12: =Z12*$E$12 -> 0 | AC12: =AB12*$E$12 -> 0 | AE12: =AD12*$E$12 -> 0 | AG12: =AF12*$E$12 -> 0 | AI12: =AH12*$E$12 -> 0 | AK12: =AJ12*$E$12 -> 0 | AM12: =AL12*$E$12 -> 0 | AO12: =AN12*$E$12 -> 0
A13: 10 | C13: บ้านคุณเม | D13: งานติดตั้งโซล่าร์เซลล์ 5kW | E13: 122000 | F13: 46148 | G13: 46203 | H13: 0 | J13: =I13*C13 -> #VALUE! | L13: =K13*E13 -> 0 | O13: =N13*$E$12 -> 0 | Q13: =P13*$E$12 -> 0 | S13: =R13*$E$12 -> 0 | U13: =T13*$E$12 -> 0 | W13: =V13*$E$12 -> 0 | Y13: =X13*$E$12 -> 0 | AA13: =Z13*$E$12 -> 0 | AC13: =AB13*$E$12 -> 0 | AE13: =AD13*$E$12 -> 0 | AG13: =AF13*$E$12 -> 0 | AI13: =AH13*$E$12 -> 0 | AK13: =AJ13*$E$12 -> 0 | AM13: =AL13*$E$12 -> 0 | AO13: =AN13*$E$12 -> 0
A14: 11 | J14: =I14*C14 -> 0 | L14: =K14*E14 -> 0 | O14: =N14*$E$12 -> 0 | Q14: =P14*$E$12 -> 0 | S14: =R14*$E$12 -> 0 | U14: =T14*$E$12 -> 0 | W14: =V14*$E$12 -> 0 | Y14: =X14*$E$12 -> 0 | AA14: =Z14*$E$12 -> 0 | AC14: =AB14*$E$12 -> 0 | AE14: =AD14*$E$12 -> 0 | AG14: =AF14*$E$12 -> 0 | AI14: =AH14*$E$12 -> 0 | AK14: =AJ14*$E$12 -> 0 | AM14: =AL14*$E$12 -> 0 | AO14: =AN14*$E$12 -> 0
A15: 12 | J15: =I15*C15 -> 0 | L15: =K15*E15 -> 0 | O15: =N15*$E$12 -> 0 | Q15: =P15*$E$12 -> 0 | S15: =R15*$E$12 -> 0 | U15: =T15*$E$12 -> 0 | W15: =V15*$E$12 -> 0 | Y15: =X15*$E$12 -> 0 | AA15: =Z15*$E$12 -> 0 | AC15: =AB15*$E$12 -> 0 | AE15: =AD15*$E$12 -> 0 | AG15: =AF15*$E$12 -> 0 | AI15: =AH15*$E$12 -> 0 | AK15: =AJ15*$E$12 -> 0 | AM15: =AL15*$E$12 -> 0 | AO15: =AN15*$E$12 -> 0
A16: 13 | J16: =I16*C16 -> 0 | L16: =K16*E16 -> 0 | O16: =N16*$E$12 -> 0 | Q16: =P16*$E$12 -> 0 | S16: =R16*$E$12 -> 0 | U16: =T16*$E$12 -> 0 | W16: =V16*$E$12 -> 0 | Y16: =X16*$E$12 -> 0 | AA16: =Z16*$E$12 -> 0 | AC16: =AB16*$E$12 -> 0 | AE16: =AD16*$E$12 -> 0 | AG16: =AF16*$E$12 -> 0 | AI16: =AH16*$E$12 -> 0 | AK16: =AJ16*$E$12 -> 0 | AM16: =AL16*$E$12 -> 0 | AO16: =AN16*$E$12 -> 0
A17: 14 | J17: =I17*C17 -> 0 | L17: =K17*E17 -> 0 | O17: =N17*$E$12 -> 0 | Q17: =P17*$E$12 -> 0 | S17: =R17*$E$12 -> 0 | U17: =T17*$E$12 -> 0 | W17: =V17*$E$12 -> 0 | Y17: =X17*$E$12 -> 0 | AA17: =Z17*$E$12 -> 0 | AC17: =AB17*$E$12 -> 0 | AE17: =AD17*$E$12 -> 0 | AG17: =AF17*$E$12 -> 0 | AI17: =AH17*$E$12 -> 0 | AK17: =AJ17*$E$12 -> 0 | AM17: =AL17*$E$12 -> 0 | AO17: =AN17*$E$12 -> 0
A18: 15 | J18: =I18*C18 -> 0 | L18: =K18*E18 -> 0 | O18: =N18*$E$18 -> 0 | Q18: =P18*$E$18 -> 0 | S18: =R18*$E$18 -> 0 | U18: =T18*$E$18 -> 0 | W18: =V18*$E$18 -> 0 | Y18: =X18*$E$18 -> 0 | AA18: =Z18*$E$18 -> 0 | AC18: =AB18*$E$18 -> 0 | AE18: =AD18*$E$18 -> 0 | AG18: =AF18*$E$18 -> 0 | AI18: =AH18*$E$18 -> 0 | AK18: =AJ18*$E$18 -> 0 | AM18: =AL18*$E$18 -> 0 | AO18: =AN18*$E$18 -> 0
A19: 16 | J19: =I19*C19 -> 0 | L19: =K19*E19 -> 0 | O19: =N19*$E$19 -> 0 | Q19: =P19*$E$19 -> 0 | S19: =R19*$E$19 -> 0 | U19: =T19*$E$19 -> 0 | W19: =V19*$E$19 -> 0 | Y19: =X19*$E$19 -> 0 | AA19: =Z19*$E$19 -> 0 | AC19: =AB19*$E$19 -> 0 | AE19: =AD19*$E$19 -> 0 | AG19: =AF19*$E$19 -> 0 | AI19: =AH19*$E$19 -> 0 | AK19: =AJ19*$E$19 -> 0 | AM19: =AL19*$E$19 -> 0 | AO19: =AN19*$E$19 -> 0
E20: =SUM(E4:E19) -> 3793351.7 | J20: =SUM(J4:J19) -> #VALUE! | L20: =SUM(L4:L19) -> 1769519.7 | O20: =SUM(O4:O19) -> 740100.93 | Q20: =Q8+Q6+Q5 -> 580000
M21: ค่าใช้จ่าย | O21: =SUM(O22:O34) -> 501799.22 | Q21: =SUM(Q22:Q32) -> 1000113.8
G22: เงินสด | H22: 342422.65 | J22: 299904 | L22: 299904 | M22: รัชดา 36 | N22: 0.7 | O22: =L22*0.7 -> 209932.8 | P22: บ้านเคน | Q22: =230050*0.7 -> 161035
J23: 85000 | L23: 85000 | M23: Aof | N23: 0.5 | O23: =L23*0.5 -> 42500 | P23: Aof | Q23: 43000
H24: =H22-O21 -> -159376.57 | M24: เงินเดือน | O24: 130000 | P24: ออฟฟิศ&เงินเดือน | Q24: 150000
J25: 157888.08 | L25: 157888.08 | M25: Overwash | N25: 0.3 | O25: =L25*0.3 -> 47366.424 | P25: APT | Q25: =480000*0.15 -> 72000
J26: 480000 | L26: 480000 | M26: อั๋น | N26: 0.15 | O26: =N26*L26 -> 72000 | P26: ท่อ | Q26: 44344.55
P27: APT | Q27: 49920
P28: APT | Q28: 124800
P29: GTI | Q29: =809.78+1318.24+118258.17+224628.1 -> 345014.29
P30: ค่าพุกและสตัด | Q30: 10000
P33: ยอดที่ค้างจ่าย | Q33: =Q25+Q24+Q22+Q30 -> 393035
P34: ยอดเก็บเงิน | Q34: =Q7+Q4+Q9 -> 273629.6

Sheet PC-009 BHP
B1: Factory/Company | C1: PROCHAIN | H1: Start Date | I1: 45833
B2: Project Name | C2: BHP Factory | H2: Sale Up Date
B3: Job Code. | C3: =C52 -> 0
B4: Quotation No. | E4: PROJECT BUDGET RECORD | H4: INVOICE (%) | I4: 0 | AA4: 45811 | AB4: 45812 | AC4: 45813 | AD4: 45814 | AE4: 45815 | AF4: 45816 | AG4: 45817 | AH4: 45818 | AI4: 45819 | AJ4: 45820 | AK4: 45821 | AL4: 45822 | AM4: 45823 | AN4: 45824 | AO4: 45825 | AP4: 45826 | AQ4: 45827 | AR4: 45828 | AS4: 45829 | AT4: 45830 | AU4: 45831 | AV4: 45832 | AW4: 45833 | AX4: 45834 | AY4: 45835 | AZ4: 45836 | BA4: 45837 | BB4: 45838 | BE4: 45839 | BF4: 45840 | BG4: 45841 | BH4: 45842 | BI4: 45843 | BJ4: 45844 | BK4: 45845 | BL4: 45846 | BM4: 45847 | BN4: 45848 | BO4: 45849 | BP4: 45850 | BQ4: 45851 | BR4: 45852 | BS4: 45853 | BT4: 45854 | BU4: 45855 | BV4: 45856 | BW4: 45857
B5: Contract Price | C5: =C53 -> 0
B6: Budget Price | C6: =F64 -> 6880000 | Z6: 100
B7: PROFIT | C7: =(C5-C6)/C5 -> #DIV/0! | D7: ACTUAL | E7: 1 | U7: No. | V7: Name | W7: Salary | X7: S per Day | Y7: ค่าโทรศัพท์ | Z7: ค่าอื่นๆ | AA7: =SUM(AA8:AA31) -> 4 | AB7: =SUM(AB8:AB31) -> 3 | AC7: =SUM(AC8:AC31) -> 3 | AD7: =SUM(AD8:AD31) -> 3 | AE7: =SUM(AE8:AE31) -> 3 | AF7: =SUM(AF8:AF31) -> 0 | AG7: =SUM(AG8:AG31) -> 11 | AH7: =SUM(AH8:AH31) -> 11 | ... BB7: =SUM(BB8:BB31) -> 0 | BE7: =SUM(BE8:BE31) -> 0 | BF7: =SUM(BF8:BF31) -> 0 | BG7: =SUM(BG8:BG31) -> 0 | BH7: =SUM(BH8:BH31) -> 0 | BI7: =SUM(BI8:BI31) -> 0 | BJ7: =SUM(BJ8:BJ31) -> 0 | BK7: =SUM(BK8:BK31) -> 0 | BL7: =SUM(BL8:BL31) -> 0 | ... BW7: =SUM(BW8:BW31) -> 0
B8: No. | C8: Vendor Name | D8: Material Number | E8: Description | F8: Text/Quo.No. | G8: Amount | H8: Updated By | I8: Date | J8: PO | U8: 1 | V8: พี่เอ็ก | W8: 31500 | X8: 1050 | Y8: 1400 | AG8: 1 | AH8: 1 | AI8: 1 | AJ8: 1 | AK8: 1 | AL8: 1 | AN8: 1 | AO8: 1 | AP8: 1 | AQ8: 1 | AR8: 1 | AS8: 1 | AU8: 1 | AV8: 1 | BC8: =SUM(AA8:BB8) -> 14 | BD8: =(BC8*X8)+Y8+Z8 -> 16100
U9: 2 | V9: เอลฟ์ | W9: 21300 | X9: 710 | Y9: 1400 | Z9: 2000 | AA9: 1 | AG9: 1 | AH9: 1 | AI9: 1 | AJ9: 1 | AK9: 1 | AL9: 1 | AN9: 1 | AO9: 1 | AP9: 1 | AQ9: 1 | AR9: 1 | AS9: 1 | AU9: 1 | AV9: 1 | BC9: =SUM(AA9:BB9) -> 15 | BD9: =(BC9*X9)+Y9+Z9 -> 14050
B10: 1 | C10: ค่าดำเนินการติดตั้งมิเตอร์การไฟฟ้า | D10: 80 | E10: ค่าดำเนินการ | G10: 15000 | H10: K.Kowit | I10: 45858 | U10: 3 | V10: เฮียนิ้ง | W10: 18500 | X10: 616.66667 | Z10: =$Z$6*BC11 -> 1400 | BC10: =SUM(AA10:BB10) -> 0 | BD10: =(BC10*X10)+Y10+Z10 -> 1400
B11: 2 | U11: 4 | V11: หนึ่ง | W11: 15000 | X11: 500 | Z11: =$Z$6*BC12 -> 1400 | AG11: 1 | AH11: 1 | AI11: 1 | AJ11: 1 | AK11: 1 | AL11: 1 | AN11: 1 | AO11: 1 | AP11: 1 | AQ11: 1 | AR11: 1 | AS11: 1 | AU11: 1 | AV11: 1 | BC11: =SUM(AA11:BB11) -> 14 | BD11: =(BC11*X11)+Y11+Z11 -> 8400
B12: 3 | U12: 5 | V12: แอล | W12: 14000 | X12: 466.66667 | Z12: =$Z$6*BC13 -> 0 | AG12: 1 | AH12: 1 | AI12: 1 | AJ12: 1 | AK12: 1 | AL12: 1 | AN12: 1 | AO12: 1 | AP12: 1 | AQ12: 1 | AR12: 1 | AS12: 1 | AU12: 1 | AV12: 1 | BC12: =SUM(AA12:BB12) -> 14 | BD12: =(BC12*X12)+Y12+Z12 -> 6533.3333
B13: 4 | U13: 6 | V13: เวฟ | W13: 14000 | X13: 466.66667 | Z13: =$Z$6*BC14 -> 0 | BC13: =SUM(AA13:BB13) -> 0 | BD13: =(BC13*X13)+Y13+Z13 -> 0
B14: 5 | U14: 78 | V14: บาส | W14: 13000 | X14: 433.33333 | Z14: =$Z$6*BC15 -> 0 | BC14: =SUM(AA14:BB14) -> 0 | BD14: =(BC14*X14)+Y14+Z14 -> 0
B15: 6 | U15: 8 | V15: พี่มิ้ว(แอดมิน) | W15: 14000 | X15: 466.66667 | Z15: =$Z$6*BC16 -> 0 | BC15: =SUM(AA15:BB15) -> 0 | BD15: =(BC15*X15)+Y15+Z15 -> 0
B16: 7 | U16: 9 | V16: พี่ดี๋ | W16: 50000 | X16: 1666.6667 | Z16: =$Z$6*BC17 -> 1400 | BC16: =SUM(AA16:BB16) -> 0 | BD16: =(BC16*X16)+Y16+Z16 -> 1400
B17: 8 | U17: 10 | V17: พี่เจมส์ | W17: 17000 | X17: 566.66667 | Z17: =$Z$6*BC18 -> 0 | AG17: 1 | AH17: 1 | AI17: 1 | AJ17: 1 | AK17: 1 | AL17: 1 | AN17: 1 | AO17: 1 | AP17: 1 | AQ17: 1 | AR17: 1 | AS17: 1 | AU17: 1 | AV17: 1 | BC17: =SUM(AA17:BB17) -> 14 | BD17: =(BC17*X17)+Y17+Z17 -> 7933.3333
B18: 9 | U18: 11 | V18: อั้ม | W18: 20000 | X18: 666.66667 | Z18: =$Z$6*BC19 -> 1400 | BC18: =SUM(AA18:BB18) -> 0 | BD18: =(BC18*X18)+Y18+Z18 -> 1400
B19: 10 | U19: 12 | V19: พี่เต้ย (รายวัน) | W19: 4950 | X19: 450 | Z19: =$Z$6*BC20 -> 0 | AG19: 1 | AH19: 1 | AI19: 1 | AJ19: 1 | AK19: 1 | AL19: 1 | AN19: 1 | AO19: 1 | AP19: 1 | AQ19: 1 | AR19: 1 | AS19: 1 | AU19: 1 | AV19: 1 | BC19: =SUM(AA19:BB19) -> 14 | BD19: =(BC19*X19)+Y19+Z19 -> 6300
B20: 11 | U20: 13 | V20: จิว(ฝึกงาน) | W20: 3300 | X20: 300 | Z20: =$Z$6*BC21 -> 0 | BC20: =SUM(AA20:BB20) -> 0 | BD20: =(BC20*X20)+Y20+Z20 -> 0
B21: 12 | U21: 14 | V21: บอล(ฝึกงาน300) | W21: 3300 | X21: 300 | Z21: =$Z$6*BC22 -> 0 | BC21: =SUM(AA21:BB21) -> 0 | BD21: =(BC21*X21)+Y21+Z21 -> 0
B22: 13 | U22: 15 | V22: มุก(ฝึกงาน) | W22: 3300 | X22: 300 | Z22: =$Z$6*BC23 -> 0 | BC22: =SUM(AA22:BB22) -> 0 | BD22: =(BC22*X22)+Y22+Z22 -> 0
B23: 14 | U23: 16 | V23: เบนซ์(ฝึกงาน300) | W23: 3300 | X23: 300 | Z23: =$Z$6*BC24 -> 1900 | BC23: =SUM(AA23:BB23) -> 0 | BD23: =(BC23*X23)+Y23+Z23 -> 1900
B24: 15 | U24: 17 | V24: เต๋า(ฝึกงาน) | W24: 2700 | X24: 300 | Z24: =$Z$6*BC25 -> 1900 | AA24: 1 | AB24: 1 | AC24: 1 | AD24: 1 | AE24: 1 | AG24: 1 | AH24: 1 | AI24: 1 | AJ24: 1 | AK24: 1 | AL24: 1 | AN24: 1 | AO24: 1 | AP24: 1 | AQ24: 1 | AR24: 1 | AS24: 1 | AU24: 1 | AV24: 1 | BC24: =SUM(AA24:BB24) -> 19 | BD24: =(BC24*X24)+Y24+Z24 -> 7600
B25: 16 | U25: 18 | V25: เฟียส(ฝึกงาน) | W25: 2200 | X25: 200 | Z25: =$Z$6*BC26 -> 1900 | AA25: 1 | AB25: 1 | AC25: 1 | AD25: 1 | AE25: 1 | AG25: 1 | AH25: 1 | AI25: 1 | AJ25: 1 | AK25: 1 | AL25: 1 | AN25: 1 | AO25: 1 | AP25: 1 | AQ25: 1 | AR25: 1 | AS25: 1 | AU25: 1 | AV25: 1 | BC25: =SUM(AA25:BB25) -> 19 | BD25: =(BC25*X25)+Y25+Z25 -> 5700
B26: 17 | U26: 19 | V26: ฟลุ๊ค(ฝึกงาน) | W26: 1440 | X26: 180 | Z26: =$Z$6*BC27 -> 0 | AA26: 1 | AB26: 1 | AC26: 1 | AD26: 1 | AE26: 1 | AG26: 1 | AH26: 1 | AI26: 1 | AJ26: 1 | AK26: 1 | AL26: 1 | AN26: 1 | AO26: 1 | AP26: 1 | AQ26: 1 | AR26: 1 | AS26: 1 | AU26: 1 | AV26: 1 | BC26: =SUM(AA26:BB26) -> 19 | BD26: =(BC26*X26)+Y26+Z26 -> 3420
B27: 18 | U27: 20 | V27: เจมส์(ฝึกงาน) | W27: 2160 | X27: 180 | Z27: =$Z$6*BC28 -> 1400 | BC27: =SUM(AA27:BB27) -> 0 | BD27: =(BC27*X27)+Y27+Z27 -> 1400
B28: 19 | U28: 21 | V28: นาย(ฝึกงาน) | W28: 1980 | X28: 180 | Z28: =$Z$6*BC29 -> 0 | AG28: 1 | AH28: 1 | AI28: 1 | AJ28: 1 | AK28: 1 | AL28: 1 | AN28: 1 | AO28: 1 | AP28: 1 | AQ28: 1 | AR28: 1 | AS28: 1 | AU28: 1 | AV28: 1 | BC28: =SUM(AA28:BB28) -> 14 | BD28: =(BC28*X28)+Y28+Z28 -> 2520
B29: 20 | U29: 22 | V29: ดิว(ฝึกงาน) | W29: 1440 | X29: 180 | Z29: =$Z$6*BC30 -> 0 | BC29: =SUM(AA29:BB29) -> 0 | BD29: =(BC29*X29)+Y29+Z29 -> 0
B30: 21 | U30: 23 | V30: น็อต(ฝึกงาน) | W30: 2160 | X30: 180 | Z30: =$Z$6*BC31 -> 1400 | BC30: =SUM(AA30:BB30) -> 0 | BD30: =(BC30*X30)+Y30+Z30 -> 1400
B31: 22 | U31: 24 | V31: อาม(ฝึกงาน) | W31: 1980 | X31: 180 | Z31: =$Z$6*BC32 -> 0 | AG31: 1 | AH31: 1 | AI31: 1 | AJ31: 1 | AK31: 1 | AL31: 1 | AN31: 1 | AO31: 1 | AP31: 1 | AQ31: 1 | AR31: 1 | AS31: 1 | AU31: 1 | AV31: 1 | BC31: =SUM(AA31:BB31) -> 14 | BD31: =(BC31*X31)+Y31+Z31 -> 2520
B32: 23 | BD32: =SUM(BD8:BD31) -> 89976.667
B33: 24
B34: 25
B35: 26
B36: 27
B37: 28
B38: 29
B39: 30
B40: 31
B41: 32
B42: 33
B43: 34
B44: 35
... B46: 37
F47: TOTAL COST | G47: =SUM(G9:G46) -> 15000
F48: BALANCE | G48: =$C$6-G47 -> 6865000
F50: All BALANCE | G50: =G48/C6 -> 0.99781977
B52: Job. Code. | C52: ='All Job balance report'!B28 -> 0
B53: Contract Price | C53: ='All Job balance report'!G28 -> 0
B54: No. | C54: Code | E54: Description | F54: Budget | G54: Expense Record | H54: Balance | I54: Remark
B56: 1 | C56: 10 | E56: MATERIALS | F56: 4900000 | G56: =SUMIF($D$10:$D$46,$C$56,$G$10:$G$46) -> 0 | H56: =F56-G56 -> 4900000 | L56: 3142401 | M56: 2644700
B57: 2 | C57: 20 | E57: SUB CONTRACTOR | F57: 1700000 | G57: =SUMIF($D$10:$D$46,$C$57,$G$10:$G$46) -> 0 | H57: =F57-G57 -> 1700000 | L57: =L56-SUM(F58:F63) -> 2862401
B58: 3 | C58: 30 | E58: HEAVY EQUIPMENT | F58: 30000 | G58: =SUMIF($D$10:$D$46,$C$58,$G$10:$G$46) -> 0 | H58: =F58-G58 -> 30000
B59: 4 | C59: 40 | E59: RENTAL | F59: 30000 | G59: =SUMIF($D$10:$D$46,$C$59,$G$10:$G$46) -> 0 | H59: =F59-G59 -> 30000
B60: 5 | C60: 50 | E60: STAFF EXPENSE | F60: 120000 | G60: =SUMIF($D$10:$D$46,$C$60,$G$10:$G$46) -> 0 | H60: =F60-G60 -> 120000
B61: 6 | C61: 60 | E61: OFFICE EXPENSE | F61: 30000 | G61: =SUMIF($D$10:$D$46,$C$61,$G$10:$G$46) -> 0 | H61: =F61-G61 -> 30000
B62: 7 | C62: 70 | E62: ENTERTAIN | F62: 30000 | G62: =SUMIF($D$10:$D$46,$C$62,$G$10:$G$46) -> 0 | H62: =F62-G62 -> 30000
B63: 8 | C63: 80 | E63: MISCELLANEOUS | F63: 40000 | G63: =SUMIF($D$10:$D$46,$C$63,$G$10:$G$46) -> 15000 | H63: =F63-G63 -> 25000
E64: Total | F64: =SUM(F56:F63) -> 6880000 | G64: =SUM(G56:G63) -> 15000 | H64: =SUM(H56:H63) -> 6865000
E65: % Profit | F65: =((C53-F64)/C53) -> #DIV/0!
E66: Total Profit | F66: =F65*C53 -> #DIV/0!
E67: Gross Profit | F67: =C53-G64 -> -15000
F69: 0.05
C70: 10 | D70: 1586758.4 | F70: =F67*F69 -> -750
D71: 1680045
D72: 2395153.1
D73: 110550
D74: 983133.69
D80: =SUM(D70:D79) -> 6755640.1
C82: 20 | D82: 272504.13
D83: 741860.99
D84: 937577.84
D85: 40000
D86: 482416.9
D92: =SUM(D82:D91) -> 2474359.9

Sheet PC-008 JINHAI
B1: Factory/Company | C1: PROCHAIN | H1: Start Date | I1: 45833
B2: Project Name | C2: JINHAI Factory | H2: Sale Up Date
B3: Job Code. | C3: =C52 -> TMD-2601/001
B4: Quotation No. | E4: PROJECT BUDGET RECORD | H4: INVOICE (%) | I4: 0 | AA4: 45811 | AB4: 45812 | AC4: 45813 | AD4: 45814 | AE4: 45815 | AF4: 45816 | AG4: 45817 | AH4: 45818 | AI4: 45819 | AJ4: 45820 | AK4: 45821 | AL4: 45822 | AM4: 45823 | AN4: 45824 | AO4: 45825 | AP4: 45826 | AQ4: 45827 | AR4: 45828 | AS4: 45829 | AT4: 45830 | AU4: 45831 | AV4: 45832 | AW4: 45833 | AX4: 45834 | AY4: 45835 | AZ4: 45836 | BA4: 45837 | BB4: 45838 | BE4: 45839 | BF4: 45840 | BG4: 45841 | BH4: 45842 | BI4: 45843 | BJ4: 45844 | BK4: 45845 | BL4: 45846 | BM4: 45847 | BN4: 45848 | BO4: 45849 | BP4: 45850 | BQ4: 45851 | BR4: 45852 | BS4: 45853 | BT4: 45854 | BU4: 45855 | BV4: 45856 | BW4: 45857
B5: Contract Price | C5: =C53 -> 42000
B6: Budget Price | C6: =F64 -> 10090000 | Z6: 100
B7: PROFIT | C7: =(C5-C6)/C5 -> -239.2381 | D7: ACTUAL | E7: 1 | U7: No. | V7: Name | W7: Salary | X7: S per Day | Y7: ค่าโทรศัพท์ | Z7: ค่าอื่นๆ | AA7: =SUM(AA8:AA31) -> 4 | AB7: =SUM(AB8:AB31) -> 3 | AC7: =SUM(AC8:AC31) -> 3 | AD7: =SUM(AD8:AD31) -> 3 | AE7: =SUM(AE8:AE31) -> 3 | AF7: =SUM(AF8:AF31) -> 0 | AG7: =SUM(AG8:AG31) -> 11 | AH7: =SUM(AH8:AH31) -> 11 | ... BB7: =SUM(BB8:BB31) -> 0 | BE7: =SUM(BE8:BE31) -> 0 | BF7: =SUM(BF8:BF31) -> 0 | BG7: =SUM(BG8:BG31) -> 0 | BH7: =SUM(BH8:BH31) -> 0 | BI7: =SUM(BI8:BI31) -> 0 | BJ7: =SUM(BJ8:BJ31) -> 0 | BK7: =SUM(BK8:BK31) -> 0 | BL7: =SUM(BL8:BL31) -> 0 | ... BW7: =SUM(BW8:BW31) -> 0
B8: No. | C8: Vendor Name | D8: Material Number | E8: Description | F8: Text/Quo.No. | G8: Amount | H8: Updated By | I8: Date | J8: PO | U8: 1 | V8: พี่เอ็ก | W8: 31500 | X8: 1050 | Y8: 1400 | AG8: 1 | AH8: 1 | AI8: 1 | AJ8: 1 | AK8: 1 | AL8: 1 | AN8: 1 | AO8: 1 | AP8: 1 | AQ8: 1 | AR8: 1 | AS8: 1 | AU8: 1 | AV8: 1 | BC8: =SUM(AA8:BB8) -> 14 | BD8: =(BC8*X8)+Y8+Z8 -> 16100
U9: 2 | V9: เอลฟ์ | W9: 21300 | X9: 710 | Y9: 1400 | Z9: 2000 | AA9: 1 | AG9: 1 | AH9: 1 | AI9: 1 | AJ9: 1 | AK9: 1 | AL9: 1 | AN9: 1 | AO9: 1 | AP9: 1 | AQ9: 1 | AR9: 1 | AS9: 1 | AU9: 1 | AV9: 1 | BC9: =SUM(AA9:BB9) -> 15 | BD9: =(BC9*X9)+Y9+Z9 -> 14050
B10: 1 | C10: ค่าดำเนินการติดตั้งมิเตอร์การไฟฟ้า | D10: 80 | E10: ค่าดำเนินการ | G10: 15000 | H10: K.Kowit | I10: 45858 | U10: 3 | V10: เฮียนิ้ง | W10: 18500 | X10: 616.66667 | Z10: =$Z$6*BC11 -> 1400 | BC10: =SUM(AA10:BB10) -> 0 | BD10: =(BC10*X10)+Y10+Z10 -> 1400
B11: 2 | U11: 4 | V11: หนึ่ง | W11: 15000 | X11: 500 | Z11: =$Z$6*BC12 -> 1400 | AG11: 1 | AH11: 1 | AI11: 1 | AJ11: 1 | AK11: 1 | AL11: 1 | AN11: 1 | AO11: 1 | AP11: 1 | AQ11: 1 | AR11: 1 | AS11: 1 | AU11: 1 | AV11: 1 | BC11: =SUM(AA11:BB11) -> 14 | BD11: =(BC11*X11)+Y11+Z11 -> 8400
B12: 3 | U12: 5 | V12: แอล | W12: 14000 | X12: 466.66667 | Z12: =$Z$6*BC13 -> 0 | AG12: 1 | AH12: 1 | AI12: 1 | AJ12: 1 | AK12: 1 | AL12: 1 | AN12: 1 | AO12: 1 | AP12: 1 | AQ12: 1 | AR12: 1 | AS12: 1 | AU12: 1 | AV12: 1 | BC12: =SUM(AA12:BB12) -> 14 | BD12: =(BC12*X12)+Y12+Z12 -> 6533.3333
B13: 4 | U13: 6 | V13: เวฟ | W13: 14000 | X13: 466.66667 | Z13: =$Z$6*BC14 -> 0 | BC13: =SUM(AA13:BB13) -> 0 | BD13: =(BC13*X13)+Y13+Z13 -> 0
B14: 5 | U14: 78 | V14: บาส | W14: 13000 | X14: 433.33333 | Z14: =$Z$6*BC15 -> 0 | BC14: =SUM(AA14:BB14) -> 0 | BD14: =(BC14*X14)+Y14+Z14 -> 0
B15: 6 | U15: 8 | V15: พี่มิ้ว(แอดมิน) | W15: 14000 | X15: 466.66667 | Z15: =$Z$6*BC16 -> 0 | BC15: =SUM(AA15:BB15) -> 0 | BD15: =(BC15*X15)+Y15+Z15 -> 0
B16: 7 | U16: 9 | V16: พี่ดี๋ | W16: 50000 | X16: 1666.6667 | Z16: =$Z$6*BC17 -> 1400 | BC16: =SUM(AA16:BB16) -> 0 | BD16: =(BC16*X16)+Y16+Z16 -> 1400
B17: 8 | U17: 10 | V17: พี่เจมส์ | W17: 17000 | X17: 566.66667 | Z17: =$Z$6*BC18 -> 0 | AG17: 1 | AH17: 1 | AI17: 1 | AJ17: 1 | AK17: 1 | AL17: 1 | AN17: 1 | AO17: 1 | AP17: 1 | AQ17: 1 | AR17: 1 | AS17: 1 | AU17: 1 | AV17: 1 | BC17: =SUM(AA17:BB17) -> 14 | BD17: =(BC17*X17)+Y17+Z17 -> 7933.3333
B18: 9 | U18: 11 | V18: อั้ม | W18: 20000 | X18: 666.66667 | Z18: =$Z$6*BC19 -> 1400 | BC18: =SUM(AA18:BB18) -> 0 | BD18: =(BC18*X18)+Y18+Z18 -> 1400
B19: 10 | U19: 12 | V19: พี่เต้ย (รายวัน) | W19: 4950 | X19: 450 | Z19: =$Z$6*BC20 -> 0 | AG19: 1 | AH19: 1 | AI19: 1 | AJ19: 1 | AK19: 1 | AL19: 1 | AN19: 1 | AO19: 1 | AP19: 1 | AQ19: 1 | AR19: 1 | AS19: 1 | AU19: 1 | AV19: 1 | BC19: =SUM(AA19:BB19) -> 14 | BD19: =(BC19*X19)+Y19+Z19 -> 6300
B20: 11 | U20: 13 | V20: จิว(ฝึกงาน) | W20: 3300 | X20: 300 | Z20: =$Z$6*BC21 -> 0 | BC20: =SUM(AA20:BB20) -> 0 | BD20: =(BC20*X20)+Y20+Z20 -> 0
B21: 12 | U21: 14 | V21: บอล(ฝึกงาน300) | W21: 3300 | X21: 300 | Z21: =$Z$6*BC22 -> 0 | BC21: =SUM(AA21:BB21) -> 0 | BD21: =(BC21*X21)+Y21+Z21 -> 0
B22: 13 | U22: 15 | V22: มุก(ฝึกงาน) | W22: 3300 | X22: 300 | Z22: =$Z$6*BC23 -> 0 | BC22: =SUM(AA22:BB22) -> 0 | BD22: =(BC22*X22)+Y22+Z22 -> 0
B23: 14 | U23: 16 | V23: เบนซ์(ฝึกงาน300) | W23: 3300 | X23: 300 | Z23: =$Z$6*BC24 -> 1900 | BC23: =SUM(AA23:BB23) -> 0 | BD23: =(BC23*X23)+Y23+Z23 -> 1900
B24: 15 | U24: 17 | V24: เต๋า(ฝึกงาน) | W24: 2700 | X24: 300 | Z24: =$Z$6*BC25 -> 1900 | AA24: 1 | AB24: 1 | AC24: 1 | AD24: 1 | AE24: 1 | AG24: 1 | AH24: 1 | AI24: 1 | AJ24: 1 | AK24: 1 | AL24: 1 | AN24: 1 | AO24: 1 | AP24: 1 | AQ24: 1 | AR24: 1 | AS24: 1 | AU24: 1 | AV24: 1 | BC24: =SUM(AA24:BB24) -> 19 | BD24: =(BC24*X24)+Y24+Z24 -> 7600
B25: 16 | U25: 18 | V25: เฟียส(ฝึกงาน) | W25: 2200 | X25: 200 | Z25: =$Z$6*BC26 -> 1900 | AA25: 1 | AB25: 1 | AC25: 1 | AD25: 1 | AE25: 1 | AG25: 1 | AH25: 1 | AI25: 1 | AJ25: 1 | AK25: 1 | AL25: 1 | AN25: 1 | AO25: 1 | AP25: 1 | AQ25: 1 | AR25: 1 | AS25: 1 | AU25: 1 | AV25: 1 | BC25: =SUM(AA25:BB25) -> 19 | BD25: =(BC25*X25)+Y25+Z25 -> 5700
B26: 17 | U26: 19 | V26: ฟลุ๊ค(ฝึกงาน) | W26: 1440 | X26: 180 | Z26: =$Z$6*BC27 -> 0 | AA26: 1 | AB26: 1 | AC26: 1 | AD26: 1 | AE26: 1 | AG26: 1 | AH26: 1 | AI26: 1 | AJ26: 1 | AK26: 1 | AL26: 1 | AN26: 1 | AO26: 1 | AP26: 1 | AQ26: 1 | AR26: 1 | AS26: 1 | AU26: 1 | AV26: 1 | BC26: =SUM(AA26:BB26) -> 19 | BD26: =(BC26*X26)+Y26+Z26 -> 3420
B27: 18 | U27: 20 | V27: เจมส์(ฝึกงาน) | W27: 2160 | X27: 180 | Z27: =$Z$6*BC28 -> 1400 | BC27: =SUM(AA27:BB27) -> 0 | BD27: =(BC27*X27)+Y27+Z27 -> 1400
B28: 19 | U28: 21 | V28: นาย(ฝึกงาน) | W28: 1980 | X28: 180 | Z28: =$Z$6*BC29 -> 0 | AG28: 1 | AH28: 1 | AI28: 1 | AJ28: 1 | AK28: 1 | AL28: 1 | AN28: 1 | AO28: 1 | AP28: 1 | AQ28: 1 | AR28: 1 | AS28: 1 | AU28: 1 | AV28: 1 | BC28: =SUM(AA28:BB28) -> 14 | BD28: =(BC28*X28)+Y28+Z28 -> 2520
B29: 20 | U29: 22 | V29: ดิว(ฝึกงาน) | W29: 1440 | X29: 180 | Z29: =$Z$6*BC30 -> 0 | BC29: =SUM(AA29:BB29) -> 0 | BD29: =(BC29*X29)+Y29+Z29 -> 0
B30: 21 | U30: 23 | V30: น็อต(ฝึกงาน) | W30: 2160 | X30: 180 | Z30: =$Z$6*BC31 -> 1400 | BC30: =SUM(AA30:BB30) -> 0 | BD30: =(BC30*X30)+Y30+Z30 -> 1400
B31: 22 | U31: 24 | V31: อาม(ฝึกงาน) | W31: 1980 | X31: 180 | Z31: =$Z$6*BC32 -> 0 | AG31: 1 | AH31: 1 | AI31: 1 | AJ31: 1 | AK31: 1 | AL31: 1 | AN31: 1 | AO31: 1 | AP31: 1 | AQ31: 1 | AR31: 1 | AS31: 1 | AU31: 1 | AV31: 1 | BC31: =SUM(AA31:BB31) -> 14 | BD31: =(BC31*X31)+Y31+Z31 -> 2520
B32: 23 | BD32: =SUM(BD8:BD31) -> 89976.667
B33: 24
B34: 25
B35: 26
B36: 27
B37: 28
B38: 29
B39: 30
B40: 31
B41: 32
B42: 33
B43: 34
B44: 35
... B46: 37
F47: TOTAL COST | G47: =SUM(G9:G46) -> 15000
F48: BALANCE | G48: =$C$6-G47 -> 10075000
F50: All BALANCE | G50: =G48/C6 -> 0.99851338
B52: Job. Code. | C52: ='All Job balance report'!B14 -> TMD-2601/001
B53: Contract Price | C53: ='All Job balance report'!G14 -> 42000
B54: No. | C54: Code | E54: Description | F54: Budget | G54: Expense Record | H54: Balance | I54: Remark
B56: 1 | C56: 10 | E56: MATERIALS | F56: 7580000 | G56: =SUMIF($D$10:$D$46,$C$56,$G$10:$G$46) -> 0 | H56: =F56-G56 -> 7580000 | L56: 3142401 | M56: 2644700
B57: 2 | C57: 20 | E57: SUB CONTRACTOR | F57: 2000000 | G57: =SUMIF($D$10:$D$46,$C$57,$G$10:$G$46) -> 0 | H57: =F57-G57 -> 2000000 | L57: =L56-SUM(F58:F63) -> 2632401
B58: 3 | C58: 30 | E58: HEAVY EQUIPMENT | F58: 50000 | G58: =SUMIF($D$10:$D$46,$C$58,$G$10:$G$46) -> 0 | H58: =F58-G58 -> 50000
B59: 4 | C59: 40 | E59: RENTAL | F59: 50000 | G59: =SUMIF($D$10:$D$46,$C$59,$G$10:$G$46) -> 0 | H59: =F59-G59 -> 50000
B60: 5 | C60: 50 | E60: STAFF EXPENSE | F60: 300000 | G60: =SUMIF($D$10:$D$46,$C$60,$G$10:$G$46) -> 0 | H60: =F60-G60 -> 300000
B61: 6 | C61: 60 | E61: OFFICE EXPENSE | F61: 40000 | G61: =SUMIF($D$10:$D$46,$C$61,$G$10:$G$46) -> 0 | H61: =F61-G61 -> 40000
B62: 7 | C62: 70 | E62: ENTERTAIN | F62: 30000 | G62: =SUMIF($D$10:$D$46,$C$62,$G$10:$G$46) -> 0 | H62: =F62-G62 -> 30000
B63: 8 | C63: 80 | E63: MISCELLANEOUS | F63: 40000 | G63: =SUMIF($D$10:$D$46,$C$63,$G$10:$G$46) -> 15000 | H63: =F63-G63 -> 25000
E64: Total | F64: =SUM(F56:F63) -> 10090000 | G64: =SUM(G56:G63) -> 15000 | H64: =SUM(H56:H63) -> 10075000
E65: % Profit | F65: =((C53-F64)/C53) -> -239.2381
E66: Total Profit | F66: =F65*C53 -> -10048000
E67: Gross Profit | F67: =C53-G64 -> 27000
F69: 0.05
C70: 10 | D70: 130220 | F70: =F67*F69 -> 1350
D71: 932447
D72: 2509638
D73: 657729.56
D74: 1711165
D75: 1748525.8
D76: 1193507.7
D77: 253400
D78: 1315322.9
D79: 70361
D80: =SUM(D70:D79) -> 10522317
C82: 20 | D82: 75000
D83: 102500
D84: 156474.88
D85: 183719
D86: 912852.76
D87: 953738.62
D88: 390501.84
D89: 100000
D90: 451699.78
D91: 34447.6
D92: =SUM(D82:D91) -> 3360934.5

Sheet PC-007 บ้านลาดกระบัง
B1: Factory/Company | C1: ='All Job balance report'!D13 -> Unity System Co., Ltd. | H1: Start Date | I1: 45809
B2: Project Name | C2: ='All Job balance report'!F13 -> งานค่าแรงผู้รับเหมา รพ.ภัทรเวช | H2: Sale Up Date
B3: Job Code. | C3: =C45 -> UNT-2601/001
B4: Quotation No. | E4: PROJECT BUDGET RECORD | H4: INVOICE (%) | I4: 0
B5: Contract Price | C5: =C46 -> 143840.18
B6: Budget Price | C6: =F57 -> 0
B7: PROFIT | C7: =(C5-C6)/C5 -> 1 | D7: ACTUAL | E7: 1
B8: No. | C8: Vendor Name | D8: Material Number | E8: Description | F8: Text/Quo.No. | G8: Amount | H8: Updated By | I8: Date | J8: PO
B10: 1 | C10: N.R.E | D10: 10 | E10: ราง Cable tray | F10: SUV-250107744 | G10: 9469.1 | H10: K.Kowit | I10: 45833 | J10: PO2025060023
B11: 2 | C11: บริษัท สยาม โคสทอล อินเตอร์เทรด จำกัด | D11: 10 | E11: MDB Panel | F11: 0267LC68SC | G11: 57500 | H11: K.Kowit | I11: 45832 | J11: PO2025060021
B12: 3 | C12: N.R.E | D12: 10 | E12: ท่ออ่อน PVC. | F12: SUV-250106117 | G12: 12900 | H12: K.Kowit | I12: 45798 | J12: PO2025050011
B13: 4 | C13: N.R.E | D13: 10 | E13: Fitting ราง Cable Tray | F13: SUV-250109340 | G13: 4188.8 | H13: K.Kowit | I13: 45833 | J13: PO2025080001
B14: 5 | C14: N.R.E | D14: 10 | E14: Load Center | F14: SUV-250107045 | G14: 46196.8 | H14: K.Kowit | I14: 45820 | J14: PO2025060012
B15: 6
F40: TOTAL COST | G40: =SUM(G9:G39) -> 130254.7
F41: BALANCE | G41: =$C$6-G40 -> -130254.7
F43: All BALANCE | G43: =G41/C6 -> #DIV/0!
B45: Job. Code. | C45: ='All Job balance report'!B13 -> UNT-2601/001
B46: Contract Price | C46: ='All Job balance report'!G13 -> 143840.18
B47: No. | C47: Code | E47: Description | F47: Budget | G47: Expense Record | H47: Balance | I47: Remark
B49: 1 | C49: 10 | E49: MATERIALS | F49: 0 | G49: =SUMIF($D$10:$D$39,$C$49,$G$10:$G$39) -> 130254.7 | H49: =F49-G49 -> -130254.7
B50: 2 | C50: 20 | E50: SUB CONTRACTOR | F50: 0 | G50: =SUMIF($D$10:$D$39,$C$50,$G$10:$G$39) -> 0 | H50: =F50-G50 -> 0
B51: 3 | C51: 30 | E51: HEAVY EQUIPMENT | F51: 0 | G51: =SUMIF($D$10:$D$39,$C$51,$G$10:$G$39) -> 0 | H51: =F51-G51 -> 0
B52: 4 | C52: 40 | E52: RENTAL | F52: 0 | G52: =SUMIF($D$10:$D$39,$C$52,$G$10:$G$39) -> 0 | H52: =F52-G52 -> 0
B53: 5 | C53: 50 | E53: STAFF EXPENSE | F53: 0 | G53: =SUMIF($D$10:$D$39,$C$53,$G$10:$G$39) -> 0 | H53: =F53-G53 -> 0
B54: 6 | C54: 60 | E54: OFFICE EXPENSE | F54: 0 | G54: =SUMIF($D$10:$D$39,$C$54,$G$10:$G$39) -> 0 | H54: =F54-G54 -> 0
B55: 7 | C55: 70 | E55: ENTERTAIN | F55: 0 | G55: =SUMIF($D$10:$D$39,$C$55,$G$10:$G$39) -> 0 | H55: =F55-G55 -> 0
B56: 8 | C56: 80 | E56: MISCELLANEOUS | F56: 0 | G56: =SUMIF($D$10:$D$39,$C$56,$G$10:$G$39) -> 0 | H56: =F56-G56 -> 0
E57: Total | F57: =SUM(F49:F56) -> 0 | G57: =SUM(G49:G56) -> 130254.7 | H57: =SUM(H49:H56) -> -130254.7
E58: % Profit | F58: =((C46-F57)/C46) -> 1
E59: Total Profit | F59: =F58*C46 -> 143840.18
E60: Gross Profit | F60: =C46-G57 -> 13585.48

Sheet XP-001 งานนครนายก
B1: Factory/Company | C1: ='All Job balance report'!D12 -> บริษัท เจตภัทร คอนสตรัคชั่น แอนด์ ดีไซน์ จำกัด | H1: Start Date | I1: 45818
B2: Project Name | C2: ='All Job balance report'!F12 -> งานติดตั้งคอนโด The Line Vibe ห้อง549 | H2: Sale Up Date
B3: Job Code. | C3: =C52 -> JEP-2601/001
B4: Quotation No. | E4: PROJECT BUDGET RECORD | H4: INVOICE (%) | I4: 0 | AA4: 45811 | AB4: 45812 | AC4: 45813 | AD4: 45814 | AE4: 45815 | AF4: 45816 | AG4: 45817 | AH4: 45818 | AI4: 45819 | AJ4: 45820 | AK4: 45821 | AL4: 45822 | AM4: 45823 | AN4: 45824 | AO4: 45825 | AP4: 45826 | AQ4: 45827 | AR4: 45828 | AS4: 45829 | AT4: 45830 | AU4: 45831 | AV4: 45832 | AW4: 45833 | AX4: 45834 | AY4: 45835 | AZ4: 45836 | BA4: 45837 | BB4: 45838 | BE4: 45839 | BF4: 45840 | BG4: 45841 | BH4: 45842 | BI4: 45843 | BJ4: 45844 | BK4: 45845 | BL4: 45846 | BM4: 45847 | BN4: 45848 | BO4: 45849 | BP4: 45850 | BQ4: 45851 | BR4: 45852 | BS4: 45853 | BT4: 45854 | BU4: 45855 | BV4: 45856 | BW4: 45857
B5: Contract Price | C5: =C53 -> 12000
B6: Budget Price | C6: =F64 -> 98300 | Z6: 100
B7: PROFIT | C7: =(C5-C6)/C5 -> -7.1916667 | D7: ACTUAL | E7: 1 | U7: No. | V7: Name | W7: Salary | X7: S per Day | Y7: ค่าโทรศัพท์ | Z7: ค่าอื่นๆ | AA7: =SUM(AA8:AA31) -> 4 | AB7: =SUM(AB8:AB31) -> 3 | AC7: =SUM(AC8:AC31) -> 3 | AD7: =SUM(AD8:AD31) -> 3 | AE7: =SUM(AE8:AE31) -> 3 | AF7: =SUM(AF8:AF31) -> 0 | AG7: =SUM(AG8:AG31) -> 11 | AH7: =SUM(AH8:AH31) -> 11 | ... BB7: =SUM(BB8:BB31) -> 0 | BE7: =SUM(BE8:BE31) -> 0 | BF7: =SUM(BF8:BF31) -> 0 | BG7: =SUM(BG8:BG31) -> 0 | BH7: =SUM(BH8:BH31) -> 0 | BI7: =SUM(BI8:BI31) -> 0 | BJ7: =SUM(BJ8:BJ31) -> 0 | BK7: =SUM(BK8:BK31) -> 0 | BL7: =SUM(BL8:BL31) -> 0 | ... BW7: =SUM(BW8:BW31) -> 0
B8: No. | C8: Vendor Name | D8: Material Number | E8: Description | F8: Text/Quo.No. | G8: Amount | H8: Updated By | I8: Date | J8: PO | U8: 1 | V8: พี่เอ็ก | W8: 31500 | X8: 1050 | Y8: 1400 | AG8: 1 | AH8: 1 | AI8: 1 | AJ8: 1 | AK8: 1 | AL8: 1 | AN8: 1 | AO8: 1 | AP8: 1 | AQ8: 1 | AR8: 1 | AS8: 1 | AU8: 1 | AV8: 1 | BC8: =SUM(AA8:BB8) -> 14 | BD8: =(BC8*X8)+Y8+Z8 -> 16100
U9: 2 | V9: เอลฟ์ | W9: 21300 | X9: 710 | Y9: 1400 | Z9: 2000 | AA9: 1 | AG9: 1 | AH9: 1 | AI9: 1 | AJ9: 1 | AK9: 1 | AL9: 1 | AN9: 1 | AO9: 1 | AP9: 1 | AQ9: 1 | AR9: 1 | AS9: 1 | AU9: 1 | AV9: 1 | BC9: =SUM(AA9:BB9) -> 15 | BD9: =(BC9*X9)+Y9+Z9 -> 14050
B10: 1 | C10: NRE | D10: 10 | E10: ราคาราง Cable Tray | G10: 35608.8 | H10: K.Kowit | I10: 45821 | J10: PO2025060014 | U10: 3 | V10: เฮียนิ้ง | W10: 18500 | X10: 616.66667 | Z10: =$Z$6*BC11 -> 1400 | BC10: =SUM(AA10:BB10) -> 0 | BD10: =(BC10*X10)+Y10+Z10 -> 1400
B11: 2 | C11: บริษัท สยาม โคสทอล อินเตอร์เทรด จำกัด | D11: 10 | E11: มิเตอร์ Digitakl Meter Schneider | G11: 5500 | H11: K.Kowit | I11: 45825 | J11: PO2025060018 | U11: 4 | V11: หนึ่ง | W11: 15000 | X11: 500 | Z11: =$Z$6*BC12 -> 1400 | AG11: 1 | AH11: 1 | AI11: 1 | AJ11: 1 | AK11: 1 | AL11: 1 | AN11: 1 | AO11: 1 | AP11: 1 | AQ11: 1 | AR11: 1 | AS11: 1 | AU11: 1 | AV11: 1 | BC11: =SUM(AA11:BB11) -> 14 | BD11: =(BC11*X11)+Y11+Z11 -> 8400
B12: 3 | C12: บริษัท สยาม โคสทอล อินเตอร์เทรด จำกัด | D12: 10 | E12: Steel Plate | G12: 10000 | H12: K.Kowit | I12: 45833 | J12: PO2025060022 | U12: 5 | V12: แอล | W12: 14000 | X12: 466.66667 | Z12: =$Z$6*BC13 -> 0 | AG12: 1 | AH12: 1 | AI12: 1 | AJ12: 1 | AK12: 1 | AL12: 1 | AN12: 1 | AO12: 1 | AP12: 1 | AQ12: 1 | AR12: 1 | AS12: 1 | AU12: 1 | AV12: 1 | BC12: =SUM(AA12:BB12) -> 14 | BD12: =(BC12*X12)+Y12+Z12 -> 6533.3333
B13: 4 | C13: ซื้อของทั่วไป | D13: 10 | G13: 3000 | H13: Sarawut | I13: 45833 | U13: 6 | V13: เวฟ | W13: 14000 | X13: 466.66667 | Z13: =$Z$6*BC14 -> 0 | BC13: =SUM(AA13:BB13) -> 0 | BD13: =(BC13*X13)+Y13+Z13 -> 0
B14: 5 | C14: ทีมงาน SEE พี่โจ๊ส | D14: 20 | G14: 32000 | H14: K.Kowit | I14: 45833 | U14: 78 | V14: บาส | W14: 13000 | X14: 433.33333 | Z14: =$Z$6*BC15 -> 0 | BC14: =SUM(AA14:BB14) -> 0 | BD14: =(BC14*X14)+Y14+Z14 -> 0
B15: 6 | D15: 10 | E15: ค่าน้ำมัน | G15: 500 | H15: K.Kowit | I15: 45847 | U15: 8 | V15: พี่มิ้ว(แอดมิน) | W15: 14000 | X15: 466.66667 | Z15: =$Z$6*BC16 -> 0 | BC15: =SUM(AA15:BB15) -> 0 | BD15: =(BC15*X15)+Y15+Z15 -> 0
B16: 7 | D16: 10 | E16: ค่าเหล็ก | G16: 1240 | H16: K.Kowit | I16: 45847 | U16: 9 | V16: พี่ดี๋ | W16: 50000 | X16: 1666.6667 | Z16: =$Z$6*BC17 -> 1400 | BC16: =SUM(AA16:BB16) -> 0 | BD16: =(BC16*X16)+Y16+Z16 -> 1400
B17: 8 | D17: 10 | E17: ค่าเหล็ก | G17: 240 | H17: K.Kowit | I17: 45847 | U17: 10 | V17: พี่เจมส์ | W17: 17000 | X17: 566.66667 | Z17: =$Z$6*BC18 -> 0 | AG17: 1 | AH17: 1 | AI17: 1 | AJ17: 1 | AK17: 1 | AL17: 1 | AN17: 1 | AO17: 1 | AP17: 1 | AQ17: 1 | AR17: 1 | AS17: 1 | AU17: 1 | AV17: 1 | BC17: =SUM(AA17:BB17) -> 14 | BD17: =(BC17*X17)+Y17+Z17 -> 7933.3333
B18: 9 | D18: 10 | E18: ซื้อแผ่นเหล็กเพิ่มอีก 2 แผ่น | G18: 2000 | H18: K.Kowit | I18: 45847 | U18: 11 | V18: อั้ม | W18: 20000 | X18: 666.66667 | Z18: =$Z$6*BC19 -> 1400 | BC18: =SUM(AA18:BB18) -> 0 | BD18: =(BC18*X18)+Y18+Z18 -> 1400
B19: 10 | D19: 50 | E19: ค่าแรงทีมงาน | G19: 5307 | H19: K.Kowit | I19: 45847 | N19: 668 | O19: =N19*P19 -> 2004 | P19: 3 | R19: =N19/8 -> 83.5 | S19: 10 | T19: =S19*R19 -> 835 | U19: 12 | V19: พี่เต้ย (รายวัน) | W19: 4950 | X19: 450 | Z19: =$Z$6*BC20 -> 0 | AG19: 1 | AH19: 1 | AI19: 1 | AJ19: 1 | AK19: 1 | AL19: 1 | AN19: 1 | AO19: 1 | AP19: 1 | AQ19: 1 | AR19: 1 | AS19: 1 | AU19: 1 | AV19: 1 | BC19: =SUM(AA19:BB19) -> 14 | BD19: =(BC19*X19)+Y19+Z19 -> 6300
B20: 11 | D20: 50 | E20: ค่าน้ำมันรถ | G20: 2000 | H20: K.Kowit | I20: 45847 | N20: 468 | O20: =N20*P20 -> 468 | P20: 1 | U20: 13 | V20: จิว(ฝึกงาน) | W20: 3300 | X20: 300 | Z20: =$Z$6*BC21 -> 0 | BC20: =SUM(AA20:BB20) -> 0 | BD20: =(BC20*X20)+Y20+Z20 -> 0
B21: 12 | C21: ฮาร์ดแวร์เฮาส์ | D21: 10 | E21: ค่าสี และแผ่นเหล็ก | G21: 976 | H21: K.Kowit | I21: 45847 | U21: 14 | V21: บอล(ฝึกงาน300) | W21: 3300 | X21: 300 | Z21: =$Z$6*BC22 -> 0 | BC21: =SUM(AA21:BB21) -> 0 | BD21: =(BC21*X21)+Y21+Z21 -> 0
B22: 13 | O22: =O20+O19+T19 -> 3307 | U22: 15 | V22: มุก(ฝึกงาน) | W22: 3300 | X22: 300 | Z22: =$Z$6*BC23 -> 0 | BC22: =SUM(AA22:BB22) -> 0 | BD22: =(BC22*X22)+Y22+Z22 -> 0
B23: 14 | N23: 2000 | U23: 16 | V23: เบนซ์(ฝึกงาน300) | W23: 3300 | X23: 300 | Z23: =$Z$6*BC24 -> 1900 | BC23: =SUM(AA23:BB23) -> 0 | BD23: =(BC23*X23)+Y23+Z23 -> 1900
B24: 15 | U24: 17 | V24: เต๋า(ฝึกงาน) | W24: 2700 | X24: 300 | Z24: =$Z$6*BC25 -> 1900 | AA24: 1 | AB24: 1 | AC24: 1 | AD24: 1 | AE24: 1 | AG24: 1 | AH24: 1 | AI24: 1 | AJ24: 1 | AK24: 1 | AL24: 1 | AN24: 1 | AO24: 1 | AP24: 1 | AQ24: 1 | AR24: 1 | AS24: 1 | AU24: 1 | AV24: 1 | BC24: =SUM(AA24:BB24) -> 19 | BD24: =(BC24*X24)+Y24+Z24 -> 7600
B25: 16 | U25: 18 | V25: เฟียส(ฝึกงาน) | W25: 2200 | X25: 200 | Z25: =$Z$6*BC26 -> 1900 | AA25: 1 | AB25: 1 | AC25: 1 | AD25: 1 | AE25: 1 | AG25: 1 | AH25: 1 | AI25: 1 | AJ25: 1 | AK25: 1 | AL25: 1 | AN25: 1 | AO25: 1 | AP25: 1 | AQ25: 1 | AR25: 1 | AS25: 1 | AU25: 1 | AV25: 1 | BC25: =SUM(AA25:BB25) -> 19 | BD25: =(BC25*X25)+Y25+Z25 -> 5700
B26: 17 | U26: 19 | V26: ฟลุ๊ค(ฝึกงาน) | W26: 1440 | X26: 180 | Z26: =$Z$6*BC27 -> 0 | AA26: 1 | AB26: 1 | AC26: 1 | AD26: 1 | AE26: 1 | AG26: 1 | AH26: 1 | AI26: 1 | AJ26: 1 | AK26: 1 | AL26: 1 | AN26: 1 | AO26: 1 | AP26: 1 | AQ26: 1 | AR26: 1 | AS26: 1 | AU26: 1 | AV26: 1 | BC26: =SUM(AA26:BB26) -> 19 | BD26: =(BC26*X26)+Y26+Z26 -> 3420
B27: 18 | U27: 20 | V27: เจมส์(ฝึกงาน) | W27: 2160 | X27: 180 | Z27: =$Z$6*BC28 -> 1400 | BC27: =SUM(AA27:BB27) -> 0 | BD27: =(BC27*X27)+Y27+Z27 -> 1400
B28: 19 | U28: 21 | V28: นาย(ฝึกงาน) | W28: 1980 | X28: 180 | Z28: =$Z$6*BC29 -> 0 | AG28: 1 | AH28: 1 | AI28: 1 | AJ28: 1 | AK28: 1 | AL28: 1 | AN28: 1 | AO28: 1 | AP28: 1 | AQ28: 1 | AR28: 1 | AS28: 1 | AU28: 1 | AV28: 1 | BC28: =SUM(AA28:BB28) -> 14 | BD28: =(BC28*X28)+Y28+Z28 -> 2520
B29: 20 | U29: 22 | V29: ดิว(ฝึกงาน) | W29: 1440 | X29: 180 | Z29: =$Z$6*BC30 -> 0 | BC29: =SUM(AA29:BB29) -> 0 | BD29: =(BC29*X29)+Y29+Z29 -> 0
B30: 21 | U30: 23 | V30: น็อต(ฝึกงาน) | W30: 2160 | X30: 180 | Z30: =$Z$6*BC31 -> 1400 | BC30: =SUM(AA30:BB30) -> 0 | BD30: =(BC30*X30)+Y30+Z30 -> 1400
B31: 22 | U31: 24 | V31: อาม(ฝึกงาน) | W31: 1980 | X31: 180 | Z31: =$Z$6*BC32 -> 0 | AG31: 1 | AH31: 1 | AI31: 1 | AJ31: 1 | AK31: 1 | AL31: 1 | AN31: 1 | AO31: 1 | AP31: 1 | AQ31: 1 | AR31: 1 | AS31: 1 | AU31: 1 | AV31: 1 | BC31: =SUM(AA31:BB31) -> 14 | BD31: =(BC31*X31)+Y31+Z31 -> 2520
B32: 23 | BD32: =SUM(BD8:BD31) -> 89976.667
B33: 24
B34: 25
B35: 26
B36: 27
B37: 28
B38: 29
B39: 30
B40: 31
B41: 32
B42: 33
B43: 34
B44: 35
... B46: 37
F47: TOTAL COST | G47: =SUM(G9:G46) -> 98371.8
F48: BALANCE | G48: =$C$6-G47 -> -71.8
F50: All BALANCE | G50: =G48/C6 -> -0.00073041709
B52: Job. Code. | C52: ='All Job balance report'!B12 -> JEP-2601/001
B53: Contract Price | C53: ='All Job balance report'!G12 -> 12000
B54: No. | C54: Code | E54: Description | F54: Budget | G54: Expense Record | H54: Balance | I54: Remark
B56: 1 | C56: 10 | E56: MATERIALS | F56: 60000 | G56: =SUMIF($D$10:$D$46,$C$56,$G$10:$G$46) -> 59064.8 | H56: =F56-G56 -> 935.2 | L56: 3142401 | M56: 2644700
B57: 2 | C57: 20 | E57: SUB CONTRACTOR | F57: 32300 | G57: =SUMIF($D$10:$D$46,$C$57,$G$10:$G$46) -> 32000 | H57: =F57-G57 -> 300 | L57: =L56-SUM(F58:F63) -> 3136401
B58: 3 | C58: 30 | E58: HEAVY EQUIPMENT | F58: 0 | G58: =SUMIF($D$10:$D$46,$C$58,$G$10:$G$46) -> 0 | H58: =F58-G58 -> 0
B59: 4 | C59: 40 | E59: RENTAL | F59: 0 | G59: =SUMIF($D$10:$D$46,$C$59,$G$10:$G$46) -> 0 | H59: =F59-G59 -> 0
B60: 5 | C60: 50 | E60: STAFF EXPENSE | F60: 6000 | G60: =SUMIF($D$10:$D$46,$C$60,$G$10:$G$46) -> 7307 | H60: =F60-G60 -> -1307
B61: 6 | C61: 60 | E61: OFFICE EXPENSE | F61: 0 | G61: =SUMIF($D$10:$D$46,$C$61,$G$10:$G$46) -> 0 | H61: =F61-G61 -> 0
B62: 7 | C62: 70 | E62: ENTERTAIN | F62: 0 | G62: =SUMIF($D$10:$D$46,$C$62,$G$10:$G$46) -> 0 | H62: =F62-G62 -> 0
B63: 8 | C63: 80 | E63: MISCELLANEOUS | F63: 0 | G63: =SUMIF($D$10:$D$46,$C$63,$G$10:$G$46) -> 0 | H63: =F63-G63 -> 0
E64: Total | F64: =SUM(F56:F63) -> 98300 | G64: =SUM(G56:G63) -> 98371.8 | H64: =SUM(H56:H63) -> -71.8
E65: % Profit | F65: =((C53-F64)/C53) -> -7.1916667
E66: Total Profit | F66: =F65*C53 -> -86300
E67: Gross Profit | F67: =C53-G64 -> -86371.8 | G67: =F67/C53 -> -7.19765
F69: 0.05
F70: =F67*F69 -> -4318.59

Sheet MC-002 Udonthani
B1: Factory/Company | C1: Mc.Tric Public Company Limited | H1: Start Date | I1: 45833
B2: Project Name | C2: 22kV. Pole and Underground project | H2: Sale Up Date
B3: Job Code. | C3: =C52 -> PKE-2500/002
B4: Quotation No. | E4: PROJECT BUDGET RECORD | H4: INVOICE (%) | I4: 0 | AA4: 45811 | AB4: 45812 | AC4: 45813 | AD4: 45814 | AE4: 45815 | AF4: 45816 | AG4: 45817 | AH4: 45818 | AI4: 45819 | AJ4: 45820 | AK4: 45821 | AL4: 45822 | AM4: 45823 | AN4: 45824 | AO4: 45825 | AP4: 45826 | AQ4: 45827 | AR4: 45828 | AS4: 45829 | AT4: 45830 | AU4: 45831 | AV4: 45832 | AW4: 45833 | AX4: 45834 | AY4: 45835 | AZ4: 45836 | BA4: 45837 | BB4: 45838 | BE4: 45839 | BF4: 45840 | BG4: 45841 | BH4: 45842 | BI4: 45843 | BJ4: 45844 | BK4: 45845 | BL4: 45846 | BM4: 45847 | BN4: 45848 | BO4: 45849 | BP4: 45850 | BQ4: 45851 | BR4: 45852 | BS4: 45853 | BT4: 45854 | BU4: 45855 | BV4: 45856 | BW4: 45857
B5: Contract Price | C5: =C53 -> 7000
B6: Budget Price | C6: =F64 -> 5867101 | Z6: 100
B7: PROFIT | C7: =(C5-C6)/C5 -> -837.15729 | D7: ACTUAL | E7: 1 | U7: No. | V7: Name | W7: Salary | X7: S per Day | Y7: ค่าโทรศัพท์ | Z7: ค่าอื่นๆ | AA7: =SUM(AA8:AA31) -> 4 | AB7: =SUM(AB8:AB31) -> 3 | AC7: =SUM(AC8:AC31) -> 3 | AD7: =SUM(AD8:AD31) -> 3 | AE7: =SUM(AE8:AE31) -> 3 | AF7: =SUM(AF8:AF31) -> 0 | AG7: =SUM(AG8:AG31) -> 11 | AH7: =SUM(AH8:AH31) -> 11 | ... BB7: =SUM(BB8:BB31) -> 0 | BE7: =SUM(BE8:BE31) -> 0 | BF7: =SUM(BF8:BF31) -> 0 | BG7: =SUM(BG8:BG31) -> 0 | BH7: =SUM(BH8:BH31) -> 0 | BI7: =SUM(BI8:BI31) -> 0 | BJ7: =SUM(BJ8:BJ31) -> 0 | BK7: =SUM(BK8:BK31) -> 0 | BL7: =SUM(BL8:BL31) -> 0 | ... BW7: =SUM(BW8:BW31) -> 0
B8: No. | C8: Vendor Name | D8: Material Number | E8: Description | F8: Text/Quo.No. | G8: Amount | H8: Updated By | I8: Date | J8: PO | U8: 1 | V8: พี่เอ็ก | W8: 31500 | X8: 1050 | Y8: 1400 | AG8: 1 | AH8: 1 | AI8: 1 | AJ8: 1 | AK8: 1 | AL8: 1 | AN8: 1 | AO8: 1 | AP8: 1 | AQ8: 1 | AR8: 1 | AS8: 1 | AU8: 1 | AV8: 1 | BC8: =SUM(AA8:BB8) -> 14 | BD8: =(BC8*X8)+Y8+Z8 -> 16100
U9: 2 | V9: เอลฟ์ | W9: 21300 | X9: 710 | Y9: 1400 | Z9: 2000 | AA9: 1 | AG9: 1 | AH9: 1 | AI9: 1 | AJ9: 1 | AK9: 1 | AL9: 1 | AN9: 1 | AO9: 1 | AP9: 1 | AQ9: 1 | AR9: 1 | AS9: 1 | AU9: 1 | AV9: 1 | BC9: =SUM(AA9:BB9) -> 15 | BD9: =(BC9*X9)+Y9+Z9 -> 14050
B10: 1 | C10: ตั๋วเครื่องบิน | D10: 80 | E10: บินไปสำรวจหน้างานก่อนเสนอราคา | G10: 8000 | H10: K.Kowit | I10: 45802 | U10: 3 | V10: เฮียนิ้ง | W10: 18500 | X10: 616.66667 | Z10: =$Z$6*BC11 -> 1400 | BC10: =SUM(AA10:BB10) -> 0 | BD10: =(BC10*X10)+Y10+Z10 -> 1400
B11: 2 | C11: ตั๋วเครื่องบิน | D11: 80 | E11: บินไปประชุมกับลูกค้า Kick Off Meeting | G11: 3254 | H11: K.Kowit | I11: 45802 | U11: 4 | V11: หนึ่ง | W11: 15000 | X11: 500 | Z11: =$Z$6*BC12 -> 1400 | AG11: 1 | AH11: 1 | AI11: 1 | AJ11: 1 | AK11: 1 | AL11: 1 | AN11: 1 | AO11: 1 | AP11: 1 | AQ11: 1 | AR11: 1 | AS11: 1 | AU11: 1 | AV11: 1 | BC11: =SUM(AA11:BB11) -> 14 | BD11: =(BC11*X11)+Y11+Z11 -> 8400
B12: 3 | C12: ร้านเช่ารถ | D12: 80 | E12: ค่าเช่ารถ | G12: 4300 | H12: K.Kowit | I12: 45824 | U12: 5 | V12: แอล | W12: 14000 | X12: 466.66667 | Z12: =$Z$6*BC13 -> 0 | AG12: 1 | AH12: 1 | AI12: 1 | AJ12: 1 | AK12: 1 | AL12: 1 | AN12: 1 | AO12: 1 | AP12: 1 | AQ12: 1 | AR12: 1 | AS12: 1 | AU12: 1 | AV12: 1 | BC12: =SUM(AA12:BB12) -> 14 | BD12: =(BC12*X12)+Y12+Z12 -> 6533.3333
B13: 4 | C13: ร้านเช่ารถ | D13: 80 | E13: ค่าซ่อมรถเช่า | G13: 3000 | H13: K.Kowit | I13: 45824 | U13: 6 | V13: เวฟ | W13: 14000 | X13: 466.66667 | Z13: =$Z$6*BC14 -> 0 | BC13: =SUM(AA13:BB13) -> 0 | BD13: =(BC13*X13)+Y13+Z13 -> 0
B14: 5 | C14: โรงแรมบีทู | D14: 80 | E14: ค่าโรงแรม | G14: 855 | H14: K.Kowit | I14: 45826 | U14: 78 | V14: บาส | W14: 13000 | X14: 433.33333 | Z14: =$Z$6*BC15 -> 0 | BC14: =SUM(AA14:BB14) -> 0 | BD14: =(BC14*X14)+Y14+Z14 -> 0
B15: 6 | C15: โรงแรม UD | D15: 80 | E15: ค่าโรงแรม | G15: 850 | H15: K.Kowit | I15: 45826 | U15: 8 | V15: พี่มิ้ว(แอดมิน) | W15: 14000 | X15: 466.66667 | Z15: =$Z$6*BC16 -> 0 | BC15: =SUM(AA15:BB15) -> 0 | BD15: =(BC15*X15)+Y15+Z15 -> 0
B16: 7 | C16: บริษัท เค.ที.เอ็น เอ็นจิเนียริ่ง 1112 จำกัด (สำนักงานใหญ่) | D16: 20 | E16: งาน UG และลากสาย XLPE | G16: 2644700 | H16: K.Kowit | I16: 45824 | J16: PO2025060015 | U16: 9 | V16: พี่ดี๋ | W16: 50000 | X16: 1666.6667 | Z16: =$Z$6*BC17 -> 1400 | BC16: =SUM(AA16:BB16) -> 0 | BD16: =(BC16*X16)+Y16+Z16 -> 1400
B17: 8 | C17: บริษัท ทักษิณคอนกรีต จำกัด | D17: 10 | E17: ค่าเสาไฟ และคอร์น คอนกรีต | G17: 562400 | H17: K.Kowit | I17: 45841 | J17: PO2025070004 | U17: 10 | V17: พี่เจมส์ | W17: 17000 | X17: 566.66667 | Z17: =$Z$6*BC18 -> 0 | AG17: 1 | AH17: 1 | AI17: 1 | AJ17: 1 | AK17: 1 | AL17: 1 | AN17: 1 | AO17: 1 | AP17: 1 | AQ17: 1 | AR17: 1 | AS17: 1 | AU17: 1 | AV17: 1 | BC17: =SUM(AA17:BB17) -> 14 | BD17: =(BC17*X17)+Y17+Z17 -> 7933.3333
B18: 9 | D18: 80 | E18: เลี้ยงลูกค้า | G18: =1480+16280 -> 17760 | H18: K.Kowit | I18: 45867 | U18: 11 | V18: อั้ม | W18: 20000 | X18: 666.66667 | Z18: =$Z$6*BC19 -> 1400 | BC18: =SUM(AA18:BB18) -> 0 | BD18: =(BC18*X18)+Y18+Z18 -> 1400
B19: 10 | D19: 80 | E19: ทางด่วน เดินทางไปกลับอุดรธานี | G19: 145 | H19: K.Kowit | I19: 45867 | U19: 12 | V19: พี่เต้ย (รายวัน) | W19: 4950 | X19: 450 | Z19: =$Z$6*BC20 -> 0 | AG19: 1 | AH19: 1 | AI19: 1 | AJ19: 1 | AK19: 1 | AL19: 1 | AN19: 1 | AO19: 1 | AP19: 1 | AQ19: 1 | AR19: 1 | AS19: 1 | AU19: 1 | AV19: 1 | BC19: =SUM(AA19:BB19) -> 14 | BD19: =(BC19*X19)+Y19+Z19 -> 6300
B20: 11 | C20: ค่าน้ำมัน | D20: 80 | E20: ค่าน้ำมัน เดินทางไปกลับอุดรธานี | G20: 405 | H20: K.Kowit | I20: 45867 | U20: 13 | V20: จิว(ฝึกงาน) | W20: 3300 | X20: 300 | Z20: =$Z$6*BC21 -> 0 | BC20: =SUM(AA20:BB20) -> 0 | BD20: =(BC20*X20)+Y20+Z20 -> 0
B21: 12 | C21: ค่าน้ำมัน | D21: 80 | E21: ค่าน้ำมัน เดินทางไปกลับอุดรธานี | G21: 377 | H21: K.Kowit | I21: 45867 | U21: 14 | V21: บอล(ฝึกงาน300) | W21: 3300 | X21: 300 | Z21: =$Z$6*BC22 -> 0 | BC21: =SUM(AA21:BB21) -> 0 | BD21: =(BC21*X21)+Y21+Z21 -> 0
B22: 13 | C22: ค่าน้ำมัน | D22: 80 | E22: ค่าน้ำมัน เดินทางไปกลับอุดรธานี | G22: 380 | H22: K.Kowit | I22: 45867 | U22: 15 | V22: มุก(ฝึกงาน) | W22: 3300 | X22: 300 | Z22: =$Z$6*BC23 -> 0 | BC22: =SUM(AA22:BB22) -> 0 | BD22: =(BC22*X22)+Y22+Z22 -> 0
B23: 14 | C23: ค่าน้ำมัน | D23: 80 | E23: ค่าน้ำมัน เดินทางไปกลับอุดรธานี | G23: 400 | H23: K.Kowit | I23: 45867 | U23: 16 | V23: เบนซ์(ฝึกงาน300) | W23: 3300 | X23: 300 | Z23: =$Z$6*BC24 -> 1900 | BC23: =SUM(AA23:BB23) -> 0 | BD23: =(BC23*X23)+Y23+Z23 -> 1900
B24: 15 | C24: โรงแรม B2 | D24: 50 | E24: ค่าห้องพัก 1 | G24: 540 | H24: K.Kowit | I24: 45867 | U24: 17 | V24: เต๋า(ฝึกงาน) | W24: 2700 | X24: 300 | Z24: =$Z$6*BC25 -> 1900 | AA24: 1 | AB24: 1 | AC24: 1 | AD24: 1 | AE24: 1 | AG24: 1 | AH24: 1 | AI24: 1 | AJ24: 1 | AK24: 1 | AL24: 1 | AN24: 1 | AO24: 1 | AP24: 1 | AQ24: 1 | AR24: 1 | AS24: 1 | AU24: 1 | AV24: 1 | BC24: =SUM(AA24:BB24) -> 19 | BD24: =(BC24*X24)+Y24+Z24 -> 7600
B25: 16 | C25: โรงแรม B2 | D25: 50 | E25: ค่าห้องพัก 2 | G25: 620 | H25: K.Kowit | I25: 45867 | U25: 18 | V25: เฟียส(ฝึกงาน) | W25: 2200 | X25: 200 | Z25: =$Z$6*BC26 -> 1900 | AA25: 1 | AB25: 1 | AC25: 1 | AD25: 1 | AE25: 1 | AG25: 1 | AH25: 1 | AI25: 1 | AJ25: 1 | AK25: 1 | AL25: 1 | AN25: 1 | AO25: 1 | AP25: 1 | AQ25: 1 | AR25: 1 | AS25: 1 | AU25: 1 | AV25: 1 | BC25: =SUM(AA25:BB25) -> 19 | BD25: =(BC25*X25)+Y25+Z25 -> 5700
B26: 17 | C26: ซื้อของใช้ในไซด์ | D26: 10 | E26: ค่ารองเท้าและของใช้ในไซด์ | G26: 3559.06 | H26: K.Kowit | I26: 45867 | U26: 19 | V26: ฟลุ๊ค(ฝึกงาน) | W26: 1440 | X26: 180 | Z26: =$Z$6*BC27 -> 0 | AA26: 1 | AB26: 1 | AC26: 1 | AD26: 1 | AE26: 1 | AG26: 1 | AH26: 1 | AI26: 1 | AJ26: 1 | AK26: 1 | AL26: 1 | AN26: 1 | AO26: 1 | AP26: 1 | AQ26: 1 | AR26: 1 | AS26: 1 | AU26: 1 | AV26: 1 | BC26: =SUM(AA26:BB26) -> 19 | BD26: =(BC26*X26)+Y26+Z26 -> 3420
B27: 18 | U27: 20 | V27: เจมส์(ฝึกงาน) | W27: 2160 | X27: 180 | Z27: =$Z$6*BC28 -> 1400 | BC27: =SUM(AA27:BB27) -> 0 | BD27: =(BC27*X27)+Y27+Z27 -> 1400
B28: 19 | U28: 21 | V28: นาย(ฝึกงาน) | W28: 1980 | X28: 180 | Z28: =$Z$6*BC29 -> 0 | AG28: 1 | AH28: 1 | AI28: 1 | AJ28: 1 | AK28: 1 | AL28: 1 | AN28: 1 | AO28: 1 | AP28: 1 | AQ28: 1 | AR28: 1 | AS28: 1 | AU28: 1 | AV28: 1 | BC28: =SUM(AA28:BB28) -> 14 | BD28: =(BC28*X28)+Y28+Z28 -> 2520
B29: 20 | U29: 22 | V29: ดิว(ฝึกงาน) | W29: 1440 | X29: 180 | Z29: =$Z$6*BC30 -> 0 | BC29: =SUM(AA29:BB29) -> 0 | BD29: =(BC29*X29)+Y29+Z29 -> 0
B30: 21 | U30: 23 | V30: น็อต(ฝึกงาน) | W30: 2160 | X30: 180 | Z30: =$Z$6*BC31 -> 1400 | BC30: =SUM(AA30:BB30) -> 0 | BD30: =(BC30*X30)+Y30+Z30 -> 1400
B31: 22 | U31: 24 | V31: อาม(ฝึกงาน) | W31: 1980 | X31: 180 | Z31: =$Z$6*BC32 -> 0 | AG31: 1 | AH31: 1 | AI31: 1 | AJ31: 1 | AK31: 1 | AL31: 1 | AN31: 1 | AO31: 1 | AP31: 1 | AQ31: 1 | AR31: 1 | AS31: 1 | AU31: 1 | AV31: 1 | BC31: =SUM(AA31:BB31) -> 14 | BD31: =(BC31*X31)+Y31+Z31 -> 2520
B32: 23 | W32: =SUM(W8:W31) -> 262510 | BD32: =SUM(BD8:BD31) -> 89976.667
B33: 24
B34: 25
B35: 26
B36: 27
B37: 28
B38: 29
B39: 30
B40: 31
B41: 32
B42: 33
B43: 34
B44: 35
... B46: 37
F47: TOTAL COST | G47: =SUM(G9:G46) -> 3251545.1
F48: BALANCE | G48: =$C$6-G47 -> 2615555.9
F50: All BALANCE | G50: =G48/C6 -> 0.44580039
B52: Job. Code. | C52: ='All Job balance report'!B9 -> PKE-2500/002
B53: Contract Price | C53: ='All Job balance report'!G9 -> 7000
B54: No. | C54: Code | E54: Description | F54: Budget | G54: Expense Record | H54: Balance | I54: Remark
B56: 1 | C56: 10 | E56: MATERIALS | F56: =L57 -> 2542401 | G56: =SUMIF($D$10:$D$46,$C$56,$G$10:$G$46) -> 565959.06 | H56: =F56-G56 -> 1976441.9 | L56: 3142401 | M56: 2644700
B57: 2 | C57: 20 | E57: SUB CONTRACTOR | F57: =M56+80000 -> 2724700 | G57: =SUMIF($D$10:$D$46,$C$57,$G$10:$G$46) -> 2644700 | H57: =F57-G57 -> 80000 | L57: =L56-SUM(F58:F63) -> 2542401
B58: 3 | C58: 30 | E58: HEAVY EQUIPMENT | F58: 160000 | G58: =SUMIF($D$10:$D$46,$C$58,$G$10:$G$46) -> 0 | H58: =F58-G58 -> 160000
B59: 4 | C59: 40 | E59: RENTAL | F59: 30000 | G59: =SUMIF($D$10:$D$46,$C$59,$G$10:$G$46) -> 0 | H59: =F59-G59 -> 30000
B60: 5 | C60: 50 | E60: STAFF EXPENSE | F60: 300000 | G60: =SUMIF($D$10:$D$46,$C$60,$G$10:$G$46) -> 1160 | H60: =F60-G60 -> 298840
B61: 6 | C61: 60 | E61: OFFICE EXPENSE | F61: 20000 | G61: =SUMIF($D$10:$D$46,$C$61,$G$10:$G$46) -> 0 | H61: =F61-G61 -> 20000
B62: 7 | C62: 70 | E62: ENTERTAIN | F62: 30000 | G62: =SUMIF($D$10:$D$46,$C$62,$G$10:$G$46) -> 0 | H62: =F62-G62 -> 30000
B63: 8 | C63: 80 | E63: MISCELLANEOUS | F63: 60000 | G63: =SUMIF($D$10:$D$46,$C$63,$G$10:$G$46) -> 39726 | H63: =F63-G63 -> 20274
E64: Total | F64: =SUM(F56:F63) -> 5867101 | G64: =SUM(G56:G63) -> 3251545.1 | H64: =SUM(H56:H63) -> 2615555.9
E65: % Profit | F65: =((C53-F64)/C53) -> -837.15729
E66: Total Profit | F66: =F65*C53 -> -5860101
E67: Gross Profit | F67: =C53-G64 -> -3244545.1
F69: 0.05
F70: =F67*F69 -> -162227.25

Sheet PPC-001 Nestle
B1: Factory/Company | C1: Prime Power Construction | H1: Start Date | I1: 45778
B2: Project Name | C2: 22kV. Pole installation | H2: Sale Up Date
B3: Job Code. | C3: =C63 -> SUT-2500/001
B4: Quotation No. | E4: PROJECT BUDGET RECORD | H4: INVOICE (%) | I4: 0 | AA4: 45811 | AB4: 45812 | AC4: 45813 | AD4: 45814 | AE4: 45815 | AF4: 45816 | AG4: 45817 | AH4: 45818 | AI4: 45819 | AJ4: 45820 | AK4: 45821 | AL4: 45822 | AM4: 45823 | AN4: 45824 | AO4: 45825 | AP4: 45826 | AQ4: 45827 | AR4: 45828 | AS4: 45829 | AT4: 45830 | AU4: 45831 | AV4: 45832 | AW4: 45833 | BA4: 45834 | BB4: 45835 | BC4: 45836 | BD4: 45837 | BE4: 45838 | BF4: 45839 | BG4: 45840 | BH4: 45841 | BI4: 45842 | BJ4: 45843 | BK4: 45844 | BL4: 45845 | BM4: 45846 | BN4: 45847 | BO4: 45848 | BP4: 45849 | BQ4: 45850 | BR4: 45851 | BS4: 45852 | BT4: 45853
B5: Contract Price | C5: =C64 -> 37500
B6: Budget Price | C6: =F75 -> 1397000 | Z6: 100 | AZ6: 100
B7: PROFIT | C7: =(C5-C6)/C5 -> -36.253333 | D7: ACTUAL | E7: 1 | U7: No. | V7: Name | W7: Salary | X7: S per Day | Y7: ค่าโทรศัพท์ | Z7: ค่าอื่นๆ | AA7: =SUM(AA8:AA31) -> 4 | AB7: =SUM(AB8:AB31) -> 3 | AC7: =SUM(AC8:AC31) -> 3 | AD7: =SUM(AD8:AD31) -> 3 | AE7: =SUM(AE8:AE31) -> 3 | AF7: =SUM(AF8:AF31) -> 0 | AG7: =SUM(AG8:AG31) -> 10 | AH7: =SUM(AH8:AH31) -> 10 | ... AW7: =SUM(AW8:AW31) -> 8 | BA7: =SUM(BA8:BA31) -> 8 | BB7: =SUM(BB8:BB31) -> 8 | BC7: =SUM(BC8:BC31) -> 8 | BD7: =SUM(BD8:BD31) -> 0 | BE7: =SUM(BE8:BE31) -> 7 | BF7: =SUM(BF8:BF31) -> 7 | BG7: =SUM(BG8:BG31) -> 6 | BH7: =SUM(BH8:BH31) -> 7 | ... BT7: =SUM(BT8:BT31) -> 7
B8: No. | C8: Vendor Name | D8: Material Number | E8: Description | F8: Text/Quo.No. | G8: Amount | H8: Updated By | I8: Date | J8: PO | U8: 1 | V8: พี่เอ็ก | W8: 31500 | X8: 1050 | Y8: 1400 | AG8: 1 | AH8: 1 | AI8: 1 | AJ8: 1 | AK8: 1 | AL8: 1 | AN8: 1 | AO8: 1 | AP8: 1 | AQ8: 1 | AR8: 1 | AS8: 1 | AU8: 1 | AV8: 1 | AW8: 1 | AX8: =SUM(AA8:AW8) -> 15 | AY8: =W8+$Y8+$Z8 -> 32900 | AZ8: =$AZ$6*BU8 -> 1600 | BA8: 1 | BB8: 1 | BC8: 1 | BE8: 1 | BF8: 1 | BG8: 1 | BH8: 1 | BI8: 1 | BJ8: 1 | BL8: 1 | BM8: 1 | BN8: 1 | BP8: 1 | BQ8: 1 | BS8: 1 | BT8: 1 | BU8: =SUM(BA8:BT8) -> 16 | BV8: =(BU8*$X8)+$Y8+$AZ8 -> 19800
U9: 2 | V9: เอลฟ์ | W9: 21300 | X9: 710 | Y9: 1400 | Z9: 2000 | AA9: 1 | AG9: 1 | AH9: 1 | AI9: 1 | AJ9: 1 | AK9: 1 | AL9: 1 | AN9: 1 | AO9: 1 | AP9: 1 | AQ9: 1 | AR9: 1 | AX9: =SUM(AA9:AW9) -> 12 | AY9: =(AX9*$X9)+$Y9+$Z9 -> 11920 | AZ9: =$AZ$6*BU9 -> 0 | BU9: =SUM(BA9:BT9) -> 0 | BV9: =(BU9*$X9)+$Y9+$AZ9 -> 1400
B10: 1 | C10: Siriprapa | D10: 10 | E10: PQM meter / EDMI Panel | F10: 68/05-05A-R1 | G10: 222000 | H10: K.Kowit | U10: 3 | V10: เฮียนิ้ง | W10: 18500 | X10: 616.66667 | Z10: =$Z$6*AX11 -> 1500 | AX10: =SUM(AA10:AW10) -> 0 | AZ10: =$AZ$6*BU10 -> 0 | BU10: =SUM(BA10:BT10) -> 0 | BV10: =(BU10*$X10)+$Y10+$AZ10 -> 0
B11: 2 | C11: Precise | D11: 10 | E11: อุปกรณ์ HV | F11: PO2025050018 | G11: 316060 | H11: K.Kowit | U11: 4 | V11: หนึ่ง | W11: 15000 | X11: 500 | Z11: =$Z$6*AX12 -> 1500 | AG11: 1 | AH11: 1 | AI11: 1 | AJ11: 1 | AK11: 1 | AL11: 1 | AN11: 1 | AO11: 1 | AP11: 1 | AQ11: 1 | AR11: 1 | AS11: 1 | AU11: 1 | AV11: 1 | AW11: 1 | AX11: =SUM(AA11:AW11) -> 15 | AY11: =W11+$Y11+$Z11 -> 16500 | AZ11: =$AZ$6*BU11 -> 1600 | BA11: 1 | BB11: 1 | BC11: 1 | BE11: 1 | BF11: 1 | BG11: 1 | BH11: 1 | BI11: 1 | BJ11: 1 | BL11: 1 | BM11: 1 | BN11: 1 | BP11: 1 | BQ11: 1 | BS11: 1 | BT11: 1 | BU11: =SUM(BA11:BT11) -> 16 | BV11: =(BU11*$X11)+$Y11+$AZ11 -> 9600
B12: 3 | C12: บริษัท ธราดล 2555 จำกัด | D12: 20 | E12: จ้างตัดคอนกรีต | F12: PO2025060004 | G12: 8800 | H12: K.Kowit | U12: 5 | V12: แอล | W12: 14000 | X12: 466.66667 | Z12: =$Z$6*AX13 -> 0 | AG12: 1 | AH12: 1 | AI12: 1 | AJ12: 1 | AK12: 1 | AL12: 1 | AN12: 1 | AO12: 1 | AP12: 1 | AQ12: 1 | AR12: 1 | AS12: 1 | AU12: 1 | AV12: 1 | AW12: 1 | AX12: =SUM(AA12:AW12) -> 15 | AY12: =(AX12*$X12)+$Y12+$Z12 -> 7000 | AZ12: =$AZ$6*BU12 -> 1600 | BA12: 1 | BB12: 1 | BC12: 1 | BE12: 1 | BF12: 1 | BG12: 1 | BH12: 1 | BI12: 1 | BJ12: 1 | BL12: 1 | BM12: 1 | BN12: 1 | BP12: 1 | BQ12: 1 | BS12: 1 | BT12: 1 | BU12: =SUM(BA12:BT12) -> 16 | BV12: =(BU12*$X12)+$Y12+$AZ12 -> 9066.6667
B13: 4 | C13: หจก. บีเอ็ม แอนด์ เบนซ์ ค้าวัสดุ (อยุธยา) | D13: 10 | F13: 999INV-2506-0160 | G13: 1046.73 | H13: K.Kowit | U13: 6 | V13: เวฟ | W13: 14000 | X13: 466.66667 | Z13: =$Z$6*AX14 -> 0 | AX13: =SUM(AA13:AW13) -> 0 | AZ13: =$AZ$6*BU13 -> 0 | BU13: =SUM(BA13:BT13) -> 0 | BV13: =(BU13*$X13)+$Y13+$AZ13 -> 0
B14: 5 | C14: เช่าเครื่องตัดปูน | D14: 40 | F14: QR-00184228 | G14: 1121.5 | H14: K.Kowit | U14: 78 | V14: บาส | W14: 13000 | X14: 433.33333 | Z14: =$Z$6*AX15 -> 0 | AX14: =SUM(AA14:AW14) -> 0 | AZ14: =$AZ$6*BU14 -> 0 | BU14: =SUM(BA14:BT14) -> 0 | BV14: =(BU14*$X14)+$Y14+$AZ14 -> 0
B15: 6 | C15: ส.อรุน | D15: 10 | E15: เสาคอนกรีต | F15: QT-25001984 | G15: 235239.5 | H15: K.Kowit | U15: 8 | V15: พี่มิ้ว(แอดมิน) | W15: 14000 | X15: 466.66667 | Z15: =$Z$6*AX16 -> 0 | AX15: =SUM(AA15:AW15) -> 0 | AZ15: =$AZ$6*BU15 -> 0 | BU15: =SUM(BA15:BT15) -> 0 | BV15: =(BU15*$X15)+$Y15+$AZ15 -> 0
B16: 7 | C16: ซ่อมรถ | D16: 30 | E16: ซ่อมรถสว่าน | F16: BL2025060012 | G16: 17500 | H16: K.Kowit | U16: 9 | V16: พี่ดี๋ | W16: 50000 | X16: 1666.6667 | Z16: =$Z$6*AX17 -> 0 | AX16: =SUM(AA16:AW16) -> 0 | AZ16: =$AZ$6*BU16 -> 0 | BU16: =SUM(BA16:BT16) -> 0 | BV16: =(BU16*$X16)+$Y16+$AZ16 -> 0
B17: 8 | C17: ร้านนครสวรรค์ | D17: 10 | E17: หัวเพชร เจาะดิน | G17: 3500 | H17: K.Kowit | U17: 10 | V17: พี่เจมส์ | W17: 17000 | X17: 566.66667 | Z17: =$Z$6*AX18 -> 0 | AX17: =SUM(AA17:AW17) -> 0 | AY17: =(AX17*$X17)+$Y17+$Z17 -> 0 | AZ17: =$AZ$6*BU17 -> 0 | BU17: =SUM(BA17:BT17) -> 0 | BV17: =(BU17*$X17)+$Y17+$AZ17 -> 0
B18: 9 | C18: ร้านค้าอุปกรณ์ก่อสร้าง | D18: 10 | E18: ชะแลง ไม้กวาด กรรไกรตัดเหล็ก | G18: 1093.46 | H18: K.Kowit | U18: 11 | V18: อั้ม | W18: 20000 | X18: 666.66667 | Z18: =$Z$6*AX19 -> 1500 | AX18: =SUM(AA18:AW18) -> 0 | AZ18: =$AZ$6*BU18 -> 0 | BU18: =SUM(BA18:BT18) -> 0 | BV18: =(BU18*$X18)+$Y18+$AZ18 -> 0
B19: 10 | C19: ร้านค้าอุปกรณ์ก่อสร้าง | D19: 10 | E19: กระสอบปุ๋ย | G19: 168.22 | H19: K.Kowit | U19: 12 | V19: พี่เต้ย (รายวัน) | W19: 4950 | X19: 450 | Z19: =$Z$6*AX20 -> 0 | AG19: 1 | AH19: 1 | AI19: 1 | AJ19: 1 | AK19: 1 | AL19: 1 | AN19: 1 | AO19: 1 | AP19: 1 | AQ19: 1 | AR19: 1 | AS19: 1 | AU19: 1 | AV19: 1 | AW19: 1 | AX19: =SUM(AA19:AW19) -> 15 | AY19: =(AX19*$X19)+$Y19+$Z19 -> 6750 | AZ19: =$AZ$6*BU19 -> 1500 | BA19: 1 | BB19: 1 | BC19: 1 | BE19: 1 | BF19: 1 | BH19: 1 | BI19: 1 | BJ19: 1 | BL19: 1 | BM19: 1 | BN19: 1 | BP19: 1 | BQ19: 1 | BS19: 1 | BT19: 1 | BU19: =SUM(BA19:BT19) -> 15 | BV19: =(BU19*$X19)+$Y19+$AZ19 -> 8250
B20: 11 | C20: SSI | D20: 10 | E20: ชุด KIT ต่อสาย 3M | G20: 2200 | H20: K.Kowit | U20: 13 | V20: จิว(ฝึกงาน) | W20: 3300 | X20: 300 | Z20: =$Z$6*AX21 -> 0 | AX20: =SUM(AA20:AW20) -> 0 | AZ20: =$AZ$6*BU20 -> 0 | BU20: =SUM(BA20:BT20) -> 0 | BV20: =(BU20*$X20)+$Y20+$AZ20 -> 0
B21: 12 | C21: ฮาร์ดแวร์เฮาส์ | D21: 10 | E21: เครื่องมือต่อสายไฟ | G21: 1102.1 | H21: K.Kowit | U21: 14 | V21: บอล(ฝึกงาน300) | W21: 3300 | X21: 300 | Z21: =$Z$6*AX22 -> 0 | AX21: =SUM(AA21:AW21) -> 0 | AZ21: =$AZ$6*BU21 -> 0 | BU21: =SUM(BA21:BT21) -> 0 | BV21: =(BU21*$X21)+$Y21+$AZ21 -> 0
B22: 13 | C22: ณัฐภูมิ อีควิปเม้นท์ จำกัด | D22: 10 | E22: ลูกถ้วยหัวเสา และเหล็ก คอร์น | G22: 210608.1 | H22: K.Kowit | U22: 15 | V22: มุก(ฝึกงาน) | W22: 3300 | X22: 300 | Z22: =$Z$6*AX23 -> 0 | AX22: =SUM(AA22:AW22) -> 0 | AZ22: =$AZ$6*BU22 -> 0 | BU22: =SUM(BA22:BT22) -> 0 | BV22: =(BU22*$X22)+$Y22+$AZ22 -> 0
B23: 14 | C23: กิจพูนชัย จำกัด | D23: 10 | E23: น๊อตประกอบหัวเสา | G23: 42061 | H23: K.Kowit | U23: 16 | V23: เบนซ์(ฝึกงาน300) | W23: 3300 | X23: 300 | Z23: =$Z$6*AX24 -> 1700 | AX23: =SUM(AA23:AW23) -> 0 | AZ23: =$AZ$6*BU23 -> 0 | BU23: =SUM(BA23:BT23) -> 0 | BV23: =(BU23*$X23)+$Y23+$AZ23 -> 0
B24: 15 | D24: 30 | E24: ค่าซ่อมรถลุงชาย | G24: 8000 | H24: K.Kowit | U24: 17 | V24: เต๋า(ฝึกงาน) | W24: 2700 | X24: 300 | Z24: =$Z$6*AX25 -> 2000 | AA24: 1 | AB24: 1 | AC24: 1 | AD24: 1 | AE24: 1 | AG24: 1 | AH24: 1 | AI24: 1 | AJ24: 1 | AK24: 1 | AL24: 1 | AN24: 1 | AO24: 1 | AP24: 1 | AQ24: 1 | AR24: 1 | AS24: 1 | AX24: =SUM(AA24:AW24) -> 17 | AY24: =(AX24*$X24)+$Y24+$Z24 -> 7100 | AZ24: =$AZ$6*BU24 -> 0 | BU24: =SUM(BA24:BT24) -> 0 | BV24: =(BU24*$X24)+$Y24+$AZ24 -> 0
B25: 16 | C25: ค่าแรง | D25: 50 | E25: ค่าแรงคนทำงานทั้งหมด | G25: =AY34 -> 159886.67 | H25: K.Kowit | U25: 18 | V25: เฟียส(ฝึกงาน) | W25: 2200 | X25: 200 | Z25: =$Z$6*AX26 -> 2000 | AA25: 1 | AB25: 1 | AC25: 1 | AD25: 1 | AE25: 1 | AG25: 1 | AH25: 1 | AI25: 1 | AJ25: 1 | AK25: 1 | AL25: 1 | AN25: 1 | AO25: 1 | AP25: 1 | AQ25: 1 | AR25: 1 | AS25: 1 | AU25: 1 | AV25: 1 | AW25: 1 | AX25: =SUM(AA25:AW25) -> 20 | AY25: =(AX25*$X25)+$Y25+$Z25 -> 6000 | AZ25: =$AZ$6*BU25 -> 1600 | BA25: 1 | BB25: 1 | BC25: 1 | BE25: 1 | BF25: 1 | BG25: 1 | BH25: 1 | BI25: 1 | BJ25: 1 | BL25: 1 | BM25: 1 | BN25: 1 | BP25: 1 | BQ25: 1 | BS25: 1 | BT25: 1 | BU25: =SUM(BA25:BT25) -> 16 | BV25: =(BU25*$X25)+$Y25+$AZ25 -> 4800
B26: 17 | C26: บ้านดินทอง | D26: 50 | E26: ค่าที่พัก 1 เดือน | G26: 13500 | H26: K.Kowit | I26: เริ่มพักวันที่ 9/6/2025 | U26: 19 | V26: ฟลุ๊ค(ฝึกงาน) | W26: 1440 | X26: 180 | Z26: =$Z$6*AX27 -> 0 | AA26: 1 | AB26: 1 | AC26: 1 | AD26: 1 | AE26: 1 | AG26: 1 | AH26: 1 | AI26: 1 | AJ26: 1 | AK26: 1 | AL26: 1 | AN26: 1 | AO26: 1 | AP26: 1 | AQ26: 1 | AR26: 1 | AS26: 1 | AU26: 1 | AV26: 1 | AW26: 1 | AX26: =SUM(AA26:AW26) -> 20 | AY26: =(AX26*$X26)+$Y26+$Z26 -> 3600 | AZ26: =$AZ$6*BU26 -> 1600 | BA26: 1 | BB26: 1 | BC26: 1 | BE26: 1 | BF26: 1 | BG26: 1 | BH26: 1 | BI26: 1 | BJ26: 1 | BL26: 1 | BM26: 1 | BN26: 1 | BP26: 1 | BQ26: 1 | BS26: 1 | BT26: 1 | BU26: =SUM(BA26:BT26) -> 16 | BV26: =(BU26*$X26)+$Y26+$AZ26 -> 4480
B27: 18 | C27: Precise | D27: 10 | E27: Dropfuse 200A | F27: PO2025060020 / QNT-2525-02635 | G27: 13800 | H27: K.Kowit | I27: 45850 | U27: 20 | V27: เจมส์(ฝึกงาน) | W27: 2160 | X27: 180 | Z27: =$Z$6*AX28 -> 1500 | AX27: =SUM(AA27:AW27) -> 0 | AZ27: =$AZ$6*BU27 -> 0 | BU27: =SUM(BA27:BT27) -> 0 | BV27: =(BU27*$X27)+$Y27+$AZ27 -> 0
B28: 19 | C28: บริษัท สุขี เครน จำกัด | D28: 30 | E28: ค่าซ่อมเกียร์ฝาก สาย PTO พร้อมก้ามปู น้ำมันเกียร์ | F28: BL2025060026 | G28: 11500 | H28: K.Kowit | I28: 45850 | U28: 21 | V28: นาย(ฝึกงาน) | W28: 1980 | X28: 180 | Z28: =$Z$6*AX29 -> 0 | AG28: 1 | AH28: 1 | AI28: 1 | AJ28: 1 | AK28: 1 | AL28: 1 | AN28: 1 | AO28: 1 | AP28: 1 | AQ28: 1 | AR28: 1 | AS28: 1 | AU28: 1 | AV28: 1 | AW28: 1 | AX28: =SUM(AA28:AW28) -> 15 | AY28: =(AX28*$X28)+$Y28+$Z28 -> 2700 | AZ28: =$AZ$6*BU28 -> 1600 | BA28: 1 | BB28: 1 | BC28: 1 | BE28: 1 | BF28: 1 | BG28: 1 | BH28: 1 | BI28: 1 | BJ28: 1 | BL28: 1 | BM28: 1 | BN28: 1 | BP28: 1 | BQ28: 1 | BS28: 1 | BT28: 1 | BU28: =SUM(BA28:BT28) -> 16 | BV28: =(BU28*$X28)+$Y28+$AZ28 -> 4480
B29: 20 | C29: บริษัท อรุณค้าเหล็ก จำกัด | D29: 10 | E29: เหล็กซีรางน้ำ 75มม. | F29: J680702015 | G29: 2310 | H29: K.Kowit | I29: 45850 | U29: 22 | V29: ดิว(ฝึกงาน) | W29: 1440 | X29: 180 | Z29: =$Z$6*AX30 -> 0 | AX29: =SUM(AA29:AW29) -> 0 | AZ29: =$AZ$6*BU29 -> 0 | BU29: =SUM(BA29:BT29) -> 0 | BV29: =(BU29*$X29)+$Y29+$AZ29 -> 0
B30: 21 | C30: บริษัท ไทยถาวรรุ่งโรจน์ จำกัด | D30: 10 | E30: ท่อน้ำ HDPE และข้อต่อ | G30: 799 | H30: K.Kowit | I30: 45850 | U30: 23 | V30: น็อต(ฝึกงาน) | W30: 2160 | X30: 180 | Z30: =$Z$6*AX31 -> 1500 | AX30: =SUM(AA30:AW30) -> 0 | AZ30: =$AZ$6*BU30 -> 0 | BU30: =SUM(BA30:BT30) -> 0 | BV30: =(BU30*$X30)+$Y30+$AZ30 -> 0
B31: 22 | C31: หจก. บีเอ็ม แอนด์ เบนซ์ ค้าวัสดุ (อยุธยา) | D31: 10 | E31: อุปกรณ์ทั่วไป เครื่องมือ | G31: 450 | H31: K.Kowit | I31: 45850 | U31: 24 | V31: อาม(ฝึกงาน) | W31: 1980 | X31: 180 | Z31: =$Z$6*AX32 -> 0 | AG31: 1 | AH31: 1 | AI31: 1 | AJ31: 1 | AK31: 1 | AL31: 1 | AN31: 1 | AO31: 1 | AP31: 1 | AQ31: 1 | AR31: 1 | AS31: 1 | AU31: 1 | AV31: 1 | AW31: 1 | AX31: =SUM(AA31:AW31) -> 15 | AY31: =(AX31*$X31)+$Y31+$Z31 -> 2700 | AZ31: =$AZ$6*BU31 -> 300 | BA31: 1 | BB31: 1 | BC31: 1 | BU31: =SUM(BA31:BT31) -> 3 | BV31: =(BU31*$X31)+$Y31+$AZ31 -> 840
B32: 23 | C32: หจก. บีเอ็ม แอนด์ เบนซ์ ค้าวัสดุ (อยุธยา) | D32: 10 | E32: อุปกรณ์ทั่วไป เครื่องมือ | G32: 320 | H32: K.Kowit | I32: 45850 | AY32: =SUM(AY8:AY31) -> 97170 | BV32: =SUM(BV8:BV31) -> 62716.667
B33: 24 | C33: ร้านขายของแถวบางคล้า | D33: 10 | E33: Snake guard | G33: 15000 | H33: K.Kowit | I33: 45850 | O33: 38060.938 | P33: 38060.938 | Q33: 2013814174 | R33: กสิกร (ถวิล)
B34: 25 | D34: 70 | E34: ค่าเลี้ยงข้าวลูกค้า | G34: 5610 | H34: K.Kowit | I34: 45850 | O34: 20268.75 | P34: 20268.75 | Q34: 1152673074 | R34: กสิกร(สิรภพ) | AY34: =AY32+BV32 -> 159886.67
B35: 26 | D35: 20 | E35: ค่าจ้างทีมงานเร่งด่วนสำหรับงานชัตดาวน์ | G35: 15000 | H35: K.Kowit | I35: ทำงานวันที่ 12/08/2025 | O35: 17275 | P35: 17275 | Q35: 1951329262 | R35: กสิกร (อดิศักดิ์)
B36: 27 | D36: 20 | E36: ค่า Setting Relay | G36: 5000 | H36: K.Kowit | I36: 45850 | O36: 6693.75 | P36: 6693.75 | Q36: 0461948944 | R36: กสิกร(ดำรงศักดิ์ นิวาสรัมย์)
B37: 28 | D37: 70 | E37: เลี้ยงปิดไซด์ | G37: 7000 | H37: K.Kowit | I37: 45850 | N37: 2 | O37: 6671.875 | P37: 13343.75 | Q37: 0893870970 | R37: กสิกร(นันทพร) แฟน
B38: 29 | C38: N.R.E | D38: 10 | E38: ค่าหางปลา และ กราวด์ Rod | G38: 3104.81 | H38: K.Kowit | I38: 45850 | N38: 2 | O38: 5322.5 | P38: 10645 | Q38: 0623566064 | R38: กสิกร (เกียรติยศ)
B39: 30 | C39: บริษัท พนัส เอ็นจิเนียร์ จำกัด (สำนักงานใหญ่) | D39: 10 | E39: สลิง 25 | G39: 4080 | H39: K.Kowit | I39: 45850 | N39: 2 | O39: 3315 | P39: 6630 | Q39: 2048224310 | R39: กสิกร (ศตวรรช)
B40: 31 | C40: หจก. บีเอ็ม แอนด์ เบนซ์ ค้าวัสดุ (อยุธยา) | D40: 10 | E40: โฮซอ | G40: 186.92 | H40: K.Kowit | I40: 45850 | N40: 2 | O40: 4502.75 | P40: 9005.5 | Q40: 2093776650 | R40: กสิกร (จิรวัฒน์)
B41: 32 | C41: หจก. บีเอ็ม แอนด์ เบนซ์ ค้าวัสดุ (อยุธยา) | D41: 10 | E41: ปากกา คัดเตอร์ ฉากจับไม้ | G41: 112.5 | H41: K.Kowit | I41: 45850 | P41: 121922.69
B42: 33 | C42: หจก. บีเอ็ม แอนด์ เบนซ์ ค้าวัสดุ (อยุธยา) | D42: 10 | E42: Box ยางพร้อมเต้ารับ | G42: 420.56 | H42: K.Kowit | I42: 45850
B43: 34 | C43: บริษัท ไทยถาวรรุ่งโรจน์ จำกัด | D43: 10 | E43: เหล็กเส้น และลวดผูกเหล็ก | G43: 1869.16 | H43: K.Kowit | I43: 45850
B44: 35 | D44: 10 | E44: ค่าคอนกรีต | G44: 6000 | H44: K.Kowit | I44: 45859
B45: 36 | D45: 10 | E45: ค่าสเนกการ์ด | G45: 11800 | H45: K.Kowit | I45: 45852
B46: 37 | C46: ช่างน้อย | D46: 20 | E46: อบรมเซฟตี้ ช่างน้อย | G46: 6000 | H46: K.Kowit | I46: 45860
B47: 38 | D47: 20 | E47: ค่า Site test | G47: 5000 | H47: K.Kowit | I47: 45850
B48: 39
F58: TOTAL COST | G58: =SUM(G9:G57) -> 1359250.2
F59: BALANCE | G59: =$C$6-G58 -> 37749.773
F61: All BALANCE | G61: =G59/C6 -> 0.027022028
B63: Job. Code. | C63: ='All Job balance report'!B8 -> SUT-2500/001
B64: Contract Price | C64: ='All Job balance report'!G8 -> 37500
B65: No. | C65: Code | E65: Description | F65: Budget | G65: Expense Record | H65: Balance | I65: Remark
B67: 1 | C67: 10 | E67: MATERIALS | F67: 1200000 | G67: =SUMIF($D$10:$D$57,$C$67,$G$10:$G$57) -> 1095332.1 | H67: =F67-G67 -> 104667.94
B68: 2 | C68: 20 | E68: SUB CONTRACTOR | F68: 10000 | G68: =SUMIF($D$10:$D$57,$C$68,$G$10:$G$57) -> 39800 | H68: =F68-G68 -> -29800
B69: 3 | C69: 30 | E69: HEAVY EQUIPMENT | F69: 97000 | G69: =SUMIF($D$10:$D$57,$C$69,$G$10:$G$57) -> 37000 | H69: =F69-G69 -> 60000
B70: 4 | C70: 40 | E70: RENTAL | F70: 0 | G70: =SUMIF($D$10:$D$57,$C$70,$G$10:$G$57) -> 1121.5 | H70: =F70-G70 -> -1121.5
B71: 5 | C71: 50 | E71: STAFF EXPENSE | F71: 90000 | G71: =SUMIF($D$10:$D$57,$C$71,$G$10:$G$57) -> 173386.67 | H71: =F71-G71 -> -83386.667
B72: 6 | C72: 60 | E72: OFFICE EXPENSE | F72: 0 | G72: =SUMIF($D$10:$D$57,$C$72,$G$10:$G$57) -> 0 | H72: =F72-G72 -> 0
B73: 7 | C73: 70 | E73: ENTERTAIN | F73: 0 | G73: =SUMIF($D$10:$D$57,$C$73,$G$10:$G$57) -> 12610 | H73: =F73-G73 -> -12610
B74: 8 | C74: 80 | E74: MISCELLANEOUS | F74: 0 | G74: =SUMIF($D$10:$D$57,$C$74,$G$10:$G$57) -> 0 | H74: =F74-G74 -> 0
E75: Total | F75: =SUM(F67:F74) -> 1397000 | G75: =SUM(G67:G74) -> 1359250.2 | H75: =SUM(H67:H74) -> 37749.773
E76: % Profit | F76: =((C64-F75)/C64) -> -36.253333
E77: Total Profit | F77: =F76*C64 -> -1359500
E78: Gross Profit | F78: =C64-G75 -> -1321750.2 | G78: =F78/C64 -> -35.246673
F80: 0.05
F81: =F78*F80 -> -66087.511

Sheet PC-006 JOWLE
B1: Factory/Company | C1: PROCHAIN | H1: Start Date | I1: 45336
B2: Project Name | C2: JOWLE Factory | H2: Sale Up Date
B3: Job Code. | C3: =C71 -> UNT-2500/001
B4: Quotation No. | E4: PROJECT BUDGET RECORD | H4: INVOICE (%) | I4: 0
B5: Contract Price | C5: =C72 -> 371100
B6: Budget Price | C6: =F83 -> 9862000
B7: PROFIT | C7: =(C5-C6)/C5 -> -25.575047 | D7: ACTUAL | E7: 1
B8: No. | C8: Vendor Name | D8: Material Number | E8: Description | F8: Text/Quo.No. | G8: Amount | H8: Updated By | I8: Date | J8: PO
B10: 1 | C10: NRE | D10: 10 | E10: สายไฟ FRC สำหรับระบบ Fire Alarm | F10: SUV-250103489 | G10: 78720 | H10: K.Kowit | I10: 45735
B11: 2 | C11: บริษัท คว๊อด อิเลคทริค จำกัด | D11: 10 | E11: หม้อแปลงไฟฟ้าระบบระบายความร้อนด้วยน้ำมัน | F11: QT20250304150 | G11: 395000 | H11: k.milk | I11: 45748
B12: 3 | C12: N.R.E | D12: 10 | E12: สาย Max-foh-l 1x2.5 sqmm. | F12: SUV-250103784 | G12: 78720 | H12: k.milk | I12: 45748
B13: 4 | C13: เมธีกุล จำกัด | D13: 10 | E13: สายไฟ THW 1.5 MM^2 | F13: QT68030968 | G13: 5854.8 | H13: k.milk | I13: 45748
B14: 5 | C14: เมธีกุล จำกัด | D14: 10 | E14: 60227 IEC01 THW | F14: QT68030868 | G14: 2114343.7 | H14: k.milk | I14: 45748
B15: 6 | C15: สรรพากร | D15: 60 | E15: Duty Stamp | G15: 13800 | H15: K.Kowit
B16: 7 | C16: ค่าแรงพี่แมน | D16: 20 | E16: ค่าแรงพี่แมนสำหรับทั้งโครงการ | G16: 1150000 | H16: K.Kowit | I16: 45769
B17: 8 | C17: N.R.E | D17: 10 | E17: Wireway 100x100 | F17: SUV-250106361 | G17: 106275 | H17: K.Kowit | I17: 45806 | J17: PO2025050024
B18: 9 | C18: N.R.E | D18: 10 | E18: สายทนไฟ | F18: SUV-250106381 | G18: 23616 | H18: K.Kowit | I18: 45803
B19: 10 | C19: บริษัทไทคิน สตีล จำกัด | D19: 10 | E19: สตัด หัวน๊อต | F19: QT0036013 | G19: 9705.16 | H19: K.Kowit | I19: 45803
B20: 11 | C20: N.R.E | D20: 10 | E20: THW 2.5 Sq.mm. | F20: SUV-250106333 | G20: 30030 | H20: K.Kowit | I20: 45803
B21: 12 | C21: N.R.E | D21: 10 | E21: ท่ออ่อน ขาว | F21: SUV-250106291 | G21: 4755 | H21: K.Kowit | I21: 45803
B22: 13 | C22: บริษัทไทคิน สตีล จำกัด | D22: 10 | E22: สกรูเกลียวเหล็ก 7x1.1/2" | F22: QT0035903 | G22: 1044.75 | H22: K.Kowit | I22: 45798
B23: 14 | C23: N.R.E | D23: 10 | E23: ท่ออ่อน ขาว | F23: SUV-250105440 | G23: 25107 | H23: K.Kowit | I23: 45783 | J23: PO2025050002
B24: 15 | C24: N.R.E | D24: 10 | E24: ท่อ EMT 1/2" | F24: SUV-250107305 | G24: 25935 | H24: K.Kowit | I24: 45825 | J24: PO2025060017
B25: 16 | C25: N.R.E | D25: 10 | E25: รางซีตื้น ท่อเหล็ก แคล้มปะกับ | F25: SUV-250107216 | G25: 31577.2 | H25: K.Kowit | I25: 45825 | J25: PO2025060016
B26: 17 | C26: N.R.E | D26: 10 | E26: Wireway 100x100 | F26: SUV-250106549 | G26: 14235 | H26: K.Kowit | I26: 45810 | J26: PO2025060003
B27: 18 | C27: N.R.E | D27: 10 | E27: DB Panel for Office | F27: SUV-250107837 | G27: 41949.6 | H27: K.Kowit | I27: 45835 | J27: PO2025060027
B28: 19 | C28: N.R.E | D28: 10 | E28: พุกดรอปอิน | F28: QT0036688 | G28: 4650 | H28: K.Kowit | I28: 45834 | J28: PO2025060026
B29: 20 | C29: N.R.E | D29: 10 | E29: ท่อเหล็กร้อยสายไฟ EMT 1/2" | F29: SUV-250102205 | G29: 101080 | H29: K.Kowit | I29: 45834 | J29: PO2025060025
B30: 21 | C30: N.R.E | D30: 10 | E30: แคล้มปะกับ รางไวเวย์ 100x100 | F30: SUV-250107806 | G30: 80893.16 | H30: K.Kowit | I30: 45834 | J30: PO2025060024
B31: 22
B32: 23
B33: 24
B34: 25
B35: 26
B36: 27
B37: 28
B38: 29
B39: 30
B40: 31
B41: 32
B42: 33
... B64: 55
F66: TOTAL COST | G66: =SUM(G9:G65) -> 4337291.3
F67: BALANCE | G67: =$C$6-G66 -> 5524708.7
F69: All BALANCE | G69: =G67/C6 -> 0.56020165
B71: Job. Code. | C71: ='All Job balance report'!B7 -> UNT-2500/001
B72: Contract Price | C72: ='All Job balance report'!G7 -> 371100
B73: No. | C73: Code | E73: Description | F73: Budget | G73: Expense Record | H73: Balance | I73: Remark
B75: 1 | C75: 10 | E75: MATERIALS | F75: 7500000 | G75: =SUMIF($D$10:$D$65,$C$75,$G$10:$G$65) -> 3173491.3 | H75: =F75-G75 -> 4326508.7
B76: 2 | C76: 20 | E76: SUB CONTRACTOR | F76: 1480000 | G76: =SUMIF($D$10:$D$65,$C$76,$G$10:$G$65) -> 1150000 | H76: =F76-G76 -> 330000
B77: 3 | C77: 30 | E77: HEAVY EQUIPMENT | F77: 400000 | G77: =SUMIF($D$10:$D$65,$C$77,$G$10:$G$65) -> 0 | H77: =F77-G77 -> 400000
B78: 4 | C78: 40 | E78: RENTAL | F78: 180000 | G78: =SUMIF($D$10:$D$65,$C$78,$G$10:$G$65) -> 0 | H78: =F78-G78 -> 180000
B79: 5 | C79: 50 | E79: STAFF EXPENSE | F79: 242000 | G79: =SUMIF($D$10:$D$65,$C$79,$G$10:$G$65) -> 0 | H79: =F79-G79 -> 242000
B80: 6 | C80: 60 | E80: OFFICE EXPENSE | F80: 25000 | G80: =SUMIF($D$10:$D$65,$C$80,$G$10:$G$65) -> 13800 | H80: =F80-G80 -> 11200
B81: 7 | C81: 70 | E81: ENTERTAIN | F81: 15000 | G81: =SUMIF($D$10:$D$65,$C$81,$G$10:$G$65) -> 0 | H81: =F81-G81 -> 15000
B82: 8 | C82: 80 | E82: MISCELLANEOUS | F82: 20000 | G82: =SUMIF($D$10:$D$65,$C$82,$G$10:$G$65) -> 0 | H82: =F82-G82 -> 20000
E83: Total | F83: =SUM(F75:F82) -> 9862000 | G83: =SUM(G75:G82) -> 4337291.3 | H83: =SUM(H75:H82) -> 5524708.7
E84: % Profit | F84: =((C72-F83)/C72) -> -25.575047
E85: Total Profit | F85: =F84*C72 -> -9490900
E86: Gross Profit | F86: =C72-G83 -> -3966191.3

Sheet PC-005 SHIN FONG
B1: Factory/Company | C1: PROCHAIN | H1: =+F13 -> 0 | I1: 45336
B2: Project Name | C2: SHIN FONG Factory | H2: Sale Up Date
B3: Job Code. | C3: SF-001
B4: Quotation No. | E4: PROJECT BUDGET RECORD | H4: INVOICE (%) | I4: 0
B5: Contract Price | C5: =C72 -> 26000
B6: Budget Price | C6: 2930000
B7: PROFIT | C7: =(C5-C6)/C5 -> -111.69231 | D7: ACTUAL | E7: 1
B8: No. | C8: Vendor Name | D8: Material Number | E8: Description | F8: Text/Quo.No. | G8: Amount | H8: Updated By | I8: Date
B10: 1 | C10: เมธีกุล จำกัด | D10: 10 | E10: สายไฟ 60227 IEC01 THW | F10: QT68030869 | G10: 546041.2 | H10: k.milk | I10: 45748
B11: 2 | C11: บริษัท คว็อด อิเลคทริค จำกัด | D11: 10 | E11: หม้อแปลง 500kVA | F11: QT2025050132 | G11: 245000 | H11: K.Kowit | I11: 45798
B12: 3
B13: 4
B14: 5
B15: 6
B16: 7
B17: 8
B18: 9
B19: 10
B20: 11
B21: 12
B22: 13
B23: 14
... B50: 41
F66: TOTAL COST | G66: =SUM(G9:G65) -> 791041.2
F67: BALANCE | G67: =$C$6-G66 -> 2138958.8
F69: All BALANCE | G69: =G67/C6 -> 0.73002007
B71: Job. Code. | C71: ='All Job balance report'!B6 -> QMP-2500/001
B72: Contract Price | C72: ='All Job balance report'!G6 -> 26000
B73: No. | C73: Code | E73: Description | F73: Budget | G73: Expense Record | H73: Balance | I73: Remark
B75: 1 | C75: 10 | E75: MATERIALS | F75: 1800000 | G75: =SUMIF($D$10:$D$65,$C$75,$G$10:$G$65) -> 791041.2 | H75: =F75-G75 -> 1008958.8
B76: 2 | C76: 20 | E76: SUB CONTRACTOR | F76: 500000 | G76: =SUMIF($D$10:$D$65,$C$76,$G$10:$G$65) -> 0 | H76: =F76-G76 -> 500000
B77: 3 | C77: 30 | E77: HEAVY EQUIPMENT | F77: 50000 | G77: =SUMIF($D$10:$D$65,$C$77,$G$10:$G$65) -> 0 | H77: =F77-G77 -> 50000
B78: 4 | C78: 40 | E78: RENTAL | F78: 30000 | G78: =SUMIF($D$10:$D$65,$C$78,$G$10:$G$65) -> 0 | H78: =F78-G78 -> 30000
B79: 5 | C79: 50 | E79: STAFF EXPENSE | F79: 450000 | G79: =SUMIF($D$10:$D$65,$C$79,$G$10:$G$65) -> 0 | H79: =F79-G79 -> 450000
B80: 6 | C80: 60 | E80: OFFICE EXPENSE | F80: 60000 | G80: =SUMIF($D$10:$D$65,$C$80,$G$10:$G$65) -> 0 | H80: =F80-G80 -> 60000
B81: 7 | C81: 70 | E81: ENTERTAIN | F81: 20000 | G81: =SUMIF($D$10:$D$65,$C$81,$G$10:$G$65) -> 0 | H81: =F81-G81 -> 20000
B82: 8 | C82: 80 | E82: MISCELLANEOUS | F82: 20000 | G82: =SUMIF($D$10:$D$65,$C$82,$G$10:$G$65) -> 0 | H82: =F82-G82 -> 20000
E83: Total | F83: =SUM(F75:F82) -> 2930000 | G83: =SUM(G75:G82) -> 791041.2 | H83: =SUM(H75:H82) -> 2138958.8
E84: % Profit | F84: =((C72-F83)/C72) -> -111.69231
E85: Total Profit | F85: =F84*C72 -> -2904000
E86: Gross Profit | F86: =C72-G83 -> -765041.2

Sheet PC-004 อาคาร D
B1: Factory/Company | C1: PROCHAIN | H1: Start Date | I1: 45336
B2: Project Name | C2: มาบตาพุต ร้านอาหาร ร้านกาแฟ อาคาร D และ อาคาร A | H2: Sale Up Date | N2: B-A | O2: B-D | P2: ร้านกาแฟ | Q2: ร้านอาหาร
B3: Job Code. | C3: =C71 -> PKE-2500/001 | M3: PO No. | N3: PO6800405
B4: Quotation No. | E4: PROJECT BUDGET RECORD | H4: INVOICE (%) | I4: 0 | N4: PA6800158
B5: Contract Price | C5: =C72 -> 32460
B6: Budget Price | C6: =F83 -> 256000 | M6: Contract Price | N6: 2254570 | P6: 397867.06 | Q6: 513604.21
B7: PROFIT | C7: =(C5-C6)/C5 -> -6.8866297 | D7: ACTUAL | E7: 1 | N7: 265430.02
B8: No. | C8: Vendor Name | D8: Material Number | E8: Description | F8: Text/Quo.No. | G8: Amount | H8: Updated By | I8: Date
N9: =SUM(N6:N8) -> 2520000 | O9: =SUM(O6:O8) -> 0 | P9: =SUM(P6:P8) -> 397867.06 | Q9: =SUM(Q6:Q8) -> 513604.21 | R9: =SUM(N9:Q9) -> 3431471.3
C10: N.R.E | D10: 10 | E10: Cable THW 2.5 | F10: SUV-250106507 | G10: 28210 | H10: K.Kowit | I10: 45748
C11: N.R.E | D11: 10 | E11: สาย Max-foh-l 1x2.5 sqmm. | F11: SUV-250107052 | G11: 13120 | H11: K.Kowit | I11: 45820
F66: TOTAL COST | G66: =SUM(G9:G65) -> 41330
F67: BALANCE | G67: =$C$6-G66 -> 214670
F69: All BALANCE | G69: =G67/C6 -> 0.83855469
B71: Job. Code. | C71: ='All Job balance report'!B5 -> PKE-2500/001
B72: Contract Price | C72: ='All Job balance report'!G5 -> 32460
B73: No. | C73: Code | E73: Description | F73: Budget | G73: Expense Record | H73: Balance | I73: Remark
N74: B-A | O74: B-D | P74: ร้านกาแฟ | Q74: ร้านอาหาร
B75: 1 | C75: 10 | E75: MATERIALS | F75: 130000 | G75: =SUMIF($D$10:$D$65,$C$75,$G$10:$G$65) -> 41330 | H75: =F75-G75 -> 88670 | N75: =1391385.86+550222.39 -> 1941608.2 | O75: 187326.21 | P75: 171283.81 | Q75: 229202.12 | R75: =SUM(N75:Q75) -> 2529420.4
B76: 2 | C76: 20 | E76: SUB CONTRACTOR | F76: 86000 | G76: =SUMIF($D$10:$D$65,$C$76,$G$10:$G$65) -> 0 | H76: =F76-G76 -> 86000 | N76: =125499.72+40000-N79 -> 100499.72 | O76: =129657.59-O79 -> 79657.59 | P76: =119025.22-P79 -> 69025.22 | Q76: =145843.83-Q79 -> 115843.83 | R76: =SUM(N76:Q76) -> 365026.36
B77: 3 | C77: 30 | E77: HEAVY EQUIPMENT | F77: 0 | G77: =SUMIF($D$10:$D$65,$C$77,$G$10:$G$65) -> 0 | H77: =F77-G77 -> 0 | R77: =SUM(N77:Q77) -> 0
B78: 4 | C78: 40 | E78: RENTAL | F78: 0 | G78: =SUMIF($D$10:$D$65,$C$78,$G$10:$G$65) -> 0 | H78: =F78-G78 -> 0 | R78: =SUM(N78:Q78) -> 0
B79: 5 | C79: 50 | E79: STAFF EXPENSE | F79: 30000 | G79: =SUMIF($D$10:$D$65,$C$79,$G$10:$G$65) -> 0 | H79: =F79-G79 -> 30000 | N79: 65000 | O79: 50000 | P79: 50000 | Q79: 30000 | R79: =SUM(N79:Q79) -> 195000
B80: 6 | C80: 60 | E80: OFFICE EXPENSE | F80: 0 | G80: =SUMIF($D$10:$D$65,$C$80,$G$10:$G$65) -> 0 | H80: =F80-G80 -> 0 | R80: =SUM(N80:Q80) -> 0
B81: 7 | C81: 70 | E81: ENTERTAIN | F81: 0 | G81: =SUMIF($D$10:$D$65,$C$81,$G$10:$G$65) -> 0 | H81: =F81-G81 -> 0 | R81: =SUM(N81:Q81) -> 0
B82: 8 | C82: 80 | E82: MISCELLANEOUS | F82: 10000 | G82: =SUMIF($D$10:$D$65,$C$82,$G$10:$G$65) -> 0 | H82: =F82-G82 -> 10000 | R82: =SUM(N82:Q82) -> 0
E83: Total | F83: =SUM(F75:F82) -> 256000 | G83: =SUM(G75:G82) -> 41330 | H83: =SUM(H75:H82) -> 214670 | R83: =SUM(N83:Q83) -> 0
E84: % Profit | F84: =((C72-F83)/C72) -> -6.8866297
E85: Total Profit | F85: =F84*C72 -> -223540 | N85: =SUM(N75:N84) -> 2107108 | O85: =SUM(O75:O84) -> 316983.8 | P85: =SUM(P75:P84) -> 290309.03 | Q85: =SUM(Q75:Q84) -> 375045.95 | R85: =SUM(N85:Q85) -> 3089446.8
E86: Gross Profit | F86: =C72-G83 -> -8870

Sheet ค่าใช้จ่ายออฟฟิศ
E2: Office Expense
B4: ตั้งงบ | C4: 50000
B6: Item No. | C6: Vendor Name | D6: Material Number | E6: Description | F6: Text/Quo.No. | G6: Amount | H6: Updated By | I6: Date
B7: 1 | D7: 60 | E7: ค่าป้ายบริษัท | G7: 800 | H7: K.Kowit | I7: 45899
B8: 2 | D8: 60 | E8: ค่าตรายาง | G8: 660 | H8: K.Kowit | I8: 45901
B9: 3 | D9: 60 | E9: ค่าบัญชี ค่าธรรมเนียมเปิดบริษัท | G9: 8000 | H9: K.Kowit | I9: 45901
B10: 4 | D10: 60 | E10: เสื้อช็อปบริษัท | G10: 1404 | H10: K.Kowit | I10: 45922
B11: 5 | D11: 60 | E11: เสื้อช็อปบริษัท | G11: 4815 | H11: K.Kowit | I11: 45922
B12: 6 | D12: 60 | E12: นามบัตรพิมพ์ 1 ด้าน | G12: 250 | H12: K.Kowit | I12: 45922
B13: 7 | D13: 10 | E13: ค่าเครื่องมือ สว่านไฟฟ้า เครื่องเจียร | G13: =353+1685+1830 -> 3868 | H13: K.Kowit | I13: 45922
B14: 8 | D14: 20 | E14: บัญชี เดือน 10 | G14: 1500 | H14: K.Kowit | I14: 46017
B15: 9 | D15: 20 | E15: บัญชี เดือน 11 | G15: 1500 | H15: K.Kowit | I15: 46017
B16: 10 | D16: 10 | E16: ค่าชุดประแจ คีมย้ำ ใบตัด ใบเจียร | G16: 1043 | H16: K.Kowit | I16: 46017
B17: 11 | D17: 10 | E17: แคมป์ มิเตอร์ | G17: 1200 | H17: K.Kowit | I17: 46017
B18: 12 | D18: 10 | E18: ค่าซองจดหมาย ซองน้ำตาล | G18: 643 | H18: K.Kowit | I18: 46017
B19: 13 | D19: 60 | E19: ค่าป้ายรับสมัครงาน | G19: 1000 | H19: K.Kowit | I19: 46019
B20: 14 | D20: 60 | E20: ค่าส่งป้าย | G20: 234 | H20: K.Kowit | I20: 46019
B21: 15 | D21: 60 | E21: ค่ากระดาษ A4 | F21: 3792 | G21: 61 | H21: K.Kowit | I21: 46037
B22: 16
B23: 17
B24: 18
B25: 19
B26: 20
B27: 21
B28: 22
F29: TOTAL COST | G29: =SUM(G7:G28) -> 26978 | H29: ยอดรวมไม่รวมค่าออฟฟิศ
F30: BALANCE | G30: =$C$4-G29 -> 23022
F31: ใช้เงินไปแล้ว | G31: =$G$29/$C$4 -> 0.53956
F32: ยอดกำไรบริษัท | G32: ='All Job balance report'!L29 -> 213147.72
F33: ยอดคงเหลือหลังหักค่าใช้จ่ายออฟฟิศ | G33: =G32-G29 -> 186169.72
E35: ค่ามัดจำออฟฟิศ ค่าใช้จ่ายทั้งหมด ชำระค่าเช่าล่วงหน้า 1 เดือน 15,000 บาท เงินประกัน 3 เดือน 16,000 x 3 = 48,000 บาท ชำระรวม 63,000 บาท ทำสัญญาเริ่มข้าพัก 10 มกราคม 2025 | G35: 63000 | H35: K.Kowit | I35: 46017
B38: Job. Code. | C38: ='All Job balance report'!B2 -> PEK-2500/001
B39: Budget | C39: 20000
B40: No. | C40: Code | E40: Description | F40: Budget | G40: Expense Record | H40: Balance | I40: Remark
B42: 1 | C42: 10 | E42: MATERIALS | F42: 8000 | G42: =SUMIF($D$7:$D$35,$C$42,$G$7:$G$35) -> 6754 | H42: =F42-G42 -> 1246
B43: 2 | C43: 20 | E43: SUB CONTRACTOR | F43: 5000 | G43: =SUMIF($D$7:$D$35,$C$43,$G$7:$G$35) -> 3000 | H43: =F43-G43 -> 2000
B44: 3 | C44: 30 | E44: HEAVY EQUIPMENT | G44: =SUMIF($D$7:$D$35,$C$44,$G$7:$G$35) -> 0 | H44: =F44-G44 -> 0
B45: 4 | C45: 40 | E45: RENTAL | G45: =SUMIF($D$7:$D$35,$C$45,$G$7:$G$35) -> 0 | H45: =F45-G45 -> 0
B46: 5 | C46: 50 | E46: STAFF EXPENSE | G46: =SUMIF($D$7:$D$35,$C$46,$G$7:$G$35) -> 0 | H46: =F46-G46 -> 0
B47: 6 | C47: 60 | E47: OFFICE EXPENSE | F47: =C39 -> 20000 | G47: =SUMIF($D$7:$D$35,$C$47,$G$7:$G$35) -> 17224 | H47: =F47-G47 -> 2776
B48: 7 | C48: 70 | E48: ENTERTAIN | G48: =SUMIF($D$7:$D$35,$C$48,$G$7:$G$35) -> 0 | H48: =F48-G48 -> 0
B49: 8 | C49: 80 | E49: MISCELLANEOUS | G49: =SUMIF($D$7:$D$35,$C$49,$G$7:$G$35) -> 0 | H49: =F49-G49 -> 0
E50: Total | F50: =SUM(F42:F49) -> 33000 | G50: =SUM(G42:G49) -> 26978 | H50: =SUM(H42:H49) -> 6022

Sheet All Job balance report
A1: No. | B1: Job Code | C1: Offer No. | D1: Client | E1: Project Name (เพิ่ม) | F1: Description | G1: Contact price | H1: Budget | I1: % profit | J1: Profit | K1: Balance from record | L1: Gross Profit กำไรหลังหักค่าใช้จ่าย | M1: INVOICE | N1: INVOICE ค้างจ่าย | O1: กำหนดจ่าย | P1: งานเสร็จแล้ว | Q1: ค่าแรง โกวิท 25% ของกำไร | R1: รับค่าจ้างแล้ว | S1: จ่ายแล้ว | T1: Gross Profit | U1: Inchart | V1: Job Complete
A2: 1 | B2: PEK-2500/001 | C2: QTE-DDP-20250006 | D2: บริษัท เป็นเอก เอ็นเนอร์จี เซฟวิ่ง จำกัด | F2: เปลี่ยนหลอดไฟไฮเบย์ CP Warehouse | G2: 66000 | H2: ='01 PEK-001 Pen Eak'!F43 -> 58500 | I2: ='01 PEK-001 Pen Eak'!F44 -> 0.11363636 | J2: =I2*G2 -> 7500 | K2: ='01 PEK-001 Pen Eak'!H43 -> -3658.64 | L2: =J2+K2 -> 3841.36 | M2: 1 | N2: 0 | P2: 1 | Q2: =$Q$30*L2 -> 960.34 | R2: 45997 | S2: 960.34 | T2: =L2/G2 -> 0.058202424 | U2: 1 | V2: 1
A3: 2 | B3: JPP-2500/001 | C3: QTE-DDP-20250004 | D3: Jatupaspol Co., Ltd. | F3: งานค่าแรงติดตั้ง โรงงาน ช.ไพรศาล | G3: 330000 | H3: ='02 JPP-001 งานชัยนาท'!F31 -> 325000 | I3: ='02 JPP-001 งานชัยนาท'!F32 -> 0.015151515 | J3: =I3*G3 -> 5000 | K3: ='02 JPP-001 งานชัยนาท'!H31 -> 0 | L3: =J3+K3 -> 5000 | M3: 0.8 | N3: 0.2 | O3: 46021 | P3: 1 | T3: =L3/G3 -> 0.015151515 | U3: 1 | V3: 0.8
A4: 3 | B4: PEK-2500/002 | C4: QTE-DDP-20250007 | D4: บริษัท ทีจี คอนโทรล จำกัด | F4: เปลี่ยน ACB Big-C Udonthani | G4: 163000 | H4: ='03 TG-002 เปลี่ยน ACB'!F38 -> 149500 | I4: ='03 TG-002 เปลี่ยน ACB'!F39 -> 0.082822086 | J4: =I4*G4 -> 13500 | K4: ='03 TG-002 เปลี่ยน ACB'!H38 -> 9483 | L4: =J4+K4 -> 22983 | M4: 1 | N4: 0 | P4: 1 | T4: =L4/G4 -> 0.141 | U4: 1 | V4: 1
A5: 4 | B5: PKE-2500/001 | C5: QTE-DDP-20250008 | D5: PK Engineering Solution Service Co., Ltd. | F5: งานติดตั้งตู้ และทำ Tray รสา 1 ชั้น 18 19 | G5: =20564+11896 -> 32460 | H5: ='04 PKE-001 ติดตั้งลากสาย RASA1'!F44 -> 24400 | I5: ='04 PKE-001 ติดตั้งลากสาย RASA1'!F45 -> 0.24830561 | J5: =I5*G5 -> 8060 | K5: ='04 PKE-001 ติดตั้งลากสาย RASA1'!H44 -> 718.92 | L5: =J5+K5 -> 8778.92 | M5: 1 | N5: 0 | P5: 1 | Q5: =$Q$30*L5 -> 2194.73 | R5: 45997 | S5: 2194.73 | T5: =L5/G5 -> 0.27045348 | U5: 1 | V5: 1
A6: 5 | B6: QMP-2500/001 | C6: QTE-DDP-20250023 | D6: บริษัท ควอลิตี้ มีท โปรเซสซิ่ง จำกัด | F6: งาน PM หม้อแปลง 315kVA | G6: 26000 | H6: 17800 | I6: ='05 QMP-001งาน PM 315kVA'!F38 -> 0.27692308 | J6: =I6*G6 -> 7200 | K6: ='05 QMP-001งาน PM 315kVA'!H37 -> 733 | L6: =J6+K6 -> 7933 | M6: 1 | N6: 0 | P6: 1 | Q6: =$Q$30*L6 -> 1983.25 | R6: 45997 | S6: 1983.25 | T6: =L6/G6 -> 0.30511538 | U6: 1 | V6: 1
A7: 6 | B7: UNT-2500/001 | C7: - | D7: Unity System Co., Ltd. | F7: งานค่าแรงผู้รับเหมา | G7: ='06 UNT-001 รพ.ภัทรเวช'!C33 -> 371100 | H7: ='06 UNT-001 รพ.ภัทรเวช'!F45 -> 371100 | I7: ='06 UNT-001 รพ.ภัทรเวช'!F46 -> 0 | J7: ='06 UNT-001 รพ.ภัทรเวช'!F47 -> 0 | K7: ='06 UNT-001 รพ.ภัทรเวช'!H45 -> 20179.72 | L7: =J7+K7 -> 20179.72 | M7: 0.8 | N7: 0 | O7: 46020 | P7: 0.8 | T7: =L7/G7 -> 0.054378119 | U7: 1 | V7: 0.8
A8: 7 | B8: SUT-2500/001 | C8: QTE-DDP-20250026 | D8: คุณสุทธิพงษ์ | F8: งานบ้านห้วยขวาง | G8: 37500 | H8: ='07 SUT-001 บ้านห้วยขวาง'!F45 -> 28290 | I8: ='07 SUT-001 บ้านห้วยขวาง'!F46 -> 0.2456 | J8: ='07 SUT-001 บ้านห้วยขวาง'!F47 -> 9210 | K8: ='07 SUT-001 บ้านห้วยขวาง'!H45 -> -6690.2 | L8: ='07 SUT-001 บ้านห้วยขวาง'!F48 -> 2519.8 | M8: 1 | N8: 0 | P8: 0.9 | Q8: =$Q$30*L8 -> 629.95 | R8: 45997 | S8: 2388.54 | T8: =L8/G8 -> 0.067194667 | U8: 1 | V8: 0.95
A9: 8 | B9: PKE-2500/002 | C9: QTE-DDP-20250031 | D9: PK Engineering Solution Service Co., Ltd. | F9: งานติดตั้งพัดลมระบายอากาศ | G9: 7000 | H9: 4000 | I9: ='08 PKE-002 ติดตั้งพัดลมระบายอาก'!F44 -> 0.37142857 | J9: =I9*G9 -> 2600 | K9: ='08 PKE-002 ติดตั้งพัดลมระบายอาก'!H43 -> 857 | L9: 0 | M9: 1 | N9: 1 | O9: 46052 | P9: 1 | T9: =L9/G9 -> 0 | U9: 1 | V9: 1
F10: Contact Total | G10: =SUM(G2:G9) -> 1033060 | H10: =SUM(H2:H9) -> 978590 | I10: =L10/G10 -> 0.068956111 | J10: =SUM(J2:J9) -> 53070 | K10: =SUM(K2:K9) -> 21622.8 | L10: =SUM(L2:L9) -> 71235.8
A12: 9 | B12: JEP-2601/001 | C12: DDP-2026000001 | D12: บริษัท เจตภัทร คอนสตรัคชั่น แอนด์ ดีไซน์ จำกัด | F12: งานติดตั้งคอนโด The Line Vibe ห้อง549 | G12: 12000 | H12: ='09 JEP-2601-001'!F45 -> 12800 | I12: ='09 JEP-2601-001'!F46 -> -0.066666667 | J12: =I12*G12 -> -800 | K12: ='09 JEP-2601-001'!H45 -> -45555 | L12: =J12+K12 -> -46355 | M12: 1 | P12: 1 | T12: =L12/G12 -> -3.8629167 | U12: 1 | V12: 1
A13: 10 | B13: UNT-2601/001 | C13: DDP-2026000002 | D13: Unity System Co., Ltd. | F13: งานค่าแรงผู้รับเหมา รพ.ภัทรเวช | G13: ='10 UNT-2601-001 รพ.ภัทรเวช (2)'!G23+'10 UNT-2601-001 รพ.ภัทรเวช (2)'!G24+'10 UNT-2601-001 รพ.ภัทรเวช (2)'!G25+'10 UNT-2601-001 รพ.ภัทรเวช (2)'!G26 -> 143840.18 | H13: ='10 UNT-2601-001 รพ.ภัทรเวช (2)'!G45 -> 128708.19 | I13: ='10 UNT-2601-001 รพ.ภัทรเวช (2)'!F46 -> 0 | J13: =I13*G13 -> 0 | K13: ='10 UNT-2601-001 รพ.ภัทรเวช (2)'!H45 -> 15131.99 | L13: =J13+K13 -> 15131.99 | M13: 1 | N13: 0 | O13: 46081 | P13: 1 | T13: =L13/G13 -> 0.10520002 | U13: 1 | V13: 1
A14: 11 | B14: TMD-2601/001 | C14: DDP-2026000003 | D14: Thai Meidensha Co., Ltd. | F14: งาน PM Test Protection Relay | G14: 42000 | H14: ='11 TMD-2601-001'!F45 -> 40000 | I14: ='11 TMD-2601-001'!F46 -> 0.047619048 | J14: =I14*G14 -> 2000 | K14: ='11 TMD-2601-001'!H45 -> 3000 | L14: =J14+K14 -> 5000 | M14: 1 | N14: 0 | P14: 1 | T14: =L14/G14 -> 0.11904762 | U14: 1 | V14: 1
A15: 12 | B15: TMD-2601/002 | C15: QTE-DDP-2026000XX | D15: Thai Meidensha Co., Ltd. | F15: งานรถไฟฟ้าสายสีส้ม สำรวจหน้างาน | G15: ='12 TMD-2601-002'!M17 -> 69855 | H15: ='12 TMD-2601-002'!F45 -> 40000 | I15: ='12 TMD-2601-002'!F46 -> 0.4273853 | J15: =I15*G15 -> 29855 | K15: ='12 TMD-2601-002'!H45 -> 1903.67 | L15: =J15+K15 -> 31758.67 | M15: 0 | N15: 1 | O15: 46192 | P15: 1 | T15: =L15/G15 -> 0.45463703 | U15: 1 | V15: 1
A16: 13 | B16: JPP-2500/001 | C16: QTE-DDP-2026000XX | D16: Jatupaspol Co., Ltd. | F16: งาน Manday ลากสาย Gulf | G16: 19000 | H16: ='13 JPP-2601-001'!F45 -> 15000 | I16: ='13 JPP-2601-001'!F46 -> 0.78526949 | J16: =I16*G16 -> 14920.12 | K16: ='13 JPP-2601-001'!H45 -> 14533.64 | L16: =J16+K16 -> 29453.76 | M16: 0 | N16: 1 | O16: 46192 | P16: 1 | T16: =L16/G16 -> 1.5501979 | U16: 1 | V16: 1
A17: 14 | B17: TMD-2601/003 | C17: QTE-DDP-2026000XX | D17: Thai Meidensha Co., Ltd. | F17: งาน PM Honda | G17: 20000 | H17: ='14 TMD-2601-003'!F45 -> 16000 | I17: ='14 TMD-2601-003'!F46 -> 0.2 | J17: =I17*G17 -> 4000 | K17: ='14 TMD-2601-003'!H45 -> 16000 | L17: =J17+K17 -> 20000 | M17: 0 | N17: 1 | O17: 46192 | P17: 1
A18: 15 | B18: SRP-2601/001 | C18: QTE-DDP-2026000XX | D18: Siriplace นครปฐม | F18: งานติตดั้งลากสายเมนสำหรับลานจอดรถ | G18: 65000 | P18: 1
A19: 16 | B19: PEK-2601/001 | C19: QTE-DDP-2026000XX | D19: งานต่อเติมข้างบ้าน | F19: งานเทปูน ทำพื้นและคาน | G19: 16000 | P19: 1
A20: 17 | B20: TMD-2601/004 | D20: Thai Meidensha Co., Ltd. | F20: งานติดตั้งท่อสำหรับ MWS 5 ห้อง | G20: 620000 | H20: ='21 TMD-004'!F45 -> 550000 | I20: ='21 TMD-004'!F46 -> 0.11290323 | J20: =I20*G20 -> 70000 | K20: ='21 TMD-004'!H45 -> 10464.58 | L20: =J20+K20 -> 80464.58 | M20: 0.9 | P20: 0.9
A21: 18 | B21: TMD-2601/005 | D21: Thai Meidensha Co., Ltd. | F21: งานติดตั้งท่อลากสายแอร์ OCC | G21: 18000 | H21: ='22 TMD-005'!F45 -> 10000 | I21: ='22 TMD-005'!F46 -> 0.44444444 | J21: =I21*G21 -> 8000 | K21: ='22 TMD-005'!H45 -> 10000 | L21: =J21+K21 -> 18000 | M21: 1 | P21: 0.8
A22: 19 | B22: SOL-2604/01 | D22: บ้านคุณเม | F22: Solar cell 10kWp. + Batt 21kWh. | G22: 400000 | P22: 1 | U22: 1
A23: 20 | B23: SOL-2604/02 | D23: ร้าน Over Wash | F23: Solar cell 17.9kWp. | G23: 235660 | P23: 1 | U23: 1
A24: 21 | B24: TMD-006 | D24: Thai Meidensha Co., Ltd. | F24: งานติดตั้ง General Waste/Dangerous Waste | G24: 339693.72 | H24: ='23 TMD-006'!F45 -> 280000 | I24: ='23 TMD-006'!F46 -> 0.17572806 | J24: =I24*G24 -> 59693.72 | K24: ='23 TMD-006'!H45 -> 0 | L24: =J24+K24 -> 59693.72 | M24: 0.9 | P24: 0.5
A25: 22 | B25: POM-007 | C25: QTE-DDP-202600100 | D25: คุณปอม | F25: ติดตั้ง Solar Cell | G25: 300000 | U25: 1
A26: 23 | U26: 1
A27: 24 | U27: 1
A28: 25 | U28: 1
F29: Contact Total | G29: =SUM(G12:G28) -> 2301048.9 | H29: =SUM(H12:H28) -> 1092508.2 | I29: =L29/G29 -> 0.092630678 | J29: =SUM(J12:J28) -> 187668.84 | K29: =SUM(K12:K28) -> 25478.88 | L29: =SUM(L12:L28) -> 213147.72 | Q29: =SUM(Q2:Q28) -> 5768.27
Q30: 0.25 | S30: =SUM(S2:S29) -> 7526.86
L31: ยังไม่ต้องทำ
B33: Sale | C33: Contact | D33: Gross Profit | F33: Profit percent
B34: 1 | C34: =SUMIF($U$2:$U$28,$B$34,$G$2:$G$28) -> 2255415.2 | D34: =SUMIF($U$2:$U$28,$B$34,L12:$L$28) -> 114683.14 | F34: =D34/C34 -> 0.050847907
B35: 2 | C35: =SUMIF($U$2:$U$28,$B$35,$G$2:$G$28) -> 0 | D35: =SUMIF($U$2:$U$28,$B$35,L2:$L$28) -> 0 | F35: =D35/C35 -> #DIV/0!

Sheet 24 POM-007
B1: Factory/Company | C1: ='All Job balance report'!D21 -> Thai Meidensha Co., Ltd. | H1: Start Date | I1: 46113
B2: Project Name | C2: ='All Job balance report'!F21 -> งานติดตั้งท่อลากสายแอร์ OCC | H2: Sale Up Date
B3: Job Code. | C3: ='All Job balance report'!B21 -> TMD-2601/005 | M3: PO No.
B4: Quotation No. | E4: PROJECT BUDGET RECORD | H4: INVOICE (%) | I4: 0
B5: Contract Price | C5: =C33 -> 339693.72
B6: Budget Price | C6: =F45 -> 360000 | M6: Contract Price | P6: วัน | Q6: ค่าแรง
B7: PROFIT | C7: =(C5-C6)/C5 -> -0.059778203 | D7: ACTUAL | E7: 1 | L7: ค่าแรงงวดงานที่ 1 | M7: 21753.1 | O7: ช่างชัย | P7: 30 | Q7: 14000
B8: No. | C8: Vendor Name | D8: Material Number | E8: Description | F8: Text/Quo.No. (ของร้านค้า) | G8: Amount | H8: Updated By | I8: Date | J8: PO | L8: ค่าแรงงวดงานที่ 2 | M8: 39301.1 | O8: ช่างออม | P8: 25 | Q8: =400*P8 -> 10000
B9: 1 | C9: APT | D9: 20 | E9: ค่าแรงทีมงาน | G9: 280000 | H9: K.Kowit | I9: 46148 | L9: ค่าแรงงวดงานที่ 3 | M9: 0 | O9: ช่างบอล | P9: 6 | Q9: 6000
B10: 2 | C10: ร้านโซล่าดีดี | D10: 10 | E10: แพงอุปกร์ Solar | F10: TEST007 | G10: 70000 | L10: ค่าแรงงวดงานที่ 4 | M10: 0
B11: 3
B12: 4
B13: 6
B14: 8
B15: 9
B16: 10
B17: 11 | M17: =SUM(M7:M16) -> 61054.2 | Q17: =SUM(Q7:Q16) -> 30000
B18: 12
B19: 13
B20: 14
B23: 99
B24: 99
B25: 99
B26: 99
F27: TOTAL COST | G27: =SUM(G9:G26) -> 350000
F28: BALANCE | G28: =$C$6-G27 -> 10000
F30: All BALANCE | G30: =G28/C6 -> 0.027777778
B32: Job. Code. | C32: ='All Job balance report'!B21 -> TMD-2601/005
B33: Contract Price | C33: ='All Job balance report'!G24 -> 339693.72 | D33: 0
B34: No. | C34: Code | E34: Description | F34: Budget | G34: Expense Record | H34: Balance | I34: Remark
B36: 1 | C36: 10 | E36: MATERIALS | F36: 80000 | G36: =SUMIF($D$9:$D$26,$C$36,$G$9:$G$26) -> 70000 | H36: =F36-G36 -> 10000
B37: 2 | C37: 20 | E37: SUB CONTRACTOR | F37: 280000 | G37: =SUMIF($D$9:$D$26,$C$37,$G$9:$G$26) -> 280000 | H37: =F37-G37 -> 0
B38: 3 | C38: 30 | E38: HEAVY EQUIPMENT | F38: 0 | G38: =SUMIF($D$9:$D$26,$C$38,$G$9:$G$26) -> 0 | H38: =F38-G38 -> 0
B39: 4 | C39: 40 | E39: RENTAL | F39: 0 | G39: =SUMIF($D$9:$D$26,$C$39,$G$9:$G$26) -> 0 | H39: =F39-G39 -> 0
B40: 5 | C40: 50 | E40: STAFF EXPENSE | F40: 0 | G40: =SUMIF($D$9:$D$26,$C$40,$G$9:$G$26) -> 0 | H40: =F40-G40 -> 0
B41: 6 | C41: 60 | E41: OFFICE EXPENSE | F41: 0 | G41: =SUMIF($D$9:$D$26,$C$41,$G$9:$G$26) -> 0 | H41: =F41-G41 -> 0
B42: 7 | C42: 70 | E42: ENTERTAIN | F42: 0 | G42: =SUMIF($D$9:$D$26,$C$42,$G$9:$G$26) -> 0 | H42: =F42-G42 -> 0
B43: 8 | C43: 80 | E43: MISCELLANEOUS | F43: 0 | G43: =SUMIF($D$9:$D$26,$C$43,$G$9:$G$26) -> 0 | H43: =F43-G43 -> 0
B44: 9 | C44: 90 | E44: OTHER | F44: 0 | G44: =SUMIF($D$9:$D$26,$C$44,$G$9:$G$26) -> 0 | H44: =F44-G44 -> 0
E45: Total | F45: =SUM(F36:F44) -> 360000 | G45: =SUM(G36:G44) -> 350000 | H45: =SUM(H36:H44) -> 10000
E46: % Profit | F46: =((C33-F45)/C33) -> -0.059778203
E47: Total Profit | F47: =F46*C33 -> -20306.28
E48: Gross Profit | F48: =C33-G45 -> -10306.28
E50: ค่าแรง โกวิท | F50: =F48*0.25 -> -2576.57

Sheet 23 TMD-006
B1: Factory/Company | C1: ='All Job balance report'!D21 -> Thai Meidensha Co., Ltd. | H1: Start Date | I1: 46113
B2: Project Name | C2: ='All Job balance report'!F21 -> งานติดตั้งท่อลากสายแอร์ OCC | H2: Sale Up Date
B3: Job Code. | C3: ='All Job balance report'!B21 -> TMD-2601/005 | M3: PO No.
B4: Quotation No. | E4: PROJECT BUDGET RECORD | H4: INVOICE (%) | I4: 0
B5: Contract Price | C5: =C33 -> 339693.72
B6: Budget Price | C6: =F45 -> 280000 | M6: Contract Price | P6: วัน | Q6: ค่าแรง
B7: PROFIT | C7: =(C5-C6)/C5 -> 0.17572806 | D7: ACTUAL | E7: 1 | L7: ค่าแรงงวดงานที่ 1 | M7: 21753.1 | O7: ช่างชัย | P7: 30 | Q7: 14000
B8: No. | C8: Vendor Name | D8: Material Number | E8: Description | F8: Text/Quo.No. | G8: Amount | H8: Updated By | I8: Date | J8: PO | L8: ค่าแรงงวดงานที่ 2 | M8: 39301.1 | O8: ช่างออม | P8: 25 | Q8: =400*P8 -> 10000
B9: 1 | C9: APT | D9: 20 | E9: ค่าแรงทีมงาน | G9: 280000 | H9: K.Kowit | I9: 46148 | L9: ค่าแรงงวดงานที่ 3 | M9: 0 | O9: ช่างบอล | P9: 6 | Q9: 6000
B10: 2 | L10: ค่าแรงงวดงานที่ 4 | M10: 0
B11: 3
B12: 4
B13: 6
B14: 8
B15: 9
B16: 10
B17: 11 | M17: =SUM(M7:M16) -> 61054.2 | Q17: =SUM(Q7:Q16) -> 30000
B18: 12
B19: 13
B20: 14
B23: 99
B24: 99
B25: 99
B26: 99
F27: TOTAL COST | G27: =SUM(G9:G26) -> 280000
F28: BALANCE | G28: =$C$6-G27 -> 0
F30: All BALANCE | G30: =G28/C6 -> 0
B32: Job. Code. | C32: ='All Job balance report'!B21 -> TMD-2601/005
B33: Contract Price | C33: ='All Job balance report'!G24 -> 339693.72 | D33: 0
B34: No. | C34: Code | E34: Description | F34: Budget | G34: Expense Record | H34: Balance | I34: Remark
B36: 1 | C36: 10 | E36: MATERIALS | F36: 0 | G36: =SUMIF($D$9:$D$26,$C$36,$G$9:$G$26) -> 0 | H36: =F36-G36 -> 0
B37: 2 | C37: 20 | E37: SUB CONTRACTOR | F37: 280000 | G37: =SUMIF($D$9:$D$26,$C$37,$G$9:$G$26) -> 280000 | H37: =F37-G37 -> 0
B38: 3 | C38: 30 | E38: HEAVY EQUIPMENT | F38: 0 | G38: =SUMIF($D$9:$D$26,$C$38,$G$9:$G$26) -> 0 | H38: =F38-G38 -> 0
B39: 4 | C39: 40 | E39: RENTAL | F39: 0 | G39: =SUMIF($D$9:$D$26,$C$39,$G$9:$G$26) -> 0 | H39: =F39-G39 -> 0
B40: 5 | C40: 50 | E40: STAFF EXPENSE | F40: 0 | G40: =SUMIF($D$9:$D$26,$C$40,$G$9:$G$26) -> 0 | H40: =F40-G40 -> 0
B41: 6 | C41: 60 | E41: OFFICE EXPENSE | F41: 0 | G41: =SUMIF($D$9:$D$26,$C$41,$G$9:$G$26) -> 0 | H41: =F41-G41 -> 0
B42: 7 | C42: 70 | E42: ENTERTAIN | F42: 0 | G42: =SUMIF($D$9:$D$26,$C$42,$G$9:$G$26) -> 0 | H42: =F42-G42 -> 0
B43: 8 | C43: 80 | E43: MISCELLANEOUS | F43: 0 | G43: =SUMIF($D$9:$D$26,$C$43,$G$9:$G$26) -> 0 | H43: =F43-G43 -> 0
B44: 9 | C44: 90 | E44: OTHER | F44: 0 | G44: =SUMIF($D$9:$D$26,$C$44,$G$9:$G$26) -> 0 | H44: =F44-G44 -> 0
E45: Total | F45: =SUM(F36:F44) -> 280000 | G45: =SUM(G36:G44) -> 280000 | H45: =SUM(H36:H44) -> 0
E46: % Profit | F46: =((C33-F45)/C33) -> 0.17572806
E47: Total Profit | F47: =F46*C33 -> 59693.72
E48: Gross Profit | F48: =C33-G45 -> 59693.72
E50: ค่าแรง โกวิท | F50: =F48*0.25 -> 14923.43

Sheet 22 TMD-005
B1: Factory/Company | C1: ='All Job balance report'!D21 -> Thai Meidensha Co., Ltd. | H1: Start Date | I1: 46113
B2: Project Name | C2: ='All Job balance report'!F21 -> งานติดตั้งท่อลากสายแอร์ OCC | H2: Sale Up Date
B3: Job Code. | C3: ='All Job balance report'!B21 -> TMD-2601/005 | M3: PO No.
B4: Quotation No. | E4: PROJECT BUDGET RECORD | H4: INVOICE (%) | I4: 0
B5: Contract Price | C5: =C33 -> 18000
B6: Budget Price | C6: =F45 -> 10000 | M6: Contract Price | P6: วัน | Q6: ค่าแรง
B7: PROFIT | C7: =(C5-C6)/C5 -> 0.44444444 | D7: ACTUAL | E7: 1 | L7: ค่าแรงงวดงานที่ 1 | M7: 21753.1 | O7: ช่างชัย | P7: 30 | Q7: 14000
B8: No. | C8: Vendor Name | D8: Material Number | E8: Description | F8: Text/Quo.No. | G8: Amount | H8: Updated By | I8: Date | J8: PO | L8: ค่าแรงงวดงานที่ 2 | M8: 39301.1 | O8: ช่างออม | P8: 25 | Q8: =400*P8 -> 10000
B9: 1 | C9: DDP | D9: 50 | E9: ค่าแรงทีมงาน | G9: 0 | H9: K.Kowit | I9: 46148 | L9: ค่าแรงงวดงานที่ 3 | M9: 0 | O9: ช่างบอล | P9: 6 | Q9: 6000
B10: 2 | L10: ค่าแรงงวดงานที่ 4 | M10: 0
B11: 3
B12: 4
B13: 6
B14: 8
B15: 9
B16: 10
B17: 11 | M17: =SUM(M7:M16) -> 61054.2 | Q17: =SUM(Q7:Q16) -> 30000
B18: 12
B19: 13
B20: 14
B23: 99
B24: 99
B25: 99
B26: 99
F27: TOTAL COST | G27: =SUM(G9:G26) -> 0
F28: BALANCE | G28: =$C$6-G27 -> 10000
F30: All BALANCE | G30: =G28/C6 -> 1
B32: Job. Code. | C32: ='All Job balance report'!B21 -> TMD-2601/005
B33: Contract Price | C33: ='All Job balance report'!G21 -> 18000 | D33: 0
B34: No. | C34: Code | E34: Description | F34: Budget | G34: Expense Record | H34: Balance | I34: Remark
B36: 1 | C36: 10 | E36: MATERIALS | F36: 0 | G36: =SUMIF($D$9:$D$26,$C$36,$G$9:$G$26) -> 0 | H36: =F36-G36 -> 0
B37: 2 | C37: 20 | E37: SUB CONTRACTOR | F37: 0 | G37: =SUMIF($D$9:$D$26,$C$37,$G$9:$G$26) -> 0 | H37: =F37-G37 -> 0
B38: 3 | C38: 30 | E38: HEAVY EQUIPMENT | F38: 0 | G38: =SUMIF($D$9:$D$26,$C$38,$G$9:$G$26) -> 0 | H38: =F38-G38 -> 0
B39: 4 | C39: 40 | E39: RENTAL | F39: 0 | G39: =SUMIF($D$9:$D$26,$C$39,$G$9:$G$26) -> 0 | H39: =F39-G39 -> 0
B40: 5 | C40: 50 | E40: STAFF EXPENSE | F40: 10000 | G40: =SUMIF($D$9:$D$26,$C$40,$G$9:$G$26) -> 0 | H40: =F40-G40 -> 10000
B41: 6 | C41: 60 | E41: OFFICE EXPENSE | F41: 0 | G41: =SUMIF($D$9:$D$26,$C$41,$G$9:$G$26) -> 0 | H41: =F41-G41 -> 0
B42: 7 | C42: 70 | E42: ENTERTAIN | F42: 0 | G42: =SUMIF($D$9:$D$26,$C$42,$G$9:$G$26) -> 0 | H42: =F42-G42 -> 0
B43: 8 | C43: 80 | E43: MISCELLANEOUS | F43: 0 | G43: =SUMIF($D$9:$D$26,$C$43,$G$9:$G$26) -> 0 | H43: =F43-G43 -> 0
B44: 9 | C44: 90 | E44: OTHER | F44: 0 | G44: =SUMIF($D$9:$D$26,$C$44,$G$9:$G$26) -> 0 | H44: =F44-G44 -> 0
E45: Total | F45: =SUM(F36:F44) -> 10000 | G45: =SUM(G36:G44) -> 0 | H45: =SUM(H36:H44) -> 10000
E46: % Profit | F46: =((C33-F45)/C33) -> 0.44444444
E47: Total Profit | F47: =F46*C33 -> 8000
E48: Gross Profit | F48: =C33-G45 -> 18000
E50: ค่าแรง โกวิท | F50: =F48*0.25 -> 4500

Sheet 21 TMD-004
B1: Factory/Company | C1: ='All Job balance report'!D20 -> Thai Meidensha Co., Ltd. | H1: Start Date | I1: 46113
B2: Project Name | C2: ='All Job balance report'!F20 -> งานติดตั้งท่อสำหรับ MWS 5 ห้อง | H2: Sale Up Date
B3: Job Code. | C3: ='All Job balance report'!B20 -> TMD-2601/004 | M3: PO No.
B4: Quotation No. | E4: PROJECT BUDGET RECORD | H4: INVOICE (%) | I4: 0
B5: Contract Price | C5: =C33 -> 620000
B6: Budget Price | C6: =F45 -> 550000 | M6: Contract Price | P6: วัน | Q6: ค่าแรง
B7: PROFIT | C7: =(C5-C6)/C5 -> 0.11290323 | D7: ACTUAL | E7: 1 | L7: ค่าแรงงวดงานที่ 1 | M7: 21753.1 | O7: ช่างชัย | P7: 30 | Q7: 14000
B8: No. | C8: Vendor Name | D8: Material Number | E8: Description | F8: Text/Quo.No. | G8: Amount | H8: Updated By | I8: Date | J8: PO | L8: ค่าแรงงวดงานที่ 2 | M8: 39301.1 | O8: ช่างออม | P8: 25 | Q8: =400*P8 -> 10000
B9: 1 | C9: APT | D9: 10 | E9: ค่าแรง งานติดตั้งระบบไฟฟ้า | G9: 480000 | H9: K.Kowit | I9: 46049 | L9: ค่าแรงงวดงานที่ 3 | M9: 0 | O9: ช่างบอล | P9: 6 | Q9: 6000
B10: 2 | C10: DDP | D10: 50 | E10: ค่าแรงทีมงาน | G10: 54535.42 | H10: K.Kowit | I10: 46148 | L10: ค่าแรงงวดงานที่ 4 | M10: 0
B11: 3 | C11: testpom | D11: 10 | E11: เหล็ก | G11: 5000 | H11: K.Pom
B12: 4
B13: 6
B14: 8
B15: 9
B16: 10
B17: 11 | M17: =SUM(M7:M16) -> 61054.2 | Q17: =SUM(Q7:Q16) -> 30000
B18: 12
B19: 13
B20: 14
B23: 99
B24: 99
B25: 99
B26: 99
F27: TOTAL COST | G27: =SUM(G9:G26) -> 539535.42
F28: BALANCE | G28: =$C$6-G27 -> 10464.58
F30: All BALANCE | G30: =G28/C6 -> 0.019026509
B32: Job. Code. | C32: ='All Job balance report'!B17 -> TMD-2601/003
B33: Contract Price | C33: ='All Job balance report'!G20 -> 620000 | D33: 0 | F33: (ต้นทุน) | G33: (ค่าใช้จ่าย)
B34: No. | C34: Code | E34: Description | F34: Budget | G34: Expense Record | H34: Balance | I34: Remark
B36: 1 | C36: 10 | E36: MATERIALS | F36: 10000 | G36: =SUMIF($D$9:$D$26,$C$36,$G$9:$G$26) -> 485000 | H36: =F36-G36 -> -475000
B37: 2 | C37: 20 | E37: SUB CONTRACTOR | F37: 480000 | G37: =SUMIF($D$9:$D$26,$C$37,$G$9:$G$26) -> 0 | H37: =F37-G37 -> 480000
B38: 3 | C38: 30 | E38: HEAVY EQUIPMENT | F38: 0 | G38: =SUMIF($D$9:$D$26,$C$38,$G$9:$G$26) -> 0 | H38: =F38-G38 -> 0
B39: 4 | C39: 40 | E39: RENTAL | F39: 0 | G39: =SUMIF($D$9:$D$26,$C$39,$G$9:$G$26) -> 0 | H39: =F39-G39 -> 0
B40: 5 | C40: 50 | E40: STAFF EXPENSE | F40: 60000 | G40: =SUMIF($D$9:$D$26,$C$40,$G$9:$G$26) -> 54535.42 | H40: =F40-G40 -> 5464.58
B41: 6 | C41: 60 | E41: OFFICE EXPENSE | F41: 0 | G41: =SUMIF($D$9:$D$26,$C$41,$G$9:$G$26) -> 0 | H41: =F41-G41 -> 0
B42: 7 | C42: 70 | E42: ENTERTAIN | F42: 0 | G42: =SUMIF($D$9:$D$26,$C$42,$G$9:$G$26) -> 0 | H42: =F42-G42 -> 0
B43: 8 | C43: 80 | E43: MISCELLANEOUS | F43: 0 | G43: =SUMIF($D$9:$D$26,$C$43,$G$9:$G$26) -> 0 | H43: =F43-G43 -> 0
B44: 9 | C44: 90 | E44: OTHER | F44: 0 | G44: =SUMIF($D$9:$D$26,$C$44,$G$9:$G$26) -> 0 | H44: =F44-G44 -> 0
E45: Total | F45: =SUM(F36:F44) -> 550000 | G45: =SUM(G36:G44) -> 539535.42 | H45: =SUM(H36:H44) -> 10464.58
E46: % Profit | F46: =((C33-F45)/C33) -> 0.11290323
E47: Total Profit | F47: =F46*C33 -> 70000
E48: Gross Profit | F48: =C33-G45 -> 80464.58
E50: ค่าแรง โกวิท | F50: =F48*0.25 -> 20116.145

Sheet 20 SOL-264 02
B1: Factory/Company | C1: ='All Job balance report'!D23 -> ร้าน Over Wash | H1: Start Date | I1: 45934
B2: Project Name | C2: ='All Job balance report'!F23 -> Solar cell 17.9kWp. | H2: Sale Up Date
B3: Job Code. | C3: ='All Job balance report'!B23 -> SOL-2604/02 | M3: PO No.
B4: Quotation No. | E4: PROJECT BUDGET RECORD | H4: INVOICE (%) | I4: 0
B5: Contract Price | C5: =C35 -> 235660
B6: Budget Price | C6: =F47 -> 215000 | M6: Contract Price | P6: วันทำงาน | Q6: ค่าแรง | U6: OT | V6: 1.5
B7: PROFIT | C7: =(C5-C6)/C5 -> 0.087668675 | D7: ACTUAL | E7: 1 | L7: ค่าแรงงวดงานที่ 1 | M7: 21753.1 | O7: ช่างชัย | P7: 3 | Q7: 14000 | R7: =Q7/25 -> 560 | S7: =R7*P7 -> 1680 | T7: =R7/8 -> 70 | U7: 8 | V7: =T7*U7*$V$6 -> 840
B8: No. | C8: Vendor Name | D8: Material Number | E8: Description | F8: Text/Quo.No. | G8: Amount | H8: Updated By | I8: Date | J8: PO | L8: ค่าแรงงวดงานที่ 2 | M8: 39301.1 | O8: ช่างออม | P8: 3 | Q8: 400 | R8: =Q8 -> 400 | S8: =R8*P8 -> 1200 | T8: =R8/8 -> 50 | U8: 8 | V8: =T8*U8*$V$6 -> 600
B9: 1 | C9: GTI | D9: 10 | E9: ค่าอุปกรณ์ ติดตั้ง แผง อินเวอร์เตอร์ Mounting | G9: 157888.08 | H9: K.Kowit | I9: 46122 | L9: ค่าแรงงวดงานที่ 3 | M9: 0 | O9: ช่างบอล | P9: 3 | Q9: 400 | R9: =Q9 -> 400 | S9: =R9*P9 -> 1200 | T9: =R9/8 -> 50 | U9: 8 | V9: =T9*U9*$V$6 -> 600
B10: 2 | C10: GTI | D10: 10 | E10: ค่าอุปกรณ์ ติดตั้ง Mounting | G10: 1318.24 | H10: K.Kowit | I10: 46122 | L10: ค่าแรงงวดงานที่ 4 | M10: 0 | O10: วิศวกร | P10: 3 | Q10: 24000 | R10: =Q10/25 -> 960 | S10: =R10*P10 -> 2880 | T10: =R10/8 -> 120 | U10: 8 | V10: =T10*U10*$V$6 -> 1440
B11: 3 | C11: GTI | D11: 10 | E11: ค่าอุปกรณ์ ติดตั้ง Mounting | G11: 809.78 | H11: K.Kowit | I11: 46122
B12: 4 | C12: Solar Thailand | D12: 10 | E12: ค่าสาย RS485 | G12: 2407.6 | H12: K.Kowit | I12: 46122
B13: 5 | C13: Electric and Cable Co., Ltd. | D13: 10 | E13: ค่าท่อและอุปกรณ์อื่นๆ | G13: 18741 | H13: K.Kowit | I13: 46122
B14: 6 | C14: Hardware House | D14: 10 | E14: สายไฟ THW 10Sq.mm. | G14: 5300 | H14: K.Kowit | I14: 46122
B15: 7 | D15: 10 | E15: เจมส์ซื้อของ | G15: 1272 | H15: เจมส์
B16: 8 | C16: ไทวัสดุ | D16: 10 | E16: เจมส์ซื้อของบันได | G16: 5068 | H16: เจมส์
B17: 9 | C17: Hardware House | D17: 10 | E17: เบรกเกอร์ ABB | G17: 500 | H17: เจมส์ | M17: =SUM(M7:M16) -> 61054.2 | S17: =SUM(S7:S16) -> 6960 | V17: =SUM(V7:V16) -> 3480
B18: 10 | C18: เมืองไฟฟ้า | D18: 10 | E18: อุปกรณ์ สิ้นเปลือง | G18: 1500 | H18: เจมส์
B19: 11 | C19: ปตท. | D19: 50 | E19: ค่าน้ำมันรถเดินทาง | G19: 2000 | H19: เจมส์ | S19: =S17+V17 -> 10440
B20: 12 | D20: 50 | E20: ค่าแรงคนงาน | G20: =S19 -> 10440 | H20: เจมส์
B21: 13 | D21: 50 | E21: ค่าแรงพี่ตุ๋ย | G21: 2000
B22: 14 | D22: 50 | E22: ค่าแรงมอสเขียนแบบ | G22: 2000
B23: 15
B24: 16
B25: 17
B26: 18
B27: 19
B28: 20
F29: TOTAL COST | G29: =SUM(G9:G28) -> 211244.7
F30: BALANCE | G30: =$C$6-G29 -> 3755.3
F32: All BALANCE | G32: =G30/C6 -> 0.017466512
B34: Job. Code. | C34: ='All Job balance report'!B23 -> SOL-2604/02
B35: Contract Price | C35: ='All Job balance report'!G23 -> 235660 | D35: 0
B36: No. | C36: Code | E36: Description | F36: Budget | G36: Expense Record | H36: Balance | I36: Remark
B38: 1 | C38: 10 | E38: MATERIALS | F38: 200000 | G38: =SUMIF($D$9:$D$28,$C$38,$G$9:$G$28) -> 194804.7 | H38: =F38-G38 -> 5195.3
B39: 2 | C39: 20 | E39: SUB CONTRACTOR | F39: 0 | G39: =SUMIF($D$9:$D$28,$C$39,$G$9:$G$28) -> 0 | H39: =F39-G39 -> 0
B40: 3 | C40: 30 | E40: HEAVY EQUIPMENT | F40: 0 | G40: =SUMIF($D$9:$D$28,$C$40,$G$9:$G$28) -> 0 | H40: =F40-G40 -> 0
B41: 4 | C41: 40 | E41: RENTAL | F41: 0 | G41: =SUMIF($D$9:$D$28,$C$41,$G$9:$G$28) -> 0 | H41: =F41-G41 -> 0
B42: 5 | C42: 50 | E42: STAFF EXPENSE | F42: 15000 | G42: =SUMIF($D$9:$D$28,$C$42,$G$9:$G$28) -> 16440 | H42: =F42-G42 -> -1440
B43: 6 | C43: 60 | E43: OFFICE EXPENSE | F43: 0 | G43: =SUMIF($D$9:$D$28,$C$43,$G$9:$G$28) -> 0 | H43: =F43-G43 -> 0
B44: 7 | C44: 70 | E44: ENTERTAIN | F44: 0 | G44: =SUMIF($D$9:$D$28,$C$44,$G$9:$G$28) -> 0 | H44: =F44-G44 -> 0
B45: 8 | C45: 80 | E45: MISCELLANEOUS | F45: 0 | G45: =SUMIF($D$9:$D$28,$C$45,$G$9:$G$28) -> 0 | H45: =F45-G45 -> 0
B46: 9 | C46: 90 | E46: OTHER | F46: 0 | G46: =SUMIF($D$9:$D$28,$C$46,$G$9:$G$28) -> 0 | H46: =F46-G46 -> 0
E47: Total | F47: =SUM(F38:F46) -> 215000 | G47: =SUM(G38:G46) -> 211244.7 | H47: =SUM(H38:H46) -> 3755.3
E48: % Profit | F48: =((C35-F47)/C35) -> 0.087668675
E49: Total Profit | F49: =F48*C35 -> 20660
E50: Gross Profit | F50: =C35-G47 -> 24415.3
F52: =F50/F47 -> 0.11355953

Sheet 15 RACH36
B1: Factory/Company | C1: บ้านคุณเม รัชดา 36 | H1: Start Date | I1: 45934
B2: Project Name | C2: ='All Job balance report'!F15 -> งานรถไฟฟ้าสายสีส้ม สำรวจหน้างาน | H2: Sale Up Date
B3: Job Code. | C3: =C32 -> TMD-2601/003 | M3: PO No.
B4: Quotation No. | E4: PROJECT BUDGET RECORD | H4: INVOICE (%) | I4: 0
B5: Contract Price | C5: =C33 -> 400000
B6: Budget Price | C6: =F45 -> 390000 | M6: Contract Price | P6: วัน | Q6: ค่าแรง
B7: PROFIT | C7: =(C5-C6)/C5 -> 0.025 | D7: ACTUAL | E7: 1 | L7: ค่าแรงงวดงานที่ 1 | M7: 21753.1 | O7: ช่างชัย | P7: 30 | Q7: 14000
B8: No. | C8: Vendor Name | D8: Material Number | E8: Description | F8: Text/Quo.No. | G8: Amount | H8: Updated By | I8: Date | J8: PO | L8: ค่าแรงงวดงานที่ 2 | M8: 39301.1 | O8: ช่างออม | P8: 25 | Q8: =400*P8 -> 10000
B9: 1 | D9: 20 | E9: ค่าติดตั้งอุปกรณ์ | G9: 85000 | H9: K.Kowit | I9: 46049 | L9: ค่าแรงงวดงานที่ 3 | M9: 0 | O9: ช่างบอล | P9: 6 | Q9: 6000
B10: 2 | D10: 10 | E10: ค่าแผง | G10: 299904 | H10: K.Kowit | L10: ค่าแรงงวดงานที่ 4 | M10: 0
B11: 3 | D11: 10 | E11: ค่าคอมมิชชั่น | G11: 2500 | H11: Ken
B12: 4
B13: 6
B14: 8
B15: 9
B16: 10
B17: 11 | M17: =SUM(M7:M16) -> 61054.2 | Q17: =SUM(Q7:Q16) -> 30000
B18: 12
B19: 13
B20: 14
B23: 99
B24: 99
B25: 99
B26: 99
F27: TOTAL COST | G27: =SUM(G9:G26) -> 387404
F28: BALANCE | G28: =$C$6-G27 -> 2596
F30: All BALANCE | G30: =G28/C6 -> 0.0066564103
B32: Job. Code. | C32: ='All Job balance report'!B17 -> TMD-2601/003
B33: Contract Price | C33: 400000 | D33: 0
B34: No. | C34: Code | E34: Description | F34: Budget | G34: Expense Record | H34: Balance | I34: Remark
B36: 1 | C36: 10 | E36: MATERIALS | F36: 300000 | G36: =SUMIF($D$9:$D$26,$C$36,$G$9:$G$26) -> 302404 | H36: =F36-G36 -> -2404
B37: 2 | C37: 20 | E37: SUB CONTRACTOR | F37: 90000 | G37: =SUMIF($D$9:$D$26,$C$37,$G$9:$G$26) -> 85000 | H37: =F37-G37 -> 5000
B38: 3 | C38: 30 | E38: HEAVY EQUIPMENT | F38: 0 | G38: =SUMIF($D$9:$D$26,$C$38,$G$9:$G$26) -> 0 | H38: =F38-G38 -> 0
B39: 4 | C39: 40 | E39: RENTAL | F39: 0 | G39: =SUMIF($D$9:$D$26,$C$39,$G$9:$G$26) -> 0 | H39: =F39-G39 -> 0
B40: 5 | C40: 50 | E40: STAFF EXPENSE | F40: 0 | G40: =SUMIF($D$9:$D$26,$C$40,$G$9:$G$26) -> 0 | H40: =F40-G40 -> 0
B41: 6 | C41: 60 | E41: OFFICE EXPENSE | F41: 0 | G41: =SUMIF($D$9:$D$26,$C$41,$G$9:$G$26) -> 0 | H41: =F41-G41 -> 0
B42: 7 | C42: 70 | E42: ENTERTAIN | F42: 0 | G42: =SUMIF($D$9:$D$26,$C$42,$G$9:$G$26) -> 0 | H42: =F42-G42 -> 0
B43: 8 | C43: 80 | E43: MISCELLANEOUS | F43: 0 | G43: =SUMIF($D$9:$D$26,$C$43,$G$9:$G$26) -> 0 | H43: =F43-G43 -> 0
B44: 9 | C44: 90 | E44: OTHER | F44: 0 | G44: =SUMIF($D$9:$D$26,$C$44,$G$9:$G$26) -> 0 | H44: =F44-G44 -> 0
E45: Total | F45: =SUM(F36:F44) -> 390000 | G45: =SUM(G36:G44) -> 387404 | H45: =SUM(H36:H44) -> 2596
E46: % Profit | F46: =((C33-F45)/C33) -> 0.025
E47: Total Profit | F47: =F46*C33 -> 10000
E48: Gross Profit | F48: =C33-G45 -> 12596

Sheet 14 TMD-2601-003
B1: Factory/Company | C1: ='All Job balance report'!D15 -> Thai Meidensha Co., Ltd. | H1: Start Date | I1: 45934
B2: Project Name | C2: ='All Job balance report'!F15 -> งานรถไฟฟ้าสายสีส้ม สำรวจหน้างาน | H2: Sale Up Date
B3: Job Code. | C3: =C32 -> TMD-2601/003 | M3: PO No.
B4: Quotation No. | E4: PROJECT BUDGET RECORD | H4: INVOICE (%) | I4: 0
B5: Contract Price | C5: =C33 -> 20000
B6: Budget Price | C6: =F45 -> 16000 | M6: Contract Price | P6: วัน | Q6: ค่าแรง
B7: PROFIT | C7: =(C5-C6)/C5 -> 0.2 | D7: ACTUAL | E7: 1 | L7: ค่าแรงงวดงานที่ 1 | M7: 21753.1 | O7: ช่างชัย | P7: 30 | Q7: 14000
B8: No. | C8: Vendor Name | D8: Material Number | E8: Description | F8: Text/Quo.No. | G8: Amount | H8: Updated By | I8: Date | J8: PO | L8: ค่าแรงงวดงานที่ 2 | M8: 39301.1 | O8: ช่างออม | P8: 25 | Q8: =400*P8 -> 10000
B9: 1 | H9: K.Kowit | I9: 46049 | L9: ค่าแรงงวดงานที่ 3 | M9: 0 | O9: ช่างบอล | P9: 6 | Q9: 6000
B10: 2 | L10: ค่าแรงงวดงานที่ 4 | M10: 0
B11: 3
B12: 4
B13: 6
B14: 8
B15: 9
B16: 10
B17: 11 | M17: =SUM(M7:M16) -> 61054.2 | Q17: =SUM(Q7:Q16) -> 30000
B18: 12
B19: 13
B20: 14
B23: 99
B24: 99
B25: 99
B26: 99
F27: TOTAL COST | G27: =SUM(G9:G26) -> 0
F28: BALANCE | G28: =$C$6-G27 -> 16000
F30: All BALANCE | G30: =G28/C6 -> 1
B32: Job. Code. | C32: ='All Job balance report'!B17 -> TMD-2601/003
B33: Contract Price | C33: ='All Job balance report'!G17 -> 20000 | D33: 0
B34: No. | C34: Code | E34: Description | F34: Budget | G34: Expense Record | H34: Balance | I34: Remark
B36: 1 | C36: 10 | E36: MATERIALS | F36: 0 | G36: =SUMIF($D$9:$D$26,$C$36,$G$9:$G$26) -> 0 | H36: =F36-G36 -> 0
B37: 2 | C37: 20 | E37: SUB CONTRACTOR | F37: 10000 | G37: =SUMIF($D$9:$D$26,$C$37,$G$9:$G$26) -> 0 | H37: =F37-G37 -> 10000
B38: 3 | C38: 30 | E38: HEAVY EQUIPMENT | F38: 0 | G38: =SUMIF($D$9:$D$26,$C$38,$G$9:$G$26) -> 0 | H38: =F38-G38 -> 0
B39: 4 | C39: 40 | E39: RENTAL | F39: 0 | G39: =SUMIF($D$9:$D$26,$C$39,$G$9:$G$26) -> 0 | H39: =F39-G39 -> 0
B40: 5 | C40: 50 | E40: STAFF EXPENSE | F40: 6000 | G40: =SUMIF($D$9:$D$26,$C$40,$G$9:$G$26) -> 0 | H40: =F40-G40 -> 6000
B41: 6 | C41: 60 | E41: OFFICE EXPENSE | F41: 0 | G41: =SUMIF($D$9:$D$26,$C$41,$G$9:$G$26) -> 0 | H41: =F41-G41 -> 0
B42: 7 | C42: 70 | E42: ENTERTAIN | F42: 0 | G42: =SUMIF($D$9:$D$26,$C$42,$G$9:$G$26) -> 0 | H42: =F42-G42 -> 0
B43: 8 | C43: 80 | E43: MISCELLANEOUS | F43: 0 | G43: =SUMIF($D$9:$D$26,$C$43,$G$9:$G$26) -> 0 | H43: =F43-G43 -> 0
B44: 9 | C44: 90 | E44: OTHER | F44: 0 | G44: =SUMIF($D$9:$D$26,$C$44,$G$9:$G$26) -> 0 | H44: =F44-G44 -> 0
E45: Total | F45: =SUM(F36:F44) -> 16000 | G45: =SUM(G36:G44) -> 0 | H45: =SUM(H36:H44) -> 16000
E46: % Profit | F46: =((C33-F45)/C33) -> 0.2
E47: Total Profit | F47: =F46*C33 -> 4000
E48: Gross Profit | F48: =C33-G45 -> 20000
E50: ค่าแรง โกวิท | F50: =F48*0.25 -> 5000

Sheet 13 JPP-2601-001
B1: Factory/Company | C1: ='All Job balance report'!D16 -> Jatupaspol Co., Ltd. | H1: Start Date | I1: 46045
B2: Project Name | C2: ='All Job balance report'!F16 -> งาน Manday ลากสาย Gulf | H2: Sale Up Date
B3: Job Code. | C3: ='All Job balance report'!B16 -> JPP-2500/001 | M3: PO No.
B4: Quotation No. | E4: PROJECT BUDGET RECORD | H4: INVOICE (%) | I4: 0
B5: Contract Price | C5: =C33 -> 69855
B6: Budget Price | C6: =F45 -> 15000 | M6: Contract Price
B7: PROFIT | C7: =(C5-C6)/C5 -> 0.78526949 | D7: ACTUAL | E7: 1 | L7: ค่าแรงงวดงานที่ 1 | M7: 0
B8: No. | C8: Vendor Name | D8: Material Number | E8: Description | F8: Text/Quo.No. | G8: Amount | H8: Updated By | I8: Date | J8: PO | L8: ค่าแรงงวดงานที่ 2 | M8: 0
B9: 1 | C9: MEGA Home ระยอง | D9: 10 | E9: ค่าอุปกรณ์เซฟตี้ | G9: 466.36 | H9: K.Kowit | I9: 46076 | L9: ค่าแรงงวดงานที่ 3 | M9: 0
B10: 2 | L10: ค่าแรงงวดงานที่ 4 | M10: 0
B11: 3
B12: 4
B13: 6
B14: 8
B15: 9
B16: 10
B17: 11 | M17: =SUM(M7:M16) -> 0
B18: 12
B19: 13
B20: 14
B23: 99
B24: 99
B25: 99
B26: 99
F27: TOTAL COST | G27: =SUM(G9:G26) -> 466.36
F28: BALANCE | G28: =$C$6-G27 -> 14533.64
F30: All BALANCE | G30: =G28/C6 -> 0.96890933
B32: Job. Code. | C32: ='All Job balance report'!B16 -> JPP-2500/001
B33: Contract Price | C33: ='All Job balance report'!G15 -> 69855 | D33: 0
B34: No. | C34: Code | E34: Description | F34: Budget | G34: Expense Record | H34: Balance | I34: Remark
B36: 1 | C36: 10 | E36: MATERIALS | F36: 5000 | G36: =SUMIF($D$9:$D$26,$C$36,$G$9:$G$26) -> 466.36 | H36: =F36-G36 -> 4533.64
B37: 2 | C37: 20 | E37: SUB CONTRACTOR | F37: 0 | G37: =SUMIF($D$9:$D$26,$C$37,$G$9:$G$26) -> 0 | H37: =F37-G37 -> 0
B38: 3 | C38: 30 | E38: HEAVY EQUIPMENT | F38: 0 | G38: =SUMIF($D$9:$D$26,$C$38,$G$9:$G$26) -> 0 | H38: =F38-G38 -> 0
B39: 4 | C39: 40 | E39: RENTAL | F39: 0 | G39: =SUMIF($D$9:$D$26,$C$39,$G$9:$G$26) -> 0 | H39: =F39-G39 -> 0
B40: 5 | C40: 50 | E40: STAFF EXPENSE | F40: 10000 | G40: =SUMIF($D$9:$D$26,$C$40,$G$9:$G$26) -> 0 | H40: =F40-G40 -> 10000
B41: 6 | C41: 60 | E41: OFFICE EXPENSE | F41: 0 | G41: =SUMIF($D$9:$D$26,$C$41,$G$9:$G$26) -> 0 | H41: =F41-G41 -> 0
B42: 7 | C42: 70 | E42: ENTERTAIN | F42: 0 | G42: =SUMIF($D$9:$D$26,$C$42,$G$9:$G$26) -> 0 | H42: =F42-G42 -> 0
B43: 8 | C43: 80 | E43: MISCELLANEOUS | F43: 0 | G43: =SUMIF($D$9:$D$26,$C$43,$G$9:$G$26) -> 0 | H43: =F43-G43 -> 0
B44: 9 | C44: 90 | E44: OTHER | F44: 0 | G44: =SUMIF($D$9:$D$26,$C$44,$G$9:$G$26) -> 0 | H44: =F44-G44 -> 0
E45: Total | F45: =SUM(F36:F44) -> 15000 | G45: =SUM(G36:G44) -> 466.36 | H45: =SUM(H36:H44) -> 14533.64
E46: % Profit | F46: =((C33-F45)/C33) -> 0.78526949
E47: Total Profit | F47: =F46*C33 -> 54855
E48: Gross Profit | F48: =C33-G45 -> 69388.64
E50: ค่าแรง โกวิท | F50: =F48*0.25 -> 17347.16

Sheet 12 TMD-2601-002
B1: Factory/Company | C1: ='All Job balance report'!D15 -> Thai Meidensha Co., Ltd. | H1: Start Date | I1: 45934
B2: Project Name | C2: ='All Job balance report'!F15 -> งานรถไฟฟ้าสายสีส้ม สำรวจหน้างาน | H2: Sale Up Date
B3: Job Code. | C3: =C32 -> TMD-2601/002 | M3: PO No.
B4: Quotation No. | E4: PROJECT BUDGET RECORD | H4: INVOICE (%) | I4: 0
B5: Contract Price | C5: =C33 -> 69855
B6: Budget Price | C6: =F45 -> 40000 | M6: Contract Price | P6: วัน | Q6: ค่าแรง
B7: PROFIT | C7: =(C5-C6)/C5 -> 0.4273853 | D7: ACTUAL | E7: 1 | L7: ค่าแรงงวดงานที่ 1 | M7: 20330 | O7: ช่างชัย | P7: 30 | Q7: 14000
B8: No. | C8: Vendor Name | D8: Material Number | E8: Description | F8: Text/Quo.No. | G8: Amount | H8: Updated By | I8: Date | J8: PO | L8: ค่าแรงงวดงานที่ 2 | M8: 36730 | O8: ช่างออม | P8: 25 | Q8: =400*P8 -> 10000
B9: 1 | C9: โฮมโปร พระราม 9 | D9: 10 | E9: ค่าอุปกรณ์เซฟตี้ และบันได | G9: 6745 | H9: K.Kowit | I9: 46049 | L9: ค่าแรงงวดงานที่ 3 | M9: 12795 | O9: ช่างบอล | P9: 6 | Q9: 6000
B10: 2 | D10: 10 | E10: หมวกเซฟตี้และชุดถถังปั่นไมโคร | G10: 1172.74 | H10: K.Kowit | I10: 46069 | L10: ค่าแรงงวดงานที่ 4 | M10: 0
B11: 3 | D11: 10 | E11: หน้ากากอนามัย แว่นตากันสะเก็ด | G11: 178.59 | H11: K.Kowit | I11: 46063
B12: 4 | D12: 50 | E12: ค่าแรงช่าง 3 คน | G12: =Q17 -> 30000 | H12: K.Kowit | I12: 46049
B13: 6
B14: 8
B15: 9
B16: 10
B17: 11 | M17: =SUM(M7:M16) -> 69855 | Q17: =SUM(Q7:Q16) -> 30000
B18: 12
B19: 13
B20: 14
B23: 99
B24: 99
B25: 99
B26: 99
F27: TOTAL COST | G27: =SUM(G9:G26) -> 38096.33
F28: BALANCE | G28: =$C$6-G27 -> 1903.67
F30: All BALANCE | G30: =G28/C6 -> 0.04759175
B32: Job. Code. | C32: ='All Job balance report'!B15 -> TMD-2601/002
B33: Contract Price | C33: ='All Job balance report'!G15 -> 69855 | D33: 0
B34: No. | C34: Code | E34: Description | F34: Budget | G34: Expense Record | H34: Balance | I34: Remark
B36: 1 | C36: 10 | E36: MATERIALS | F36: 10000 | G36: =SUMIF($D$9:$D$26,$C$36,$G$9:$G$26) -> 8096.33 | H36: =F36-G36 -> 1903.67
B37: 2 | C37: 20 | E37: SUB CONTRACTOR | F37: 0 | G37: =SUMIF($D$9:$D$26,$C$37,$G$9:$G$26) -> 0 | H37: =F37-G37 -> 0
B38: 3 | C38: 30 | E38: HEAVY EQUIPMENT | F38: 0 | G38: =SUMIF($D$9:$D$26,$C$38,$G$9:$G$26) -> 0 | H38: =F38-G38 -> 0
B39: 4 | C39: 40 | E39: RENTAL | F39: 0 | G39: =SUMIF($D$9:$D$26,$C$39,$G$9:$G$26) -> 0 | H39: =F39-G39 -> 0
B40: 5 | C40: 50 | E40: STAFF EXPENSE | F40: 30000 | G40: =SUMIF($D$9:$D$26,$C$40,$G$9:$G$26) -> 30000 | H40: =F40-G40 -> 0
B41: 6 | C41: 60 | E41: OFFICE EXPENSE | F41: 0 | G41: =SUMIF($D$9:$D$26,$C$41,$G$9:$G$26) -> 0 | H41: =F41-G41 -> 0
B42: 7 | C42: 70 | E42: ENTERTAIN | F42: 0 | G42: =SUMIF($D$9:$D$26,$C$42,$G$9:$G$26) -> 0 | H42: =F42-G42 -> 0
B43: 8 | C43: 80 | E43: MISCELLANEOUS | F43: 0 | G43: =SUMIF($D$9:$D$26,$C$43,$G$9:$G$26) -> 0 | H43: =F43-G43 -> 0
B44: 9 | C44: 90 | E44: OTHER | F44: 0 | G44: =SUMIF($D$9:$D$26,$C$44,$G$9:$G$26) -> 0 | H44: =F44-G44 -> 0
E45: Total | F45: =SUM(F36:F44) -> 40000 | G45: =SUM(G36:G44) -> 38096.33 | H45: =SUM(H36:H44) -> 1903.67
E46: % Profit | F46: =((C33-F45)/C33) -> 0.4273853
E47: Total Profit | F47: =F46*C33 -> 29855
E48: Gross Profit | F48: =C33-G45 -> 31758.67
E50: ค่าแรง โกวิท | F50: =F48*0.25 -> 7939.6675

Sheet 11 TMD-2601-001
B1: Factory/Company | C1: ='All Job balance report'!D14 -> Thai Meidensha Co., Ltd. | H1: Start Date | I1: 45934
B2: Project Name | C2: ='All Job balance report'!F14 -> งาน PM Test Protection Relay | H2: Sale Up Date
B3: Job Code. | C3: =C32 -> TMD-2601/001 | M3: PO No.
B4: Quotation No. | E4: PROJECT BUDGET RECORD | H4: INVOICE (%) | I4: 0
B5: Contract Price | C5: =C33 -> 42000
B6: Budget Price | C6: =F45 -> 40000 | M6: Contract Price
B7: PROFIT | C7: =(C5-C6)/C5 -> 0.047619048 | D7: ACTUAL | E7: 1
B8: No. | C8: Vendor Name | D8: Material Number | E8: Description | F8: Text/Quo.No. | G8: Amount | H8: Updated By | I8: Date | J8: PO
B9: 1 | D9: 20 | E9: ค่าแรงทีมเทส | G9: 37000 | H9: K.Kowit | I9: 46350
B10: 2
B11: 3
B12: 4
B13: 6
B14: 8
B15: 9
B16: 10
B17: 11
B18: 12
B23: 99
B24: 99
B25: 99
B26: 99
F27: TOTAL COST | G27: =SUM(G9:G26) -> 37000
F28: BALANCE | G28: =$C$6-G27 -> 3000
F30: All BALANCE | G30: =G28/C6 -> 0.075
B32: Job. Code. | C32: ='All Job balance report'!B14 -> TMD-2601/001
B33: Contract Price | C33: ='All Job balance report'!G14 -> 42000 | D33: 0
B34: No. | C34: Code | E34: Description | F34: Budget | G34: Expense Record | H34: Balance | I34: Remark
B36: 1 | C36: 10 | E36: MATERIALS | F36: 0 | G36: =SUMIF($D$9:$D$26,$C$36,$G$9:$G$26) -> 0 | H36: =F36-G36 -> 0
B37: 2 | C37: 20 | E37: SUB CONTRACTOR | F37: 40000 | G37: =SUMIF($D$9:$D$26,$C$37,$G$9:$G$26) -> 37000 | H37: =F37-G37 -> 3000
B38: 3 | C38: 30 | E38: HEAVY EQUIPMENT | F38: 0 | G38: =SUMIF($D$9:$D$26,$C$38,$G$9:$G$26) -> 0 | H38: =F38-G38 -> 0
B39: 4 | C39: 40 | E39: RENTAL | F39: 0 | G39: =SUMIF($D$9:$D$26,$C$39,$G$9:$G$26) -> 0 | H39: =F39-G39 -> 0
B40: 5 | C40: 50 | E40: STAFF EXPENSE | F40: 0 | G40: =SUMIF($D$9:$D$26,$C$40,$G$9:$G$26) -> 0 | H40: =F40-G40 -> 0
B41: 6 | C41: 60 | E41: OFFICE EXPENSE | F41: 0 | G41: =SUMIF($D$9:$D$26,$C$41,$G$9:$G$26) -> 0 | H41: =F41-G41 -> 0
B42: 7 | C42: 70 | E42: ENTERTAIN | F42: 0 | G42: =SUMIF($D$9:$D$26,$C$42,$G$9:$G$26) -> 0 | H42: =F42-G42 -> 0
B43: 8 | C43: 80 | E43: MISCELLANEOUS | F43: 0 | G43: =SUMIF($D$9:$D$26,$C$43,$G$9:$G$26) -> 0 | H43: =F43-G43 -> 0
B44: 9 | C44: 90 | E44: OTHER | F44: 0 | G44: =SUMIF($D$9:$D$26,$C$44,$G$9:$G$26) -> 0 | H44: =F44-G44 -> 0
E45: Total | F45: =SUM(F36:F44) -> 40000 | G45: =SUM(G36:G44) -> 37000 | H45: =SUM(H36:H44) -> 3000
E46: % Profit | F46: =((C33-F45)/C33) -> 0.047619048
E47: Total Profit | F47: =F46*C33 -> 2000
E48: Gross Profit | F48: =C33-G45 -> 5000
E50: ค่าแรง โกวิท | F50: =F48*0.25 -> 1250

Sheet 10 UNT-2601-001 รพ.ภัทรเวช (2)
B1: Factory/Company | C1: ='All Job balance report'!D13 -> Unity System Co., Ltd. | H1: Start Date | I1: 45934
B2: Project Name | C2: ='All Job balance report'!F13 -> งานค่าแรงผู้รับเหมา รพ.ภัทรเวช | H2: Sale Up Date
B3: Job Code. | C3: =C32 -> UNT-2601/001 | M3: PO No.
B4: Quotation No. | E4: PROJECT BUDGET RECORD | H4: INVOICE (%) | I4: 0
B5: Contract Price | C5: =C33 -> 143840.18
B6: Budget Price | C6: =F45 -> 143840.18 | M6: Contract Price
B7: PROFIT | C7: =(C5-C6)/C5 -> 0 | D7: ACTUAL | E7: 1
B8: No. | C8: Vendor Name | D8: Material Number | E8: Description | F8: Text/Quo.No. | G8: Amount | H8: Updated By | I8: Date | J8: PO
B9: 1 | C9: ค่าแรง ACL. | D9: 20 | E9: ค่าแรงทีมช่าง | G9: 35959.04 | H9: K.Kowit | I9: 46036
B10: 2 | D10: 20 | G10: 35107.15 | H10: K.Kowit | I10: 46045
B11: 3 | D11: 20 | G11: 57642 | H11: K.Kowit | I11: 46062
B12: 4 | D12: 20 | G12: 0
B13: 6
B14: 8
B15: 9
B16: 10
B17: 11
B18: 12
B23: 99 | C23: รายรับจากลูกค้าเดือน 8-15 ม.ค. | D23: 0 | E23: ค่าแรงงานรายวัน ทำงานติดตั้ง | G23: 37349.3 | H23: K.Kowit | I23: 45962
B24: 99 | C24: รายรับจากลูกค้าเดือน 16-31 ม.ค. | D24: 0 | E24: ค่าแรงงานรายวัน ทำงานติดตั้ง | G24: 38520 | H24: K.Kowit | I24: 46038
B25: 99 | C25: รายรับจากลูกค้าเดือน 1-16 ก.พ. | D25: 0 | E25: ค่าแรงงานรายวัน ทำงานติดตั้ง | G25: 51770.88 | H25: K.Kowit | I25: 46062
B26: 99 | C26: รายรับจากลูกค้าเดือน 1-16 ก.พ. | D26: 0 | E26: ค่าแรงงานรายวัน ทำงานติดตั้ง | G26: 16200 | H26: K.Kowit | I26: 46079
F27: TOTAL COST | G27: =SUM(G9:G19) -> 128708.19
F28: BALANCE | G28: =$C$6-G27 -> 15131.99
F30: All BALANCE | G30: =G28/C6 -> 0.10520002
B32: Job. Code. | C32: ='All Job balance report'!B13 -> UNT-2601/001
B33: Contract Price | C33: =SUMIF($D$9:$D$26,$D$33,$G$9:$G$26) -> 143840.18 | D33: 0
B34: No. | C34: Code | E34: Description | F34: Budget | G34: Expense Record | H34: Balance | I34: Remark
B36: 1 | C36: 10 | E36: MATERIALS | F36: 0 | G36: =SUMIF($D$9:$D$26,$C$36,$G$9:$G$26) -> 0 | H36: =F36-G36 -> 0
B37: 2 | C37: 20 | E37: SUB CONTRACTOR | F37: =C33 -> 143840.18 | G37: =SUMIF($D$9:$D$26,$C$37,$G$9:$G$26) -> 128708.19 | H37: =F37-G37 -> 15131.99
B38: 3 | C38: 30 | E38: HEAVY EQUIPMENT | F38: 0 | G38: =SUMIF($D$9:$D$26,$C$38,$G$9:$G$26) -> 0 | H38: =F38-G38 -> 0
B39: 4 | C39: 40 | E39: RENTAL | F39: 0 | G39: =SUMIF($D$9:$D$26,$C$39,$G$9:$G$26) -> 0 | H39: =F39-G39 -> 0
B40: 5 | C40: 50 | E40: STAFF EXPENSE | F40: 0 | G40: =SUMIF($D$9:$D$26,$C$40,$G$9:$G$26) -> 0 | H40: =F40-G40 -> 0
B41: 6 | C41: 60 | E41: OFFICE EXPENSE | F41: 0 | G41: =SUMIF($D$9:$D$26,$C$41,$G$9:$G$26) -> 0 | H41: =F41-G41 -> 0
B42: 7 | C42: 70 | E42: ENTERTAIN | F42: 0 | G42: =SUMIF($D$9:$D$26,$C$42,$G$9:$G$26) -> 0 | H42: =F42-G42 -> 0
B43: 8 | C43: 80 | E43: MISCELLANEOUS | F43: 0 | G43: =SUMIF($D$9:$D$26,$C$43,$G$9:$G$26) -> 0 | H43: =F43-G43 -> 0
B44: 9 | C44: 90 | E44: OTHER | F44: 0 | G44: =SUMIF($D$9:$D$26,$C$44,$G$9:$G$26) -> 0 | H44: =F44-G44 -> 0
E45: Total | F45: =SUM(F36:F44) -> 143840.18 | G45: =SUM(G36:G44) -> 128708.19 | H45: =SUM(H36:H44) -> 15131.99
E46: % Profit | F46: =((C33-F45)/C33) -> 0
E47: Total Profit | F47: =F46*C33 -> 0
E48: Gross Profit | F48: =C33-G45 -> 15131.99
E50: ค่าแรง โกวิท | F50: =F48*0.25 -> 3782.9975

Sheet 09 JEP-2601-001
B1: Factory/Company | C1: บริษัท เจตภัทร คอนสตรัคชั่น แอนด์ ดีไซน์ จำกัด | H1: Start Date | I1: 45955
B2: Project Name | C2: ='All Job balance report'!F12 -> งานติดตั้งคอนโด The Line Vibe ห้อง549 | H2: Sale Up Date | N2: B-A | O2: B-D | P2: ร้านกาแฟ | Q2: ร้านอาหาร
B3: Job Code. | C3: =C32 -> JEP-2601/001 | M3: PO No. | N3: PO6800405
B4: Quotation No. | E4: PROJECT BUDGET RECORD | H4: INVOICE (%) | I4: 0 | N4: PA6800158
B5: Contract Price | C5: =C33 -> 12000
B6: Budget Price | C6: =F45 -> 12800 | M6: Contract Price | N6: 2254570 | P6: 397867.06 | Q6: 513604.21
B7: PROFIT | C7: =(C5-C6)/C5 -> -0.066666667 | D7: ACTUAL | E7: 1 | N7: 265430.02
B8: No. | C8: Vendor Name | D8: Material Number | E8: Description | F8: Text/Quo.No. | G8: Amount | H8: Updated By | I8: Date | J8: PO
B9: 1 | C9: Thai Wassadu | D9: 10 | E9: สีและเครื่องมือ | G9: 7995 | H9: K.Kowit | I9: 46045
B10: 2 | C10: ช่างกั้ง | D10: 20 | E10: ค่าแรงช่างกั้ง | G10: 4800
B11: 4 | C11: ช่างเล็ก | D11: 20 | E11: ค่าแรงช่างมาช่วยทำผนังสีน้ำเงิน และเก็บรายละเอียด | G11: 2500
B12: 5 | C12: Thai Wassadu | D12: 10 | E12: ค่าของซื้อเพิ่ม ซื้อบันได | G12: 2600
B13: 7 | C13: Thai Wassadu | D13: 10 | E13: ค่าสีซื้อเพิ่มใช้แก้ไขงานทำสี | G13: 2300
B14: 7 | C14: Shoppy | D14: 80 | E14: ค่าซื้อทีวีใหม่ให้ลุกค้า | G14: 8350
B15: 7 | C15: HMPro | D15: 10 | E15: ค่าแปลงทาสี | G15: 500
B16: 7 | D16: 10 | E16: ค่าซื้อของและค่าไปทำคอนโดอีกที่หนึ่ง | G16: =300+150 -> 450
B17: 7 | C17: MEGA Home | D17: 10 | E17: ค่าซิลิโคน สำหรับเก็บงาน | G17: 300
B18: 8 | D18: 20 | E18: ค่าจ้างช่างชุดใหม่มาทำงาน | G18: 12500
B19: 9 | D19: 60 | E19: ค่าน้ำมัน | G19: 4000
B20: 6
B21: 3
B22: 10
B23: 11
B24: 12
B25: 13 | D25: 20 | E25: ค่าปรับจากงานเสียหายในห้องลูกค้า | G25: 12060
B26: 14
F27: TOTAL COST | G27: =SUM(G9:G26) -> 58355
F28: BALANCE | G28: =$C$6-G27 -> -45555
F30: All BALANCE | G30: =G28/C6 -> -3.5589844
B32: Job. Code. | C32: ='All Job balance report'!B12 -> JEP-2601/001
B33: Contract Price | C33: ='All Job balance report'!G12 -> 12000 | D33: 0
B34: No. | C34: Code | E34: Description | F34: Budget | G34: Expense Record | H34: Balance | I34: Remark
N35: B-A | O35: B-D | P35: ร้านกาแฟ | Q35: ร้านอาหาร
B36: 1 | C36: 10 | E36: MATERIALS | F36: 12800 | G36: =SUMIF($D$9:$D$26,$C$36,$G$9:$G$26) -> 14145 | H36: =F36-G36 -> -1345 | N36: =1391385.86+550222.39 -> 1941608.2 | O36: 187326.21 | P36: 171283.81 | Q36: 229202.12 | R36: =SUM(N36:Q36) -> 2529420.4
B37: 2 | C37: 20 | E37: SUB CONTRACTOR | F37: 0 | G37: =SUMIF($D$9:$D$26,$C$37,$G$9:$G$26) -> 31860 | H37: =F37-G37 -> -31860 | N37: =125499.72+40000-N40 -> 100499.72 | O37: =129657.59-O40 -> 79657.59 | P37: =119025.22-P40 -> 69025.22 | Q37: =145843.83-Q40 -> 115843.83 | R37: =SUM(N37:Q37) -> 365026.36
B38: 3 | C38: 30 | E38: HEAVY EQUIPMENT | F38: =R38 -> 0 | G38: =SUMIF($D$9:$D$26,$C$38,$G$9:$G$26) -> 0 | H38: =F38-G38 -> 0 | R38: =SUM(N38:Q38) -> 0
B39: 4 | C39: 40 | E39: RENTAL | F39: 0 | G39: =SUMIF($D$9:$D$26,$C$39,$G$9:$G$26) -> 0 | H39: =F39-G39 -> 0 | R39: =SUM(N39:Q39) -> 0
B40: 5 | C40: 50 | E40: STAFF EXPENSE | F40: 0 | G40: =SUMIF($D$9:$D$26,$C$40,$G$9:$G$26) -> 0 | H40: =F40-G40 -> 0 | N40: 65000 | O40: 50000 | P40: 50000 | Q40: 30000 | R40: =SUM(N40:Q40) -> 195000
B41: 6 | C41: 60 | E41: OFFICE EXPENSE | F41: 0 | G41: =SUMIF($D$9:$D$26,$C$41,$G$9:$G$26) -> 4000 | H41: =F41-G41 -> -4000 | R41: =SUM(N41:Q41) -> 0
B42: 7 | C42: 70 | E42: ENTERTAIN | F42: =R42 -> 0 | G42: =SUMIF($D$9:$D$26,$C$42,$G$9:$G$26) -> 0 | H42: =F42-G42 -> 0 | R42: =SUM(N42:Q42) -> 0
B43: 8 | C43: 80 | E43: MISCELLANEOUS | F43: 0 | G43: =SUMIF($D$9:$D$26,$C$43,$G$9:$G$26) -> 8350 | H43: =F43-G43 -> -8350 | R43: =SUM(N43:Q43) -> 0
B44: 9 | C44: 90 | E44: OTHER | F44: 0 | G44: =SUMIF($D$9:$D$26,$C$44,$G$9:$G$26) -> 0 | H44: =F44-G44 -> 0 | R44: =SUM(N44:Q44) -> 0
E45: Total | F45: =SUM(F36:F44) -> 12800 | G45: =SUM(G36:G44) -> 58355 | H45: =SUM(H36:H44) -> -45555 | R45: =SUM(N45:Q45) -> 0
E46: % Profit | F46: =((C33-F45)/C33) -> -0.066666667
E47: Total Profit | F47: =F46*C33 -> -800 | N47: =SUM(N36:N46) -> 2107108 | O47: =SUM(O36:O46) -> 316983.8 | P47: =SUM(P36:P46) -> 290309.03 | Q47: =SUM(Q36:Q46) -> 375045.95 | R47: =SUM(N47:Q47) -> 3089446.8
E48: Gross Profit | F48: =C33-G45 -> -46355
E50: ค่าแรง โกวิท | F50: =F48*0.25 -> -11588.75

Sheet 08 PKE-002 ติดตั้งพัดลมระบายอาก
B1: Factory/Company | C1: ='All Job balance report'!D5 -> PK Engineering Solution Service Co., Ltd. | H1: Start Date | I1: 45934
B2: Project Name | C2: ='All Job balance report'!F9 -> งานติดตั้งพัดลมระบายอากาศ | H2: Sale Up Date | N2: B-A | O2: B-D | P2: ร้านกาแฟ | Q2: ร้านอาหาร
B3: Job Code. | C3: =C30 -> PEK-2500/002 | M3: PO No. | N3: PO6800405
B4: Quotation No. | E4: PROJECT BUDGET RECORD | H4: INVOICE (%) | I4: 0 | N4: PA6800158
B5: Contract Price | C5: =C31 -> 7000
B6: Budget Price | C6: =F43 -> 4400 | M6: Contract Price | N6: 2254570 | P6: 397867.06 | Q6: 513604.21
B7: PROFIT | C7: =(C5-C6)/C5 -> 0.37142857 | D7: ACTUAL | E7: 1 | N7: 265430.02
B8: No. | C8: Vendor Name | D8: Material Number | E8: Description | F8: Text/Quo.No. | G8: Amount | H8: Updated By | I8: Date | J8: PO
B9: 1 | C9: ฮาร์ดแวร์เฮาส์ | D9: 10 | E9: พัดลมระบายอากาศ | G9: 737 | H9: K.Kowit | I9: 46017 | J9: ต้องเบิก
B10: 2 | C10: SCC | D10: 10 | E10: สวิสซ์ไฟ | G10: 33 | H10: K.Kowit | I10: 46017 | J10: ต้องเบิก
B11: 3 | D11: 10 | E11: ฝาหน้าสวิสซ์ | G11: 19 | H11: K.Kowit | I11: 46017 | J11: ต้องเบิก
B12: 4 | D12: 10 | E12: กล่องพลาสติก | G12: 9 | H12: K.Kowit | I12: 46017 | J12: ต้องเบิก
B13: 5 | D13: 10 | E13: สายไฟ 1.5 Sq.mm. | G13: =10*6 -> 60 | H13: K.Kowit | I13: 46017 | J13: ต้องเบิก
B14: 6 | D14: 10 | E14: ลูกบิดประตู | G14: 476 | H14: K.Kowit | I14: 46017 | J14: ต้องเบิก | L14: 476 | M14: 0.07 | N14: =M14*L14 -> 33.32
B15: 7 | D15: 10 | E15: ซิลิโคน | G15: 124 | H15: K.Kowit | I15: 46017 | J15: ต้องเบิก
B16: 8 | D16: 10 | E16: ปืนยิงซิลิโคน | G16: 71 | H16: K.Kowit | I16: 46017 | J16: ต้องเบิก
B17: 9 | D17: 10 | E17: รางหลังเต่า | G17: 29 | H17: K.Kowit | I17: 46017 | J17: ต้องเบิก
B18: 10 | D18: 10 | E18: น๊อตสกรูต่างๆ | G18: =116+28+18 -> 162 | H18: K.Kowit | I18: 46017 | J18: ต้องเบิก
B19: 11 | D19: 50 | E19: ค่าน้ำมัน | G19: 500 | H19: K.Kowit | I19: 46017 | J19: ต้องเบิก
B20: 12 | D20: 20 | E20: ค่าจ้างงานช่าง ชัย | G20: 900 | H20: K.Kowit | I20: 46017 | J20: ต้องเบิก
B21: 13 | D21: 50 | E21: ถุงมือ ตลับเมตร ฉากวัดไม้ | G21: =246+27+27+123 -> 423 | H21: K.Kowit | I21: 46017 | J21: ต้องเบิก
B22: 14
B23: 15
B24: 16
F25: TOTAL COST | G25: =SUM(G9:G24) -> 3543
F26: BALANCE | G26: =$C$6-G25 -> 857
F28: All BALANCE | G28: =G26/C6 -> 0.19477273
B30: Job. Code. | C30: ='All Job balance report'!B4 -> PEK-2500/002
B31: Contract Price | C31: ='All Job balance report'!G9 -> 7000
B32: No. | C32: Code | E32: Description | F32: Budget | G32: Expense Record | H32: Balance | I32: Remark
N33: B-A | O33: B-D | P33: ร้านกาแฟ | Q33: ร้านอาหาร
B34: 1 | C34: 10 | E34: MATERIALS | F34: 3000 | G34: =SUMIF($D$9:$D$24,$C$34,$G$9:$G$24) -> 1720 | H34: =F34-G34 -> 1280 | N34: =1391385.86+550222.39 -> 1941608.2 | O34: 187326.21 | P34: 171283.81 | Q34: 229202.12 | R34: =SUM(N34:Q34) -> 2529420.4
B35: 2 | C35: 20 | E35: SUB CONTRACTOR | F35: 900 | G35: =SUMIF($D$9:$D$24,$C$35,$G$9:$G$24) -> 900 | H35: =F35-G35 -> 0 | N35: =125499.72+40000-N38 -> 100499.72 | O35: =129657.59-O38 -> 79657.59 | P35: =119025.22-P38 -> 69025.22 | Q35: =145843.83-Q38 -> 115843.83 | R35: =SUM(N35:Q35) -> 365026.36
B36: 3 | C36: 30 | E36: HEAVY EQUIPMENT | F36: =R36 -> 0 | G36: =SUMIF($D$9:$D$24,$C$36,$G$9:$G$24) -> 0 | H36: =F36-G36 -> 0 | R36: =SUM(N36:Q36) -> 0
B37: 4 | C37: 40 | E37: RENTAL | F37: 0 | G37: =SUMIF($D$9:$D$24,$C$37,$G$9:$G$24) -> 0 | H37: =F37-G37 -> 0 | R37: =SUM(N37:Q37) -> 0
B38: 5 | C38: 50 | E38: STAFF EXPENSE | F38: 500 | G38: =SUMIF($D$9:$D$24,$C$38,$G$9:$G$24) -> 923 | H38: =F38-G38 -> -423 | N38: 65000 | O38: 50000 | P38: 50000 | Q38: 30000 | R38: =SUM(N38:Q38) -> 195000
B39: 6 | C39: 60 | E39: OFFICE EXPENSE | F39: 0 | G39: =SUMIF($D$9:$D$24,$C$39,$G$9:$G$24) -> 0 | H39: =F39-G39 -> 0 | R39: =SUM(N39:Q39) -> 0
B40: 7 | C40: 70 | E40: ENTERTAIN | F40: =R40 -> 0 | G40: =SUMIF($D$9:$D$24,$C$40,$G$9:$G$24) -> 0 | H40: =F40-G40 -> 0 | R40: =SUM(N40:Q40) -> 0
B41: 8 | C41: 80 | E41: MISCELLANEOUS | F41: 0 | G41: =SUMIF($D$9:$D$24,$C$41,$G$9:$G$24) -> 0 | H41: =F41-G41 -> 0 | R41: =SUM(N41:Q41) -> 0
B42: 9 | C42: 90 | E42: OTHER | F42: 0 | G42: =SUMIF($D$9:$D$24,$C$42,$G$9:$G$24) -> 0 | H42: =F42-G42 -> 0 | R42: =SUM(N42:Q42) -> 0
E43: Total | F43: =SUM(F34:F42) -> 4400 | G43: =SUM(G34:G42) -> 3543 | H43: =SUM(H34:H42) -> 857 | R43: =SUM(N43:Q43) -> 0
E44: % Profit | F44: =((C31-F43)/C31) -> 0.37142857
E45: Total Profit | F45: =F44*C31 -> 2600 | N45: =SUM(N34:N44) -> 2107108 | O45: =SUM(O34:O44) -> 316983.8 | P45: =SUM(P34:P44) -> 290309.03 | Q45: =SUM(Q34:Q44) -> 375045.95 | R45: =SUM(N45:Q45) -> 3089446.8
E46: Gross Profit | F46: =C31-G43 -> 3457
E48: ค่าแรง โกวิท | F48: =F46*0.25 -> 864.25

Sheet 07 SUT-001 บ้านห้วยขวาง
B1: Factory/Company | C1: งานคุณสุทธิพงษ์ | H1: Start Date | I1: 45955
B2: Project Name | C2: ='All Job balance report'!F8 -> งานบ้านห้วยขวาง | H2: Sale Up Date | N2: B-A | O2: B-D | P2: ร้านกาแฟ | Q2: ร้านอาหาร
B3: Job Code. | C3: =C32 -> SUT-2500/001 | M3: PO No. | N3: PO6800405
B4: Quotation No. | E4: PROJECT BUDGET RECORD | H4: INVOICE (%) | I4: 0 | N4: PA6800158
B5: Contract Price | C5: =C33 -> 37500
B6: Budget Price | C6: =F45 -> 28290 | M6: Contract Price | N6: 2254570 | P6: 397867.06 | Q6: 513604.21
B7: PROFIT | C7: =(C5-C6)/C5 -> 0.2456 | D7: ACTUAL | E7: 1 | N7: 265430.02
B8: No. | C8: Vendor Name | D8: Material Number | E8: Description | F8: Text/Quo.No. | G8: Amount | H8: Updated By | I8: Date | J8: PO
B9: 1 | C9: BPS | D9: 10 | E9: ท่อ กล่องพลาสติก ปลั๊กไฟ สวิสซ์ไฟ | G9: 6411.92 | H9: K.Kowit | I9: 45992
B10: 2 | C10: SCC | D10: 10 | E10: ค่าสายไฟ | G10: 9577 | H10: K.Kowit | I10: 45992
B11: 4 | C11: HMPro | D11: 10 | E11: ค่ากล่องพลาสติ๊ก | G11: 656.93 | H11: K.Kowit | I11: 45997 | J11: ต้องเบิก
B12: 5 | C12: ค่าน้ำมันรถ | D12: 50 | E12: ค่าน้ำมัน | G12: 1000 | H12: K.Kowit | I12: 45996 | J12: ต้องเบิก
B13: 7 | C13: HMPro | D13: 10 | E13: รางหลังเต่า | G13: 645.55 | H13: K.Kowit | I13: 46005 | J13: ต้องเบิก
B14: 7 | D14: 10 | E14: ค่าน้ำมัน | G14: 1000 | H14: K.Kowit | I14: 46004 | J14: ต้องเบิก
B15: 7 | C15: บริษัท เมืองไฟฟ้า จำกัด | D15: 10 | E15: แคมป์ก้ามปู | G15: 283.8 | H15: K.Kowit | I15: 46005 | J15: ต้องเบิก
B16: 7 | C16: บริษัท เมืองไฟฟ้า จำกัด | D16: 10 | E16: ท่อขาวและของซื้อเพิ่ม | G16: 2289 | H16: K.Kowit | I16: 46005 | J16: ต้องเบิก
B17: 7 | C17: บริษัท เมืองไฟฟ้า จำกัด | D17: 10 | E17: เกลียวปล่อย ปลั๊กคู่ กล่องลอย | G17: 546 | H17: K.Kowit | I17: 46005 | J17: ต้องเบิก
B18: 8 | C18: ไทวัสดุ | D18: 10 | E18: ซื้อของเพิ่ม ไทวัสดุ | G18: 250 | H18: K.Kowit | I18: 46005 | J18: ต้องเบิก
B19: 9 | C19: LINE MAN | D19: 10 | E19: ค่าส่งของ | G19: =150+70 -> 220 | H19: K.Kowit | I19: 46005 | J19: ต้องเบิก
B20: 6 | C20: ค่าจ้างพี่ตุ๋ย | D20: 20 | E20: ค่าแรงพี่ตุ๋ย | G20: 1000 | H20: K.Kowit | I20: 46005 | J20: บริษัทจ่าย
B21: 3 | C21: ค่าจ้างพี่ตุ๋ย | D21: 20 | E21: ค่าห้องพัก | G21: 800 | H21: K.Kowit | I21: 45992 | J21: บริษัทจ่าย
B22: 10 | D22: 20 | E22: ค่าห้องพักคนงาน | G22: 6700 | H22: K.Kowit | I22: 46003 | J22: บริษัทจ่าย
B23: 11 | C23: ค่าจ้างพี่ตุ๋ย | D23: 20 | E23: ค่าแรงเบิกล่วงหน้า | G23: 1000 | H23: K.Kowit | I23: 46006 | J23: ต้องเบิก
B24: 12 | D24: 20 | E24: ค่าแรงเบิกล่วงหน้า | G24: 1800 | H24: K.Kowit | I24: 46015
B25: 13 | D25: 20 | E25: ค่าแรงเบิกล่วงหน้า | G25: 800 | H25: K.Kowit | I25: 46015
B26: 14 | E26: ค่าแรงเบิกล่วงหน้า
F27: TOTAL COST | G27: =SUM(G9:G26) -> 34980.2
F28: BALANCE | G28: =$C$6-G27 -> -6690.2
F30: All BALANCE | G30: =G28/C6 -> -0.23648639
B32: Job. Code. | C32: ='All Job balance report'!B8 -> SUT-2500/001
B33: Contract Price | C33: ='All Job balance report'!G8 -> 37500 | D33: 0
B34: No. | C34: Code | E34: Description | F34: Budget | G34: Expense Record | H34: Balance | I34: Remark
N35: B-A | O35: B-D | P35: ร้านกาแฟ | Q35: ร้านอาหาร
B36: 1 | C36: 10 | E36: MATERIALS | F36: =16290+1500 -> 17790 | G36: =SUMIF($D$9:$D$26,$C$36,$G$9:$G$26) -> 21880.2 | H36: =F36-G36 -> -4090.2 | N36: =1391385.86+550222.39 -> 1941608.2 | O36: 187326.21 | P36: 171283.81 | Q36: 229202.12 | R36: =SUM(N36:Q36) -> 2529420.4
B37: 2 | C37: 20 | E37: SUB CONTRACTOR | F37: 9000 | G37: =SUMIF($D$9:$D$26,$C$37,$G$9:$G$26) -> 12100 | H37: =F37-G37 -> -3100 | N37: =125499.72+40000-N40 -> 100499.72 | O37: =129657.59-O40 -> 79657.59 | P37: =119025.22-P40 -> 69025.22 | Q37: =145843.83-Q40 -> 115843.83 | R37: =SUM(N37:Q37) -> 365026.36
B38: 3 | C38: 30 | E38: HEAVY EQUIPMENT | F38: =R38 -> 0 | G38: =SUMIF($D$9:$D$26,$C$38,$G$9:$G$26) -> 0 | H38: =F38-G38 -> 0 | R38: =SUM(N38:Q38) -> 0
B39: 4 | C39: 40 | E39: RENTAL | F39: 0 | G39: =SUMIF($D$9:$D$26,$C$39,$G$9:$G$26) -> 0 | H39: =F39-G39 -> 0 | R39: =SUM(N39:Q39) -> 0
B40: 5 | C40: 50 | E40: STAFF EXPENSE | F40: 1500 | G40: =SUMIF($D$9:$D$26,$C$40,$G$9:$G$26) -> 1000 | H40: =F40-G40 -> 500 | N40: 65000 | O40: 50000 | P40: 50000 | Q40: 30000 | R40: =SUM(N40:Q40) -> 195000
B41: 6 | C41: 60 | E41: OFFICE EXPENSE | F41: 0 | G41: =SUMIF($D$9:$D$26,$C$41,$G$9:$G$26) -> 0 | H41: =F41-G41 -> 0 | R41: =SUM(N41:Q41) -> 0
B42: 7 | C42: 70 | E42: ENTERTAIN | F42: =R42 -> 0 | G42: =SUMIF($D$9:$D$26,$C$42,$G$9:$G$26) -> 0 | H42: =F42-G42 -> 0 | R42: =SUM(N42:Q42) -> 0
B43: 8 | C43: 80 | E43: MISCELLANEOUS | F43: 0 | G43: =SUMIF($D$9:$D$26,$C$43,$G$9:$G$26) -> 0 | H43: =F43-G43 -> 0 | R43: =SUM(N43:Q43) -> 0
B44: 9 | C44: 90 | E44: OTHER | F44: 0 | G44: =SUMIF($D$9:$D$26,$C$44,$G$9:$G$26) -> 0 | H44: =F44-G44 -> 0 | R44: =SUM(N44:Q44) -> 0
E45: Total | F45: =SUM(F36:F44) -> 28290 | G45: =SUM(G36:G44) -> 34980.2 | H45: =SUM(H36:H44) -> -6690.2 | R45: =SUM(N45:Q45) -> 0
E46: % Profit | F46: =((C33-F45)/C33) -> 0.2456
E47: Total Profit | F47: =F46*C33 -> 9210 | N47: =SUM(N36:N46) -> 2107108 | O47: =SUM(O36:O46) -> 316983.8 | P47: =SUM(P36:P46) -> 290309.03 | Q47: =SUM(Q36:Q46) -> 375045.95 | R47: =SUM(N47:Q47) -> 3089446.8
E48: Gross Profit | F48: =C33-G45 -> 2519.8
E50: ค่าแรง โกวิท | F50: =F48*0.25 -> 629.95

Sheet 06 UNT-001 รพ.ภัทรเวช
B1: Factory/Company | C1: ='All Job balance report'!D7 -> Unity System Co., Ltd. | H1: Start Date | I1: 45934
B2: Project Name | C2: ='All Job balance report'!F7 -> งานค่าแรงผู้รับเหมา | H2: Sale Up Date
B3: Job Code. | C3: =C32 -> QMP-2500/001 | M3: PO No.
B4: Quotation No. | E4: PROJECT BUDGET RECORD | H4: INVOICE (%) | I4: 0
B5: Contract Price | C5: =C33 -> 371100
B6: Budget Price | C6: =F45 -> 371100 | M6: Contract Price
B7: PROFIT | C7: =(C5-C6)/C5 -> 0 | D7: ACTUAL | E7: 1
B8: No. | C8: Vendor Name | D8: Material Number | E8: Description | F8: Text/Quo.No. | G8: Amount | H8: Updated By | I8: Date | J8: PO
B9: 1 | C9: ฮาร์ดแวร์เฮาส | D9: 10 | E9: กุญแจ และโซ่ล็ฮคนั่งร้าน | G9: 400 | H9: K.Kowit | I9: 45965
B10: 2 | C10: A.C.L. Engineering Plus Co., Ltd. | D10: 20 | E10: ค่าแรงเดือน 24 - 1 พ.ย. | G10: 50334.4 | H10: K.Kowit | I10: 45965
B11: 3 | C11: บริษัท รุ่งเรืองนั่งร้าน แบบเหล็ก จำกัด | D11: 10 | E11: เช่านั่งร้าน | G11: 5500 | H11: K.Kowit | I11: 45965
B12: 4 | C12: บริษัท รุ่งเรืองนั่งร้าน แบบเหล็ก จำกัด | D12: 10 | E12: ค่านั่งร้านสูญหาย | G12: 10000 | H12: K.Kowit | I12: 45977
B13: 6 | C13: A.C.L. Engineering Plus Co., Ltd. | D13: 20 | E13: ค่าแรงเดือน 2 -15 พ.ย. | G13: 79340.25 | H13: K.Kowit | I13: 45982
B14: 8 | C14: ค่าน้ำมันรถ | D14: 50 | E14: ค่าน้ำมัน | G14: 600 | H14: K.Kowit | I14: 45982
B15: 9 | D15: 10 | E15: ค่าเสื้อคนงาน | G15: 3400 | H15: K.Kowit | I15: 46001
B16: 10 | D16: 80 | E16: ค่าส่งจดหมาย | G16: 450 | H16: K.Kowit | I16: 46001
B17: 11 | D17: 20 | E17: ค่าแรงเดือน พ.ย. 16-30 | G17: 102020.88 | H17: K.Kowit | I17: 46001
B18: 12 | D18: 20 | E18: ค่าแรงเดือน ธ.ค. 1-16 | G18: 98874.75 | H18: K.Kowit | I18: 46009
B23: 99 | C23: รายรับจากลูกค้าเดือน 1-15 ธ.ค. | D23: 0 | E23: ค่าแรงงานรายวัน ทำงานติดตั้ง | G23: 117500 | H23: K.Kowit | I23: 45962
B24: 99 | C24: รายรับจากลูกค้าเดือน 24 - 2 ต.ค. | D24: 0 | E24: ค่าแรงงานรายวัน ทำงานติดตั้ง | G24: 48000 | H24: K.Kowit | I24: 45962
B25: 99 | C25: รายรับจากลูกค้าเดือน 1-16 พ.ย. | D25: 0 | E25: ค่าแรงงานรายวัน ทำงานติดตั้ง | G25: 104600 | H25: K.Kowit | I25: 45962
B26: 99 | C26: รายรับจากลูกค้าเดือน 16-30 พ.ย. | D26: 0 | E26: ค่าแรงงานรายวัน ทำงานติดตั้ง | G26: 101000 | H26: K.Kowit | I26: 45962
F27: TOTAL COST | G27: =SUM(G9:G19) -> 350920.28
F28: BALANCE | G28: =$C$6-G27 -> 20179.72
F30: All BALANCE | G30: =G28/C6 -> 0.054378119
B32: Job. Code. | C32: ='All Job balance report'!B6 -> QMP-2500/001
B33: Contract Price | C33: =SUMIF($D$9:$D$26,$D$33,$G$9:$G$26) -> 371100 | D33: 0
B34: No. | C34: Code | E34: Description | F34: Budget | G34: Expense Record | H34: Balance | I34: Remark
B36: 1 | C36: 10 | E36: MATERIALS | F36: 0 | G36: =SUMIF($D$9:$D$26,$C$36,$G$9:$G$26) -> 19300 | H36: =F36-G36 -> -19300
B37: 2 | C37: 20 | E37: SUB CONTRACTOR | F37: =C33 -> 371100 | G37: =SUMIF($D$9:$D$26,$C$37,$G$9:$G$26) -> 330570.28 | H37: =F37-G37 -> 40529.72
B38: 3 | C38: 30 | E38: HEAVY EQUIPMENT | F38: 0 | G38: =SUMIF($D$9:$D$26,$C$38,$G$9:$G$26) -> 0 | H38: =F38-G38 -> 0
B39: 4 | C39: 40 | E39: RENTAL | F39: 0 | G39: =SUMIF($D$9:$D$26,$C$39,$G$9:$G$26) -> 0 | H39: =F39-G39 -> 0
B40: 5 | C40: 50 | E40: STAFF EXPENSE | F40: 0 | G40: =SUMIF($D$9:$D$26,$C$40,$G$9:$G$26) -> 600 | H40: =F40-G40 -> -600
B41: 6 | C41: 60 | E41: OFFICE EXPENSE | F41: 0 | G41: =SUMIF($D$9:$D$26,$C$41,$G$9:$G$26) -> 0 | H41: =F41-G41 -> 0
B42: 7 | C42: 70 | E42: ENTERTAIN | F42: 0 | G42: =SUMIF($D$9:$D$26,$C$42,$G$9:$G$26) -> 0 | H42: =F42-G42 -> 0
B43: 8 | C43: 80 | E43: MISCELLANEOUS | F43: 0 | G43: =SUMIF($D$9:$D$26,$C$43,$G$9:$G$26) -> 450 | H43: =F43-G43 -> -450
B44: 9 | C44: 90 | E44: OTHER | F44: 0 | G44: =SUMIF($D$9:$D$26,$C$44,$G$9:$G$26) -> 0 | H44: =F44-G44 -> 0
E45: Total | F45: =SUM(F36:F44) -> 371100 | G45: =SUM(G36:G44) -> 350920.28 | H45: =SUM(H36:H44) -> 20179.72
E46: % Profit | F46: =((C33-F45)/C33) -> 0
E47: Total Profit | F47: =F46*C33 -> 0
E48: Gross Profit | F48: =C33-G45 -> 20179.72
E50: ค่าแรง โกวิท | F50: =F48*0.25 -> 5044.93

Sheet 05 QMP-001งาน PM 315kVA
B1: Factory/Company | C1: ='All Job balance report'!D6 -> บริษัท ควอลิตี้ มีท โปรเซสซิ่ง จำกัด | H1: Start Date | I1: 45934
B2: Project Name | C2: ='All Job balance report'!F6 -> งาน PM หม้อแปลง 315kVA | H2: Sale Up Date | N2: B-A | O2: B-D | P2: ร้านกาแฟ | Q2: ร้านอาหาร
B3: Job Code. | C3: =C24 -> PEK-2500/002 | M3: PO No. | N3: PO6800405
B4: Quotation No. | E4: PROJECT BUDGET RECORD | H4: INVOICE (%) | I4: 0 | N4: PA6800158
B5: Contract Price | C5: =C25 -> 26000
B6: Budget Price | C6: =F37 -> 18800 | M6: Contract Price | N6: 2254570 | P6: 397867.06 | Q6: 513604.21
B7: PROFIT | C7: =(C5-C6)/C5 -> 0.27692308 | D7: ACTUAL | E7: 1 | N7: 265430.02
B8: No. | C8: Vendor Name | D8: Material Number | E8: Description | F8: Text/Quo.No. | G8: Amount | H8: Updated By | I8: Date | J8: PO
B9: 1 | C9: FTECH | D9: 20 | E9: งานทดสอบหม้อแปลงและเปลี่ยนมิเตอร์ | G9: 10000 | H9: K.Kowit | I9: 45979
B10: 2 | C10: พี่สุ | D10: 20 | E10: ค่าแรงพี่สุ | G10: 6000 | H10: K.Kowit | I10: 45978
B11: 3 | C11: ปั้ม Caltex | D11: 50 | E11: แก๊สรถยนต์ | G11: 607 | H11: K.Kowit | I11: 45977 | J11: ต้องเบิก
B12: 4 | C12: ปั้ม ปตท. | D12: 50 | E12: ค่าน้ำมัน | G12: 460 | H12: K.Kowit | I12: 45977 | J12: ต้องเบิก
B13: 5 | C13: รถเก๋งฟิล์ม-เฟิร์น | D13: 40 | E13: ค่าเช่ารถเดินทางไปทำงาน | G13: 1000 | H13: K.Kowit | I13: 45977 | J13: จ่ายตรงเจ้าของรถ
B14: 6
B15: 7
B16: 8
B17: 9
B18: 10
F19: TOTAL COST | G19: =SUM(G9:G18) -> 18067
F20: BALANCE | G20: =$C$6-G19 -> 733
F22: All BALANCE | G22: =G20/C6 -> 0.038989362
B24: Job. Code. | C24: ='All Job balance report'!B4 -> PEK-2500/002
B25: Contract Price | C25: ='All Job balance report'!G6 -> 26000
B26: No. | C26: Code | E26: Description | F26: Budget | G26: Expense Record | H26: Balance | I26: Remark
N27: B-A | O27: B-D | P27: ร้านกาแฟ | Q27: ร้านอาหาร
B28: 1 | C28: 10 | E28: MATERIALS | F28: 0 | G28: =SUMIF($D$9:$D$18,$C$28,$G$9:$G$18) -> 0 | H28: =F28-G28 -> 0 | N28: =1391385.86+550222.39 -> 1941608.2 | O28: 187326.21 | P28: 171283.81 | Q28: 229202.12 | R28: =SUM(N28:Q28) -> 2529420.4
B29: 2 | C29: 20 | E29: SUB CONTRACTOR | F29: 16000 | G29: =SUMIF($D$9:$D$18,$C$29,$G$9:$G$18) -> 16000 | H29: =F29-G29 -> 0 | N29: =125499.72+40000-N32 -> 100499.72 | O29: =129657.59-O32 -> 79657.59 | P29: =119025.22-P32 -> 69025.22 | Q29: =145843.83-Q32 -> 115843.83 | R29: =SUM(N29:Q29) -> 365026.36
B30: 3 | C30: 30 | E30: HEAVY EQUIPMENT | F30: =R30 -> 0 | G30: =SUMIF($D$9:$D$18,$C$30,$G$9:$G$18) -> 0 | H30: =F30-G30 -> 0 | R30: =SUM(N30:Q30) -> 0
B31: 4 | C31: 40 | E31: RENTAL | F31: 1000 | G31: =SUMIF($D$9:$D$18,$C$31,$G$9:$G$18) -> 1000 | H31: =F31-G31 -> 0 | R31: =SUM(N31:Q31) -> 0
B32: 5 | C32: 50 | E32: STAFF EXPENSE | F32: 1800 | G32: =SUMIF($D$9:$D$18,$C$32,$G$9:$G$18) -> 1067 | H32: =F32-G32 -> 733 | N32: 65000 | O32: 50000 | P32: 50000 | Q32: 30000 | R32: =SUM(N32:Q32) -> 195000
B33: 6 | C33: 60 | E33: OFFICE EXPENSE | F33: 0 | G33: =SUMIF($D$9:$D$18,$C$33,$G$9:$G$18) -> 0 | H33: =F33-G33 -> 0 | R33: =SUM(N33:Q33) -> 0
B34: 7 | C34: 70 | E34: ENTERTAIN | F34: =R34 -> 0 | G34: =SUMIF($D$9:$D$18,$C$34,$G$9:$G$18) -> 0 | H34: =F34-G34 -> 0 | R34: =SUM(N34:Q34) -> 0
B35: 8 | C35: 80 | E35: MISCELLANEOUS | F35: 0 | G35: =SUMIF($D$9:$D$18,$C$35,$G$9:$G$18) -> 0 | H35: =F35-G35 -> 0 | R35: =SUM(N35:Q35) -> 0
B36: 9 | C36: 90 | E36: OTHER | F36: 0 | G36: =SUMIF($D$9:$D$18,$C$36,$G$9:$G$18) -> 0 | H36: =F36-G36 -> 0 | R36: =SUM(N36:Q36) -> 0
E37: Total | F37: =SUM(F28:F36) -> 18800 | G37: =SUM(G28:G36) -> 18067 | H37: =SUM(H28:H36) -> 733 | R37: =SUM(N37:Q37) -> 0
E38: % Profit | F38: =((C25-F37)/C25) -> 0.27692308
E39: Total Profit | F39: =F38*C25 -> 7200 | N39: =SUM(N28:N38) -> 2107108 | O39: =SUM(O28:O38) -> 316983.8 | P39: =SUM(P28:P38) -> 290309.03 | Q39: =SUM(Q28:Q38) -> 375045.95 | R39: =SUM(N39:Q39) -> 3089446.8
E40: Gross Profit | F40: =C25-G37 -> 7933
E42: ค่าแรง โกวิท | F42: =F40*0.25 -> 1983.25

Sheet 04 PKE-001 ติดตั้งลากสาย RASA1
B1: Factory/Company | C1: ='All Job balance report'!D5 -> PK Engineering Solution Service Co., Ltd. | H1: Start Date | I1: 45934
B2: Project Name | C2: ='All Job balance report'!F5 -> งานติดตั้งตู้ และทำ Tray รสา 1 ชั้น 18 19 | H2: Sale Up Date | N2: B-A | O2: B-D | P2: ร้านกาแฟ | Q2: ร้านอาหาร
B3: Job Code. | C3: =C31 -> PEK-2500/002 | M3: PO No. | N3: PO6800405
B4: Quotation No. | E4: PROJECT BUDGET RECORD | H4: INVOICE (%) | I4: 0 | N4: PA6800158
B5: Contract Price | C5: =C32 -> 32460
B6: Budget Price | C6: =F44 -> 24400 | M6: Contract Price | N6: 2254570 | P6: 397867.06 | Q6: 513604.21
B7: PROFIT | C7: =(C5-C6)/C5 -> 0.24830561 | D7: ACTUAL | E7: 1 | N7: 265430.02
B8: No. | C8: Vendor Name | D8: Material Number | E8: Description | F8: Text/Quo.No. | G8: Amount | H8: Updated By | I8: Date | J8: PO
B9: 1 | C9: ฮาร์ดแวร์เฮาส์ | D9: 10 | E9: ค่า Power Plug | F9: CS1681009-0787 | G9: 1092 | H9: K.Kowit | I9: 45934
B10: 2 | C10: SCC | D10: 10 | E10: ค่าสายไฟ | G10: 3318 | H10: K.Kowit | I10: 45941
B11: 3 | D11: 10 | E11: ค่า Wireway | G11: 1214.45 | H11: K.Kowit | I11: 45945
B12: 4 | D12: 50 | E12: ค่าที่จอดรถ 1 | G12: 280 | H12: K.Kowit | I12: 45945 | J12: ต้องเบิก
B13: 5 | D13: 50 | E13: ค่าที่จอดรถ 2 | G13: 280 | H13: K.Kowit | I13: 45945 | J13: ต้องเบิก
B14: 6 | D14: 20 | E14: ค่าแรงพี่ตุ๋ย | G14: 6780 | H14: K.Kowit | I14: 45945
B15: 7 | D15: 20 | E15: ลาล่ามูฟส่งของ | G15: 181 | H15: K.Kowit | I15: 45945
B16: 8 | D16: 20 | E16: ค่าจ้างงานแก้ไข | G16: 800 | H16: K.Kowit | I16: 45947
B17: 9 | D17: 10 | E17: ค่า Flex อ่อน ใส่ใต้ตู้ | G17: 631.3 | H17: K.Kowit | I17: 45947
B18: 10 | D18: 90 | E18: จ้างมอสออกแบบโซล่าเซลล์ | G18: 2000 | H18: K.Kowit | I18: 45947
B19: 11 | D19: 50 | E19: ค่าน้ำมัน | G19: 349.4 | H19: K.Kowit | I19: 45947
B20: 12 | D20: 50 | E20: ค่าทางด่วน | G20: 60 | H20: K.Kowit | I20: 45947
B21: 12 | D21: 10 | E21: ค่าอุปกรณ์สำหรับงานชั้น 18 | G21: 1427.5 | H21: K.Kowit | I21: 45947
B22: 12 | D22: 10 | E22: ค่าอุปกรณ์สำหรับงานชั้น 19 | G22: 1527.43 | H22: K.Kowit | I22: 45979
B23: 12 | D23: 50 | E23: ค่าที่จอดรถ | G23: 440 | H23: K.Kowit | I23: 45947
B24: 12 | D24: 50 | E24: ค่าแรงทีมช่าง | G24: 3300 | H24: K.Kowit | I24: 45947
B25: 12
F26: TOTAL COST | G26: =SUM(G9:G25) -> 23681.08
F27: BALANCE | G27: =$C$6-G26 -> 718.92
F29: All BALANCE | G29: =G27/C6 -> 0.029463934
B31: Job. Code. | C31: ='All Job balance report'!B4 -> PEK-2500/002
B32: Contract Price | C32: ='All Job balance report'!G5 -> 32460
B33: No. | C33: Code | E33: Description | F33: Budget | G33: Expense Record | H33: Balance | I33: Remark
N34: B-A | O34: B-D | P34: ร้านกาแฟ | Q34: ร้านอาหาร
B35: 1 | C35: 10 | E35: MATERIALS | F35: =6900+4450 -> 11350 | G35: =SUMIF($D$9:$D$25,$C$35,$G$9:$G$25) -> 9210.68 | H35: =F35-G35 -> 2139.32 | N35: =1391385.86+550222.39 -> 1941608.2 | O35: 187326.21 | P35: 171283.81 | Q35: 229202.12 | R35: =SUM(N35:Q35) -> 2529420.4
B36: 2 | C36: 20 | E36: SUB CONTRACTOR | F36: =6500+3550 -> 10050 | G36: =SUMIF($D$9:$D$25,$C$36,$G$9:$G$25) -> 7761 | H36: =F36-G36 -> 2289 | N36: =125499.72+40000-N39 -> 100499.72 | O36: =129657.59-O39 -> 79657.59 | P36: =119025.22-P39 -> 69025.22 | Q36: =145843.83-Q39 -> 115843.83 | R36: =SUM(N36:Q36) -> 365026.36
B37: 3 | C37: 30 | E37: HEAVY EQUIPMENT | F37: =R37 -> 0 | G37: =SUMIF($D$9:$D$25,$C$37,$G$9:$G$25) -> 0 | H37: =F37-G37 -> 0 | R37: =SUM(N37:Q37) -> 0
B38: 4 | C38: 40 | E38: RENTAL | F38: 0 | G38: =SUMIF($D$9:$D$25,$C$38,$G$9:$G$25) -> 0 | H38: =F38-G38 -> 0 | R38: =SUM(N38:Q38) -> 0
B39: 5 | C39: 50 | E39: STAFF EXPENSE | F39: =1500+1000+500 -> 3000 | G39: =SUMIF($D$9:$D$25,$C$39,$G$9:$G$25) -> 4709.4 | H39: =F39-G39 -> -1709.4 | N39: 65000 | O39: 50000 | P39: 50000 | Q39: 30000 | R39: =SUM(N39:Q39) -> 195000
B40: 6 | C40: 60 | E40: OFFICE EXPENSE | F40: 0 | G40: =SUMIF($D$9:$D$25,$C$40,$G$9:$G$25) -> 0 | H40: =F40-G40 -> 0 | R40: =SUM(N40:Q40) -> 0
B41: 7 | C41: 70 | E41: ENTERTAIN | F41: =R41 -> 0 | G41: =SUMIF($D$9:$D$25,$C$41,$G$9:$G$25) -> 0 | H41: =F41-G41 -> 0 | R41: =SUM(N41:Q41) -> 0
B42: 8 | C42: 80 | E42: MISCELLANEOUS | F42: 0 | G42: =SUMIF($D$9:$D$25,$C$42,$G$9:$G$25) -> 0 | H42: =F42-G42 -> 0 | R42: =SUM(N42:Q42) -> 0
B43: 9 | C43: 90 | E43: OTHER | F43: 0 | G43: =SUMIF($D$9:$D$25,$C$43,$G$9:$G$25) -> 2000 | H43: =F43-G43 -> -2000 | R43: =SUM(N43:Q43) -> 0
E44: Total | F44: =SUM(F35:F43) -> 24400 | G44: =SUM(G35:G43) -> 23681.08 | H44: =SUM(H35:H43) -> 718.92 | R44: =SUM(N44:Q44) -> 0
E45: % Profit | F45: =((C32-F44)/C32) -> 0.24830561
E46: Total Profit | F46: =F45*C32 -> 8060 | N46: =SUM(N35:N45) -> 2107108 | O46: =SUM(O35:O45) -> 316983.8 | P46: =SUM(P35:P45) -> 290309.03 | Q46: =SUM(Q35:Q45) -> 375045.95 | R46: =SUM(N46:Q46) -> 3089446.8
E47: Gross Profit | F47: =C32-G44 -> 8778.92
E49: ค่าแรง โกวิท | F49: =F47*0.25 -> 2194.73

Sheet 03 TG-002 เปลี่ยน ACB
B1: Factory/Company | C1: PROCHAIN | H1: Start Date | I1: 45934
B2: Project Name | C2: ='All Job balance report'!F4 -> เปลี่ยน ACB Big-C Udonthani | H2: Sale Up Date | N2: B-A | O2: B-D | P2: ร้านกาแฟ | Q2: ร้านอาหาร
B3: Job Code. | C3: =C25 -> PEK-2500/002 | M3: PO No. | N3: PO6800405
B4: Quotation No. | E4: PROJECT BUDGET RECORD | H4: INVOICE (%) | I4: 0 | N4: PA6800158
B5: Contract Price | C5: =C26 -> 163000
B6: Budget Price | C6: =F38 -> 149500 | M6: Contract Price | N6: 2254570 | P6: 397867.06 | Q6: 513604.21
B7: PROFIT | C7: =(C5-C6)/C5 -> 0.082822086 | D7: ACTUAL | E7: 1 | N7: 265430.02
B8: No. | C8: Vendor Name | D8: Material Number | E8: Description | F8: Text/Quo.No. | G8: Amount | H8: Updated By | I8: Date | J8: PO
N9: =SUM(N6:N8) -> 2520000 | O9: =SUM(O6:O8) -> 0 | P9: =SUM(P6:P8) -> 397867.06 | Q9: =SUM(Q6:Q8) -> 513604.21 | R9: =SUM(N9:Q9) -> 3431471.3
C10: FTECH | D10: 20 | E10: ค่าแรงรวมงานทดสอบระบบ | F10: PM371/25 | G10: 110000 | H10: K.Kowit | I10: 45934
D11: 50 | E11: ค่าที่พักและโรงแรม | G11: =890*2 -> 1780 | H11: K.Kowit | I11: 46002
D12: 50 | E12: ค่าตั๋วเครื่องบิน | G12: 1900 | H12: K.Kowit | I12: 46002
D13: 40 | E13: ค่าเช่ารถ | G13: 1500 | H13: K.Kowit | I13: 46002
D14: 50 | E14: ค่าแรง 3 วัน | G14: 0 | H14: K.Kowit | I14: 46002
D15: 50 | E15: ค่าเดินทางไปสนามบิน ไป-กลับ | G15: 1000 | H15: K.Kowit | I15: 46002
D16: 40 | E16: ค่าน้ำมันรถใช้ในอุดร | G16: 1000 | H16: K.Kowit | I16: 46002
D17: 80 | E17: ค่าส่งเอกสาร | G17: 37 | H17: K.Kowit | I17: 46004 | J17: ต้องเบิก
C18: Pen Ake Energy Saving | D18: 90 | E18: ค่าดำเนินการ PEN EAK | G18: 22800 | H18: K.Kowit | I18: 45934
F20: TOTAL COST | G20: =SUM(G9:G18) -> 140017 | H20: จำนวนเงินหลังหักค่าใช้จ่าย | I20: =C5-G20 -> 22983
F21: BALANCE | G21: =$C$6-G20 -> 9483
I22: =50000/30 -> 1666.6667
F23: All BALANCE | G23: =G21/C6 -> 0.063431438
B25: Job. Code. | C25: ='All Job balance report'!B4 -> PEK-2500/002
B26: Contract Price | C26: ='All Job balance report'!G4 -> 163000
B27: No. | C27: Code | E27: Description | F27: Budget | G27: Expense Record | H27: Balance | I27: Remark
N28: B-A | O28: B-D | P28: ร้านกาแฟ | Q28: ร้านอาหาร
B29: 1 | C29: 10 | E29: MATERIALS | F29: 0 | G29: =SUMIF($D$10:$D$19,$C$29,$G$10:$G$19) -> 0 | H29: =F29-G29 -> 0 | N29: =1391385.86+550222.39 -> 1941608.2 | O29: 187326.21 | P29: 171283.81 | Q29: 229202.12 | R29: =SUM(N29:Q29) -> 2529420.4
B30: 2 | C30: 20 | E30: SUB CONTRACTOR | F30: 115000 | G30: =SUMIF($D$10:$D$19,$C$30,$G$10:$G$19) -> 110000 | H30: =F30-G30 -> 5000 | N30: =125499.72+40000-N33 -> 100499.72 | O30: =129657.59-O33 -> 79657.59 | P30: =119025.22-P33 -> 69025.22 | Q30: =145843.83-Q33 -> 115843.83 | R30: =SUM(N30:Q30) -> 365026.36
B31: 3 | C31: 30 | E31: HEAVY EQUIPMENT | F31: =R31 -> 0 | G31: =SUMIF($D$10:$D$19,$C$31,$G$10:$G$19) -> 0 | H31: =F31-G31 -> 0 | R31: =SUM(N31:Q31) -> 0
B32: 4 | C32: 40 | E32: RENTAL | F32: 3500 | G32: =SUMIF($D$10:$D$19,$C$32,$G$10:$G$19) -> 2500 | H32: =F32-G32 -> 1000 | R32: =SUM(N32:Q32) -> 0
B33: 5 | C33: 50 | E33: STAFF EXPENSE | F33: 11000 | G33: =SUMIF($D$10:$D$19,$C$33,$G$10:$G$19) -> 4680 | H33: =F33-G33 -> 6320 | N33: 65000 | O33: 50000 | P33: 50000 | Q33: 30000 | R33: =SUM(N33:Q33) -> 195000
B34: 6 | C34: 60 | E34: OFFICE EXPENSE | F34: 0 | G34: =SUMIF($D$10:$D$19,$C$34,$G$10:$G$19) -> 0 | H34: =F34-G34 -> 0 | R34: =SUM(N34:Q34) -> 0
B35: 7 | C35: 70 | E35: ENTERTAIN | F35: =R35 -> 0 | G35: =SUMIF($D$10:$D$19,$C$35,$G$10:$G$19) -> 0 | H35: =F35-G35 -> 0 | R35: =SUM(N35:Q35) -> 0
B36: 8 | C36: 80 | E36: MISCELLANEOUS | F36: 0 | G36: =SUMIF($D$10:$D$19,$C$36,$G$10:$G$19) -> 37 | H36: =F36-G36 -> -37 | R36: =SUM(N36:Q36) -> 0
B37: 9 | C37: 90 | E37: OTHER | F37: 20000 | G37: =SUMIF($D$10:$D$19,$C$37,$G$10:$G$19) -> 22800 | H37: =F37-G37 -> -2800 | R37: =SUM(N37:Q37) -> 0
E38: Total | F38: =SUM(F29:F37) -> 149500 | G38: =SUM(G29:G37) -> 140017 | H38: =SUM(H29:H37) -> 9483 | R38: =SUM(N38:Q38) -> 0
E39: % Profit | F39: =((C26-F38)/C26) -> 0.082822086
E40: Total Profit | F40: =F39*C26 -> 13500 | N40: =SUM(N29:N39) -> 2107108 | O40: =SUM(O29:O39) -> 316983.8 | P40: =SUM(P29:P39) -> 290309.03 | Q40: =SUM(Q29:Q39) -> 375045.95 | R40: =SUM(N40:Q40) -> 3089446.8
E41: Gross Profit | F41: =C26-G38 -> 22983
E43: ค่าแรง โกวิท | F43: =F41*0.25 -> 5745.75
D44: สัดส่วน
C45: 21226.395 | D45: 0.52 | E45: DDP
C46: 19593.595 | D46: 0.48 | E46: PEN AKE

Sheet 02 JPP-001 งานชัยนาท
B1: Factory/Company | C1: PROCHAIN | H1: Start Date | I1: 45931
B2: Project Name | C2: มาบตาพุต ร้านกาแฟ | H2: Sale Up Date | N2: B-A | O2: B-D | P2: ร้านกาแฟ | Q2: ร้านอาหาร
B3: Job Code. | C3: =C18 -> JPP-2500/001 | M3: PO No. | N3: PO6800405
B4: Quotation No. | E4: PROJECT BUDGET RECORD | H4: INVOICE (%) | I4: 0.2 | N4: PA6800158
B5: Contract Price | C5: =C19 -> 330000
B6: Budget Price | C6: =F31 -> 325000 | M6: Contract Price | N6: 2254570 | P6: 397867.06 | Q6: 513604.21
B7: PROFIT | C7: =(C5-C6)/C5 -> 0.015151515 | D7: ACTUAL | E7: 1 | N7: 265430.02
B8: No. | C8: Vendor Name | D8: Material Number | E8: Description | F8: Text/Quo.No. | G8: Amount | H8: Updated By | I8: Date
C9: SEE | D9: 20 | E9: ค่าจ้างงานพี่โจ๊ส เบิกแอดวานซ์ 20% | G9: =325000*0.2 -> 65000 | H9: K.Kowit | I9: 45936
F13: TOTAL COST | G13: =SUM(G9:G12) -> 65000
F14: BALANCE | G14: =$C$6-G13 -> 260000
F16: All BALANCE | G16: =G14/C6 -> 0.8
B18: Job. Code. | C18: ='All Job balance report'!B3 -> JPP-2500/001
B19: Contract Price | C19: ='All Job balance report'!G3 -> 330000
B20: No. | C20: Code | E20: Description | F20: Budget | G20: Expense Record | H20: Balance | I20: Remark
N21: B-A | O21: B-D | P21: ร้านกาแฟ | Q21: ร้านอาหาร
B22: 1 | C22: 10 | E22: MATERIALS | F22: 0 | G22: =SUMIF($D$9:$D$12,$C$22,$G$9:$G$12) -> 0 | H22: =F22-G22 -> 0 | N22: =1391385.86+550222.39 -> 1941608.2 | O22: 187326.21 | P22: 171283.81 | Q22: 229202.12 | R22: =SUM(N22:Q22) -> 2529420.4
B23: 2 | C23: 20 | E23: SUB CONTRACTOR | F23: 325000 | G23: 325000 | H23: =F23-G23 -> 0 | N23: =125499.72+40000-N26 -> 100499.72 | O23: =129657.59-O26 -> 79657.59 | P23: =119025.22-P26 -> 69025.22 | Q23: =145843.83-Q26 -> 115843.83 | R23: =SUM(N23:Q23) -> 365026.36
B24: 3 | C24: 30 | E24: HEAVY EQUIPMENT | F24: 0 | G24: =SUMIF($D$9:$D$12,$C$24,$G$9:$G$12) -> 0 | H24: =F24-G24 -> 0 | R24: =SUM(N24:Q24) -> 0
B25: 4 | C25: 40 | E25: RENTAL | F25: 0 | G25: =SUMIF($D$9:$D$12,$C$25,$G$9:$G$12) -> 0 | H25: =F25-G25 -> 0 | R25: =SUM(N25:Q25) -> 0
B26: 5 | C26: 50 | E26: STAFF EXPENSE | F26: 0 | G26: =SUMIF($D$9:$D$12,$C$26,$G$9:$G$12) -> 0 | H26: =F26-G26 -> 0 | N26: 65000 | O26: 50000 | P26: 50000 | Q26: 30000 | R26: =SUM(N26:Q26) -> 195000
B27: 6 | C27: 60 | E27: OFFICE EXPENSE | F27: 0 | G27: =SUMIF($D$9:$D$12,$C$27,$G$9:$G$12) -> 0 | H27: =F27-G27 -> 0 | R27: =SUM(N27:Q27) -> 0
B28: 7 | C28: 70 | E28: ENTERTAIN | F28: 0 | G28: =SUMIF($D$9:$D$12,$C$28,$G$9:$G$12) -> 0 | H28: =F28-G28 -> 0 | R28: =SUM(N28:Q28) -> 0
B29: 8 | C29: 80 | E29: MISCELLANEOUS | F29: 0 | G29: =SUMIF($D$9:$D$12,$C$29,$G$9:$G$12) -> 0 | H29: =F29-G29 -> 0 | R29: =SUM(N29:Q29) -> 0
B30: 9 | C30: 90 | E30: OTHER | F30: 0 | G30: =SUMIF($D$9:$D$12,$C$30,$G$9:$G$12) -> 0 | H30: =F30-G30 -> 0 | R30: =SUM(N30:Q30) -> 0
E31: Total | F31: =SUM(F22:F30) -> 325000 | G31: =SUM(G22:G30) -> 325000 | H31: =SUM(H22:H30) -> 0 | R31: =SUM(N31:Q31) -> 0
E32: % Profit | F32: =((C19-F31)/C19) -> 0.015151515
E33: Total Profit | F33: =F32*C19 -> 5000 | N33: =SUM(N22:N32) -> 2107108 | O33: =SUM(O22:O32) -> 316983.8 | P33: =SUM(P22:P32) -> 290309.03 | Q33: =SUM(Q22:Q32) -> 375045.95 | R33: =SUM(N33:Q33) -> 3089446.8
E34: Gross Profit | F34: =C19-G31 -> 5000
E36: ค่าแรง โกวิท | F36: =F34*0.25 -> 1250

Sheet 01 PEK-001 Pen Eak
B1: Factory/Company | C1: ='All Job balance report'!D2 -> บริษัท เป็นเอก เอ็นเนอร์จี เซฟวิ่ง จำกัด | H1: Start Date | I1: 45934
B2: Project Name | C2: ='All Job balance report'!F2 -> เปลี่ยนหลอดไฟไฮเบย์ CP Warehouse | H2: Sale Up Date
B3: Job Code. | C3: =C30 -> PEK-2500/001
B4: Quotation No. | E4: PROJECT BUDGET RECORD | H4: INVOICE (%) | I4: 0.3
B5: Contract Price | C5: =C31 -> 66000
B6: Budget Price | C6: =F43 -> 58500
B7: PROFIT | C7: =(C5-C6)/C5 -> 0.11363636 | D7: ACTUAL | E7: 1
B8: No. | C8: Vendor Name | D8: Material Number | E8: Description | F8: Text/Quo.No. | G8: Amount | H8: Updated By | I8: Date
C10: บริษัท เอสซีซี เอ็นจิเนียริ่ง จำกัด | D10: 10 | E10: สายไฟ VCT3C-1.5 IEC01 2.5 | F10: DU DEE68-01 | G10: 5667 | H10: K.Kowit | I10: 45934
C11: บริษัท ไทยคิน สตีล (ประเทศไทย) จำกัด | D11: 10 | E11: อายโบลต์ โซ่เหล็ก 1/4" | F11: QT0038726 | G11: 3600 | H11: K.Kowit | I11: 45934
C12: บริษัท เอสเอสไอ เทคโนโลยี จำกัด | D12: 10 | E12: แคมป์บีม | G12: 8550 | H12: K.Kowit | I12: 45934
C13: บริษัท ซีอาร์ซี ไทยวัสดุ จำกัด | D13: 10 | E13: ค่าคอนเนคเตอร์ ท่ออ่อนเหล็ก | G13: 765 | H13: K.Kowit | I13: 45937
C14: บริษัท ซีอาร์ซี ไทยวัสดุ จำกัด | D14: 10 | E14: ท่ออ่อนเหล็ก เคเบิ้ลไท ฮุกสำหรับเซฟตี้เบลต์ | G14: 3096 | H14: K.Kowit | I14: 45937
C15: บริษัท สมาร์ท เบลส์บายส์ จำกัด (สำนักงานใหญ่) | D15: 10 | E15: เข็มขัดเซฟตี้ แบบเต็มตัว 2 ชุด | G15: 1819 | H15: K.Kowit | I15: 45937
C16: ค่าน้ำมันรถ | D16: 90 | E16: แก๊ส LPG | F16: ต้องทำเบิก | G16: 365 | H16: K.Kowit | I16: 45937
C17: ค่าน้ำมันรถ | D17: 90 | E17: แก๊ส LPG | F17: ต้องทำเบิก | G17: 392 | H17: K.Kowit | I17: 45937
C18: ค่าน้ำมันรถ | D18: 90 | E18: แก๊ส LPG | F18: ต้องทำเบิก | G18: 380 | H18: K.Kowit | I18: 45937
C19: ค่าของ | D19: 10 | E19: ค่าของงานหลอดไฟ T8 | G19: 1568.64 | H19: K.Kowit | I19: 45938
C20: ค่าขนส่ง | D20: 90 | E20: ค่าขนส่ง ลาล่ามูฟ | F20: ต้องทำเบิก | G20: 300 | H20: K.Kowit | I20: 45938
C21: ค่าแรงช่างขอเพิ่ม | D21: 20 | E21: ค่าแรงงานติตดั้ง | G21: 2500 | H21: K.Kowit | I21: 45938
C22: ค่าจ้างแรงงานช่างอาร์ม | D22: 20 | E22: ค่าแรงงานติตดั้ง | G22: 32300 | H22: K.Kowit | I22: จ่ายแล้ว 3300+5000
C23: ค่าทางด่วน | D23: 50 | E23: ค่าทางด่วน | F23: ต้องทำเบิก | G23: 350 | H23: K.Kowit | I23: 45940
C24: ค่าขนส่ง | D24: 90 | E24: ค่าขนส่ง ลาล่ามูฟ | F24: ต้องทำเบิก | G24: 506 | H24: K.Kowit | I24: 45940
F25: TOTAL COST | G25: =SUM(G9:G24) -> 62158.64
F26: BALANCE | G26: =$C$6-G25 -> -3658.64
F27: Contract | G27: 66000
F28: All BALANCE | G28: =G26/C6 -> -0.062540855
B30: Job. Code. | C30: ='All Job balance report'!B2 -> PEK-2500/001
B31: Contract Price | C31: ='All Job balance report'!G2 -> 66000
B32: No. | C32: Code | E32: Description | F32: Budget | G32: Expense Record | H32: Balance | I32: Remark
B34: 1 | C34: 10 | E34: MATERIALS | F34: 23000 | G34: =SUMIF($D$10:$D$24,$C$34,$G$10:$G$24) -> 25065.64 | H34: =F34-G34 -> -2065.64
B35: 2 | C35: 20 | E35: SUB CONTRACTOR | F35: 33000 | G35: =SUMIF($D$10:$D$24,$C$35,$G$10:$G$24) -> 34800 | H35: =F35-G35 -> -1800
B36: 3 | C36: 30 | E36: HEAVY EQUIPMENT | F36: 0 | G36: =SUMIF($D$10:$D$24,$C$36,$G$10:$G$24) -> 0 | H36: =F36-G36 -> 0
B37: 4 | C37: 40 | E37: RENTAL | F37: 0 | G37: =SUMIF($D$10:$D$24,$C$37,$G$10:$G$24) -> 0 | H37: =F37-G37 -> 0
B38: 5 | C38: 50 | E38: STAFF EXPENSE | F38: 2500 | G38: =SUMIF($D$10:$D$24,$C$38,$G$10:$G$24) -> 350 | H38: =F38-G38 -> 2150
B39: 6 | C39: 60 | E39: OFFICE EXPENSE | F39: 0 | G39: =SUMIF($D$10:$D$24,$C$39,$G$10:$G$24) -> 0 | H39: =F39-G39 -> 0
B40: 7 | C40: 70 | E40: ENTERTAIN | F40: 0 | G40: =SUMIF($D$10:$D$24,$C$40,$G$10:$G$24) -> 0 | H40: =F40-G40 -> 0
B41: 8 | C41: 80 | E41: MISCELLANEOUS | F41: 0 | G41: =SUMIF($D$10:$D$24,$C$41,$G$10:$G$24) -> 0 | H41: =F41-G41 -> 0
B42: 9 | C42: 90 | E42: OTHER | F42: 0 | G42: =SUMIF($D$10:$D$24,$C$42,$G$10:$G$24) -> 1943 | H42: =F42-G42 -> -1943
E43: Total | F43: =SUM(F34:F42) -> 58500 | G43: =SUM(G34:G42) -> 62158.64 | H43: =SUM(H34:H42) -> -3658.64
E44: % Profit | F44: =((C31-F43)/C31) -> 0.11363636
E45: Total Profit | F45: =F44*C31 -> 7500
E46: Gross Profit | F46: =C31-G43 -> 3841.36
E48: ค่าแรง โกวิท | F48: =F46*0.25 -> 960.34
